{
  "filters": {
    "10": [
      {
        "key": "sort",
        "name": "排序",
        "init": "latest",
        "value": [
          {
            "n": "最新",
            "v": "latest"
          },
          {
            "n": "高清优先",
            "v": "quality"
          },
          {
            "n": "多线路优先",
            "v": "lines"
          },
          {
            "n": "片名排序",
            "v": "name"
          }
        ]
      },
      {
        "key": "year",
        "name": "年份",
        "init": "",
        "value": [
          {
            "n": "全部",
            "v": ""
          },
          {
            "n": "2030",
            "v": "2030"
          },
          {
            "n": "2028",
            "v": "2028"
          },
          {
            "n": "2027",
            "v": "2027"
          },
          {
            "n": "2026",
            "v": "2026"
          },
          {
            "n": "2025",
            "v": "2025"
          },
          {
            "n": "2020-2022",
            "v": "2020-2022"
          },
          {
            "n": "2010年代",
            "v": "2010s"
          },
          {
            "n": "更早",
            "v": "older"
          }
        ]
      },
      {
        "key": "area",
        "name": "地区",
        "init": "",
        "value": [
          {
            "n": "全部",
            "v": ""
          },
          {
            "n": "大陆",
            "v": "大陆"
          },
          {
            "n": "港台",
            "v": "港台"
          },
          {
            "n": "日韩",
            "v": "日韩"
          },
          {
            "n": "欧美",
            "v": "欧美"
          },
          {
            "n": "泰国",
            "v": "泰国"
          }
        ]
      },
      {
        "key": "class",
        "name": "类型",
        "init": "",
        "value": [
          {
            "n": "全部",
            "v": ""
          },
          {
            "n": "动作",
            "v": "动作"
          },
          {
            "n": "喜剧",
            "v": "喜剧"
          },
          {
            "n": "爱情",
            "v": "爱情"
          },
          {
            "n": "悬疑犯罪",
            "v": "悬疑犯罪"
          },
          {
            "n": "科幻奇幻",
            "v": "科幻奇幻"
          },
          {
            "n": "恐怖惊悚",
            "v": "恐怖惊悚"
          },
          {
            "n": "剧情",
            "v": "剧情"
          },
          {
            "n": "战争历史",
            "v": "战争历史"
          }
        ]
      },
      {
        "key": "form",
        "name": "内容形态",
        "init": "",
        "value": [
          {
            "n": "全部",
            "v": ""
          },
          {
            "n": "正片",
            "v": "正片"
          },
          {
            "n": "解说",
            "v": "解说"
          },
          {
            "n": "合集",
            "v": "合集"
          },
          {
            "n": "现场",
            "v": "现场"
          },
          {
            "n": "课程",
            "v": "课程"
          },
          {
            "n": "片段",
            "v": "片段"
          }
        ]
      },
      {
        "key": "quality",
        "name": "清晰度",
        "init": "",
        "value": [
          {
            "n": "全部",
            "v": ""
          },
          {
            "n": "高清",
            "v": "hd"
          },
          {
            "n": "4K",
            "v": "4K"
          },
          {
            "n": "正片",
            "v": "正片"
          },
          {
            "n": "抢先",
            "v": "抢先"
          }
        ]
      }
    ]
  },
  "code": 1,
  "msg": "ok",
  "page": 13,
  "pagecount": 13,
  "limit": 24,
  "total": 292,
  "class": [
    {
      "type_id": "0",
      "type_name": "推荐",
      "key": "recommend"
    },
    {
      "type_id": "10",
      "type_name": "院线电影",
      "key": "theatrical_movie"
    },
    {
      "type_id": "11",
      "type_name": "网络电影",
      "key": "web_movie"
    },
    {
      "type_id": "12",
      "type_name": "其他电影",
      "key": "other_movie"
    },
    {
      "type_id": "20",
      "type_name": "电视剧",
      "key": "tv_series"
    },
    {
      "type_id": "21",
      "type_name": "网络剧",
      "key": "web_series"
    },
    {
      "type_id": "6",
      "type_name": "网络短剧",
      "key": "web_short"
    },
    {
      "type_id": "3",
      "type_name": "综艺",
      "key": "variety"
    },
    {
      "type_id": "4",
      "type_name": "动漫",
      "key": "anime"
    },
    {
      "type_id": "5",
      "type_name": "纪录片",
      "key": "documentary"
    },
    {
      "type_id": "7",
      "type_name": "解说",
      "key": "explainer"
    },
    {
      "type_id": "8",
      "type_name": "文娱知识",
      "key": "knowledge"
    },
    {
      "type_id": "9",
      "type_name": "成人伦理",
      "key": "adult"
    }
  ],
  "list": [
    {
      "vod_id": "agg_W3sicyI6ImJmenkiLCJpZCI6Ijk5MTI3In1d",
      "type_id": "21",
      "type_id_1": 20,
      "group_id": 0,
      "vod_name": "绿色骑士",
      "vod_sub": "勇者之剑  绿衣骑士Sword",
      "vod_en": "lvseqishi",
      "vod_status": 1,
      "vod_letter": "L",
      "vod_color": "",
      "vod_tag": "",
      "vod_class": "动作",
      "vod_pic": "https://img.picbf.com/upload/vod/20250824-1/d37afa1f249d79b8b956f8d5de9249ba.webp",
      "vod_pic_thumb": "",
      "vod_pic_slide": "",
      "vod_pic_screenshot": "",
      "vod_actor": "迈尔斯·欧科飞,谢丽埃勒·克莱尔,利·劳森,肖恩·康纳利,特瑞沃·霍华德,彼得·库欣,罗纳德·莱西,丽拉·柯卓娃,约翰·瑞斯-戴维斯,威尔弗里德·布兰贝尔,布鲁斯·利丁顿,道格拉斯·威尔默,布莱恩·科伯恩,大卫·拉帕波特,Emma Burdon-Sutton",
      "vod_director": "斯蒂芬·威克斯",
      "vod_writer": "斯蒂芬·威克斯Howard C. PenPhilip M. Breen",
      "vod_behind": "",
      "vod_blurb": "Gawain was a squire in King Arthur&amp;#039;s court when the Green Knight burst in and offered to play a game with a brave knight. No knights stand to defend their king&amp;#039;s honor. Except for the valiant Gawain. After being quickly knighted Gawain p",
      "vod_remarks": "更新至高清",
      "vod_pubdate": "",
      "vod_total": "0",
      "vod_serial": "0",
      "vod_tv": "",
      "vod_weekday": "",
      "vod_area": "英国",
      "vod_lang": "英语",
      "vod_year": "1984",
      "vod_version": "高清",
      "vod_state": "",
      "vod_author": "",
      "vod_jumpurl": "",
      "vod_tpl": "",
      "vod_tpl_play": "",
      "vod_tpl_down": "",
      "vod_isend": 0,
      "vod_lock": 0,
      "vod_level": 0,
      "vod_copyright": 0,
      "vod_points": 0,
      "vod_points_play": 0,
      "vod_points_down": 0,
      "vod_hits": 726,
      "vod_hits_day": 592,
      "vod_hits_week": 105,
      "vod_hits_month": 456,
      "vod_duration": "USA: 102 分",
      "vod_up": 364,
      "vod_down": 592,
      "vod_score": "10.0",
      "vod_score_all": 5840,
      "vod_score_num": 584,
      "vod_time": "2026-07-15 01:00:15",
      "vod_time_add": "1756046191",
      "vod_time_hits": 0,
      "vod_time_make": 0,
      "vod_trysee": 0,
      "vod_douban_id": 1763316,
      "vod_douban_score": "0.0",
      "vod_reurl": "",
      "vod_rel_vod": "",
      "vod_rel_art": "",
      "vod_pwd": "",
      "vod_pwd_url": "",
      "vod_pwd_play": "",
      "vod_pwd_play_url": "",
      "vod_pwd_down": "",
      "vod_pwd_down_url": "",
      "vod_content": "Gawain was a squire in King Arthur's court when the Green Knight burst in and offered to play a game with a brave knight. No knights stand to defend their king's honor. Except for the valiant Gawain. After being quickly knighted Gawain plays the game, but learns that it's all a trick, and he has lost. But the Green Knight shows mercy, letting Gawain grow a year older before hav...",
      "vod_play_from": "bfzym3u8",
      "vod_play_server": "",
      "vod_play_note": "",
      "vod_play_url": "高清$https://v.fengbao8.com/video/lvseqishi/高清/index.m3u8",
      "vod_down_from": "",
      "vod_down_server": "",
      "vod_down_note": "",
      "vod_down_url": "",
      "vod_plot": 0,
      "vod_plot_name": "",
      "vod_plot_detail": "",
      "type_name": "动作片",
      "source_category_id": "10",
      "source_category_name": "动作片",
      "_sourceSlug": "bfzy",
      "_sourceShort": "暴风",
      "source_url": "https://bfzyapi.com/api.php/provide/vod/",
      "canonical_id": "ext:douban:1763316",
      "primary_category": "theatrical_movie",
      "movie_release_channel": "theatrical",
      "classification_evidence": [
        {
          "source": "source_category_id",
          "priority": 1,
          "category": "theatrical_movie",
          "field": "source_category_id",
          "value": "10",
          "signal": "theatrical_movie"
        }
      ],
      "classification_confidence": 0.99,
      "classification_confidence_level": "high",
      "classification_confidence_score": 0.99,
      "source_candidates": [
        {
          "source": "bfzy",
          "id": "99127",
          "url": "https://bfzyapi.com/api.php/provide/vod/",
          "updated_at": ""
        }
      ],
      "play_lines": [
        {
          "source": "bfzy",
          "name": "bfzym3u8",
          "url": "高清$https://v.fengbao8.com/video/lvseqishi/高清/index.m3u8"
        }
      ],
      "douban_id": "1763316",
      "explicit_tags": [
        "院线电影"
      ],
      "release_channel": "theatrical",
      "external_release_metadata": {
        "id": "1763316",
        "title": "绿色骑士",
        "original_title": "Sword of the Valiant: The Legend of Sir Gawain and the Green Knight",
        "subtype": "movie",
        "is_tv": false,
        "pubdate": [
          "1984-11-09(英国)"
        ],
        "release_date": [],
        "pre_release_desc": "",
        "year": "1984"
      },
      "semantic_tags": "area 欧美 地区",
      "snapshot_filter_evidence": "catalog-derived"
    },
    {
      "vod_id": "agg_W3sicyI6ImJmenkiLCJpZCI6Ijk5OTEwIn1d",
      "type_id": "22",
      "type_id_1": 20,
      "group_id": 0,
      "vod_name": "做贼抓贼",
      "vod_sub": "",
      "vod_en": "zuozeizhuazei",
      "vod_status": 1,
      "vod_letter": "Z",
      "vod_color": "",
      "vod_tag": "",
      "vod_class": "喜剧",
      "vod_pic": "https://img.picbf.com/upload/vod/20250904-1/774b4808a46b184a5ebb7a96c40f2807.webp",
      "vod_pic_thumb": "",
      "vod_pic_slide": "",
      "vod_pic_screenshot": "",
      "vod_actor": "Peter Sellers,Lionel Jeffries,Bernard Cribbins,Davy Kaye,Nanette Newman,Bill Kerr",
      "vod_director": "Cliff Owen",
      "vod_writer": "",
      "vod_behind": "",
      "vod_blurb": "The crooks in London know how it works. No one carries guns and no one resists the police. Then a new gang appears that go one better. They dress as police and steal from the crooks. This upset&amp;#039;s the natural order of the policecriminal relationsh",
      "vod_remarks": "更新至高清",
      "vod_pubdate": "",
      "vod_total": "0",
      "vod_serial": "0",
      "vod_tv": "",
      "vod_weekday": "",
      "vod_area": "英国",
      "vod_lang": "英语",
      "vod_year": "1963",
      "vod_version": "高清",
      "vod_state": "",
      "vod_author": "",
      "vod_jumpurl": "",
      "vod_tpl": "",
      "vod_tpl_play": "",
      "vod_tpl_down": "",
      "vod_isend": 0,
      "vod_lock": 0,
      "vod_level": 0,
      "vod_copyright": 0,
      "vod_points": 0,
      "vod_points_play": 0,
      "vod_points_down": 0,
      "vod_hits": 503,
      "vod_hits_day": 846,
      "vod_hits_week": 990,
      "vod_hits_month": 927,
      "vod_duration": "94 分钟",
      "vod_up": 334,
      "vod_down": 288,
      "vod_score": "2.0",
      "vod_score_all": 250,
      "vod_score_num": 125,
      "vod_time": "2026-07-15 01:00:13",
      "vod_time_add": "1756998970",
      "vod_time_hits": 0,
      "vod_time_make": 0,
      "vod_trysee": 0,
      "vod_douban_id": 3113136,
      "vod_douban_score": "0.0",
      "vod_reurl": "",
      "vod_rel_vod": "",
      "vod_rel_art": "",
      "vod_pwd": "",
      "vod_pwd_url": "",
      "vod_pwd_play": "",
      "vod_pwd_play_url": "",
      "vod_pwd_down": "",
      "vod_pwd_down_url": "",
      "vod_content": "The crooks in London know how it works. No one carries guns and no one resists the police. Then a new gang appears that go one better. They dress as police and steal from the crooks. This upset's the natural order of the policecriminal relationship and the police and the crooks join forces to catch the IPOs (Impersonating Police Officers), including an armored car robbery in w...",
      "vod_play_from": "bfzym3u8",
      "vod_play_server": "",
      "vod_play_note": "",
      "vod_play_url": "高清$https://v.fengbao8.com/video/zuozeizhuazei/高清/index.m3u8",
      "vod_down_from": "",
      "vod_down_server": "",
      "vod_down_note": "",
      "vod_down_url": "",
      "vod_plot": 0,
      "vod_plot_name": "",
      "vod_plot_detail": "",
      "type_name": "喜剧片",
      "source_category_id": "10",
      "source_category_name": "喜剧片",
      "_sourceSlug": "bfzy",
      "_sourceShort": "暴风",
      "source_url": "https://bfzyapi.com/api.php/provide/vod/",
      "canonical_id": "ext:douban:3113136",
      "primary_category": "theatrical_movie",
      "movie_release_channel": "theatrical",
      "classification_evidence": [
        {
          "source": "source_category_id",
          "priority": 1,
          "category": "theatrical_movie",
          "field": "source_category_id",
          "value": "10",
          "signal": "theatrical_movie"
        }
      ],
      "classification_confidence": 0.99,
      "classification_confidence_level": "high",
      "classification_confidence_score": 0.99,
      "source_candidates": [
        {
          "source": "bfzy",
          "id": "99910",
          "url": "https://bfzyapi.com/api.php/provide/vod/",
          "updated_at": ""
        }
      ],
      "play_lines": [
        {
          "source": "bfzy",
          "name": "bfzym3u8",
          "url": "高清$https://v.fengbao8.com/video/zuozeizhuazei/高清/index.m3u8"
        }
      ],
      "douban_id": "3113136",
      "explicit_tags": [
        "院线电影"
      ],
      "release_channel": "theatrical",
      "external_release_metadata": {
        "id": "3113136",
        "title": "做贼抓贼",
        "original_title": "The Wrong Arm of the Law",
        "subtype": "movie",
        "is_tv": false,
        "pubdate": [
          "1963-04-02"
        ],
        "release_date": [],
        "pre_release_desc": "",
        "year": "1963"
      },
      "semantic_tags": "area 欧美 地区",
      "snapshot_filter_evidence": "catalog-derived"
    },
    {
      "vod_id": "agg_W3sicyI6ImJmenkiLCJpZCI6Ijk2MzMwIn1d",
      "type_id": "26",
      "type_id_1": 20,
      "group_id": 0,
      "vod_name": "十二怒汉",
      "vod_sub": "12怒汉12",
      "vod_en": "shiernuhan",
      "vod_status": 1,
      "vod_letter": "S",
      "vod_color": "",
      "vod_tag": "",
      "vod_class": "剧情",
      "vod_pic": "https://img.picbf.com/upload/vod/20250709-1/cd828b8f53e1247257b192d414704b6f.webp",
      "vod_pic_thumb": "",
      "vod_pic_slide": "",
      "vod_pic_screenshot": "",
      "vod_actor": "亨利·方达,马丁·鲍尔萨姆,约翰·菲德勒,李·科布,E.G.马绍尔,杰克·克卢格曼,爱德华·宾斯,杰克·沃登,约瑟夫·史威尼,埃德·贝格利,乔治·沃斯科维奇,罗伯特·韦伯",
      "vod_director": "西德尼·吕美特",
      "vod_writer": "雷金纳德·罗斯",
      "vod_behind": "",
      "vod_blurb": "一个在贫民窟长大的18岁少年因为涉嫌杀害自己的父亲被告上法庭，证人言之凿凿，各方面的证据都对他极为不利。十二个不同职业的人组成了这个案件的陪审团，他们要在休息室达成一致的意见，裁定少年是否有罪，如果罪名成立，少年将会被判处死刑。                                                                    　　十二个陪审团成员各有不同，除了8号陪审员（H enry Fonda 饰）之外，其他人对这个犯罪事实如此清晰的案子不屑一顾，还没有开始讨论就",
      "vod_remarks": "更新至高清",
      "vod_pubdate": "",
      "vod_total": "0",
      "vod_serial": "0",
      "vod_tv": "",
      "vod_weekday": "",
      "vod_area": "美国",
      "vod_lang": "英语",
      "vod_year": "1957",
      "vod_version": "高清",
      "vod_state": "",
      "vod_author": "",
      "vod_jumpurl": "",
      "vod_tpl": "",
      "vod_tpl_play": "",
      "vod_tpl_down": "",
      "vod_isend": 0,
      "vod_lock": 0,
      "vod_level": 0,
      "vod_copyright": 0,
      "vod_points": 0,
      "vod_points_play": 0,
      "vod_points_down": 0,
      "vod_hits": 238,
      "vod_hits_day": 751,
      "vod_hits_week": 708,
      "vod_hits_month": 206,
      "vod_duration": "96分钟",
      "vod_up": 355,
      "vod_down": 275,
      "vod_score": "1.0",
      "vod_score_all": 650,
      "vod_score_num": 650,
      "vod_time": "2026-07-14 19:05:53",
      "vod_time_add": "1752048258",
      "vod_time_hits": 0,
      "vod_time_make": 0,
      "vod_trysee": 0,
      "vod_douban_id": 1293182,
      "vod_douban_score": "9.4",
      "vod_reurl": "",
      "vod_rel_vod": "",
      "vod_rel_art": "",
      "vod_pwd": "",
      "vod_pwd_url": "",
      "vod_pwd_play": "",
      "vod_pwd_play_url": "",
      "vod_pwd_down": "",
      "vod_pwd_down_url": "",
      "vod_content": "一个在贫民窟长大的18岁少年因为涉嫌杀害自己的父亲被告上法庭，证人言之凿凿，各方面的证据都对他极为不利。十二个不同职业的人组成了这个案件的陪审团，他们要在休息室达成一致的意见，裁定少年是否有罪，如果罪名成立，少年将会被判处死刑。                                                                    　　十二个陪审团成员各有不同，除了8号陪审员（H enry Fonda 饰）之外，其他人对这个犯罪事实如此清晰的案子不屑一顾，还没有开始讨论就认定了少年有罪。8号陪审员提出了自己的“合理疑点”，耐心地说服其他的陪审员，在这个过程中，他们每个人不同的人生观也在冲突和较量……",
      "vod_play_from": "bfzym3u8",
      "vod_play_server": "",
      "vod_play_note": "",
      "vod_play_url": "高清$https://v.fengbao8.com/video/shiernuhan/高清/index.m3u8",
      "vod_down_from": "",
      "vod_down_server": "",
      "vod_down_note": "",
      "vod_down_url": "",
      "vod_plot": 0,
      "vod_plot_name": "",
      "vod_plot_detail": "",
      "type_name": "剧情片",
      "source_category_id": "10",
      "source_category_name": "剧情片",
      "_sourceSlug": "bfzy",
      "_sourceShort": "暴风",
      "source_url": "https://bfzyapi.com/api.php/provide/vod/",
      "canonical_id": "ext:douban:1293182",
      "primary_category": "theatrical_movie",
      "movie_release_channel": "theatrical",
      "classification_evidence": [
        {
          "source": "source_category_id",
          "priority": 1,
          "category": "theatrical_movie",
          "field": "source_category_id",
          "value": "10",
          "signal": "theatrical_movie"
        }
      ],
      "classification_confidence": 0.99,
      "classification_confidence_level": "high",
      "classification_confidence_score": 0.99,
      "source_candidates": [
        {
          "source": "bfzy",
          "id": "96330",
          "url": "https://bfzyapi.com/api.php/provide/vod/",
          "updated_at": ""
        }
      ],
      "play_lines": [
        {
          "source": "bfzy",
          "name": "bfzym3u8",
          "url": "高清$https://v.fengbao8.com/video/shiernuhan/高清/index.m3u8"
        }
      ],
      "douban_id": "1293182",
      "explicit_tags": [
        "院线电影"
      ],
      "release_channel": "theatrical",
      "external_release_metadata": {
        "id": "1293182",
        "title": "十二怒汉",
        "original_title": "12 Angry Men",
        "subtype": "movie",
        "is_tv": false,
        "pubdate": [
          "1957-04-10(美国)"
        ],
        "release_date": [],
        "pre_release_desc": "",
        "year": "1957"
      },
      "semantic_tags": "area 欧美 地区",
      "snapshot_filter_evidence": "catalog-derived"
    },
    {
      "vod_id": "agg_W3sicyI6Imd1YW5nc3UiLCJpZCI6IjE2ODAxMyJ9LHsicyI6ImhoenkiLCJpZCI6IjEzNTc3MiJ9LHsicyI6ImhvbmduaXUiLCJpZCI6IjE0OTMwOSJ9LHsicyI6Imh1eWEiLCJpZCI6IjExMTEwOSJ9LHsicyI6InhpbmxhbmciLCJpZCI6IjE2NTYyOSJ9XQ",
      "type_id": "14",
      "type_id_1": 2,
      "group_id": 0,
      "vod_name": "吉尔达",
      "vod_sub": "Gilda",
      "vod_en": "jierda",
      "vod_status": 1,
      "vod_letter": "J",
      "vod_color": "",
      "vod_tag": "剧情,爱情,惊悚,黑色电影",
      "vod_class": "剧情,爱情,惊悚,黑色电影,剧情片",
      "vod_pic": "https://hhmage.com/cover/a14ae8fb56ac0d41718d8f0d2805ef4e.jpg",
      "vod_pic_thumb": "",
      "vod_pic_slide": "",
      "vod_pic_screenshot": null,
      "vod_actor": "丽塔·海华斯,格伦·福特,乔治·麦克雷迪,约瑟夫·卡利亚,史蒂文·杰雷,乔·索耶,杰拉德",
      "vod_director": "查尔斯·维多",
      "vod_writer": "",
      "vod_behind": "",
      "vod_blurb": "老千约翰尼·法雷尔（格伦·福特 饰）来到阿根廷的首夜就遭遇了抢劫，幸而赌场老板巴林·蒙德森（乔治·麦克雷迪 饰）出手相救。约翰尼毛遂自荐为巴林工作，并从打手做到了经理。巴林旅行归来已为人夫，其妻吉尔达",
      "vod_remarks": "正片",
      "vod_pubdate": "1946-03-15",
      "vod_total": "1",
      "vod_serial": "0",
      "vod_tv": "",
      "vod_weekday": "",
      "vod_area": "美国",
      "vod_lang": "英语",
      "vod_year": "1946",
      "vod_version": "",
      "vod_state": "",
      "vod_author": "",
      "vod_jumpurl": "",
      "vod_tpl": "",
      "vod_tpl_play": "",
      "vod_tpl_down": "",
      "vod_isend": 1,
      "vod_lock": 0,
      "vod_level": 0,
      "vod_copyright": 0,
      "vod_points": 0,
      "vod_points_play": 0,
      "vod_points_down": 0,
      "vod_hits": 574,
      "vod_hits_day": 689,
      "vod_hits_week": 712,
      "vod_hits_month": 110,
      "vod_duration": "",
      "vod_up": 274,
      "vod_down": 387,
      "vod_score": "2.0",
      "vod_score_all": 520,
      "vod_score_num": 260,
      "vod_time": "2026-06-18 23:48:01",
      "vod_time_add": "1781797681",
      "vod_time_hits": 0,
      "vod_time_make": 0,
      "vod_trysee": 0,
      "vod_douban_id": 1301978,
      "vod_douban_score": "7.3",
      "vod_reurl": "",
      "vod_rel_vod": "",
      "vod_rel_art": "",
      "vod_pwd": "",
      "vod_pwd_url": "",
      "vod_pwd_play": "",
      "vod_pwd_play_url": "",
      "vod_pwd_down": "",
      "vod_pwd_down_url": "",
      "vod_content": "老千约翰尼·法雷尔（格伦·福特 饰）来到阿根廷的首夜就遭遇了抢劫，幸而赌场老板巴林·蒙德森（乔治·麦克雷迪 饰）出手相救。约翰尼毛遂自荐为巴林工作，并从打手做到了经理。巴林旅行归来已为人夫，其妻吉尔达（丽塔·海沃思 饰）竟是约翰尼前女友……",
      "vod_play_from": "hhyun$$$hhm3u8",
      "vod_play_server": "$$$",
      "vod_play_note": "$$$",
      "vod_play_url": "正片$https://play.hhuus.com/play/dwp0qome$$$正片$https://play.hhuus.com/play/dwp0qome/index.m3u8",
      "vod_down_from": "",
      "vod_down_server": "",
      "vod_down_note": "",
      "vod_down_url": "",
      "vod_plot": 0,
      "vod_plot_name": "",
      "vod_plot_detail": "",
      "type_name": "剧情片",
      "source_category_id": "10",
      "source_category_name": "剧情片",
      "_sourceSlug": "huya",
      "_sourceShort": "虎牙",
      "source_url": "https://www.huyaapi.com/api.php/provide/vod/from/hym3u8/",
      "canonical_id": "ext:douban:1301978",
      "primary_category": "theatrical_movie",
      "movie_release_channel": "theatrical",
      "classification_evidence": [
        {
          "source": "source_category_id",
          "priority": 1,
          "category": "theatrical_movie",
          "field": "source_category_id",
          "value": "10",
          "signal": "theatrical_movie"
        }
      ],
      "classification_confidence": 0.99,
      "classification_confidence_level": "high",
      "classification_confidence_score": 0.99,
      "source_candidates": [
        {
          "source": "huya",
          "id": "111109",
          "url": "https://www.huyaapi.com/api.php/provide/vod/from/hym3u8/",
          "updated_at": ""
        },
        {
          "source": "hhzy",
          "id": "135772",
          "url": "https://hhzyapi.com/api.php/provide/vod/",
          "updated_at": ""
        },
        {
          "source": "hongniu",
          "id": "149309",
          "url": "https://www.hongniuzy2.com/api.php/provide/vod/",
          "updated_at": ""
        },
        {
          "source": "guangsu",
          "id": "168013",
          "url": "https://api.guangsuapi.com/api.php/provide/vod/",
          "updated_at": ""
        },
        {
          "source": "xinlang",
          "id": "165629",
          "url": "https://api.xinlangapi.com/xinlangapi.php/provide/vod/",
          "updated_at": ""
        }
      ],
      "play_lines": [
        {
          "source": "huya",
          "name": "hym3u8",
          "url": "正片$https://1080p.huyall.com/play/av2Qpnga/index.m3u8"
        },
        {
          "source": "huya",
          "name": "hhyun",
          "url": "正片$https://play.hhuus.com/play/dwp0qome"
        },
        {
          "source": "huya",
          "name": "hhm3u8",
          "url": "正片$https://play.hhuus.com/play/dwp0qome/index.m3u8"
        },
        {
          "source": "hhzy",
          "name": "hhyun",
          "url": "正片$https://play.hhuus.com/play/dwp0qome"
        },
        {
          "source": "hhzy",
          "name": "hhm3u8",
          "url": "正片$https://play.hhuus.com/play/dwp0qome/index.m3u8"
        },
        {
          "source": "hongniu",
          "name": "hnyun",
          "url": "正片$https://hn.bfvvs.com/play/epYZjJra"
        },
        {
          "source": "hongniu",
          "name": "hnm3u8",
          "url": "正片$https://hn.bfvvs.com/play/epYZjJra/index.m3u8"
        },
        {
          "source": "hongniu",
          "name": "hhyun",
          "url": "正片$https://play.hhuus.com/play/dwp0qome"
        },
        {
          "source": "hongniu",
          "name": "hhm3u8",
          "url": "正片$https://play.hhuus.com/play/dwp0qome/index.m3u8"
        },
        {
          "source": "guangsu",
          "name": "gsyun",
          "url": "正片$https://v.gsuus.com/play/bqxQkgRa"
        },
        {
          "source": "guangsu",
          "name": "gsm3u8",
          "url": "正片$https://v.gsuus.com/play/bqxQkgRa/index.m3u8"
        },
        {
          "source": "guangsu",
          "name": "hhyun",
          "url": "正片$https://play.hhuus.com/play/dwp0qome"
        },
        {
          "source": "guangsu",
          "name": "hhm3u8",
          "url": "正片$https://play.hhuus.com/play/dwp0qome/index.m3u8"
        },
        {
          "source": "xinlang",
          "name": "xlyun",
          "url": "正片$https://play.xluuss.com/play/erk2ljka"
        },
        {
          "source": "xinlang",
          "name": "xlm3u8",
          "url": "正片$https://play.xluuss.com/play/erk2ljka/index.m3u8"
        },
        {
          "source": "xinlang",
          "name": "hhyun",
          "url": "正片$https://play.hhuus.com/play/dwp0qome"
        },
        {
          "source": "xinlang",
          "name": "hhm3u8",
          "url": "正片$https://play.hhuus.com/play/dwp0qome/index.m3u8"
        }
      ],
      "douban_id": "1301978",
      "explicit_tags": [
        "院线电影"
      ],
      "release_channel": "theatrical",
      "external_release_metadata": {
        "id": "1301978",
        "title": "吉尔达",
        "original_title": "Gilda",
        "subtype": "movie",
        "is_tv": false,
        "pubdate": [
          "1946-03-15"
        ],
        "release_date": [],
        "pre_release_desc": "",
        "year": "1946"
      },
      "episode_count": 1,
      "latest_episode": "0",
      "semantic_tags": "area 欧美 地区",
      "snapshot_filter_evidence": "catalog-derived"
    }
  ],
  "content_revision": "snapshot-b693cb2ce1ea39323d02",
  "snapshot_mode": "generated-filter-pack",
  "snapshot_filter": {
    "key": "area",
    "value": "欧美"
  }
}