{
  "filters": {
    "5": [
      {
        "key": "sort",
        "name": "排序",
        "init": "latest",
        "value": [
          {
            "n": "最新",
            "v": "latest"
          },
          {
            "n": "高清优先",
            "v": "quality"
          },
          {
            "n": "多线路优先",
            "v": "lines"
          },
          {
            "n": "片名排序",
            "v": "name"
          }
        ]
      },
      {
        "key": "year",
        "name": "年份",
        "init": "",
        "value": [
          {
            "n": "全部",
            "v": ""
          },
          {
            "n": "2027",
            "v": "2027"
          },
          {
            "n": "2026",
            "v": "2026"
          },
          {
            "n": "2025",
            "v": "2025"
          },
          {
            "n": "2024",
            "v": "2024"
          },
          {
            "n": "2023",
            "v": "2023"
          },
          {
            "n": "2020-2022",
            "v": "2020-2022"
          },
          {
            "n": "2010年代",
            "v": "2010s"
          },
          {
            "n": "更早",
            "v": "older"
          }
        ]
      },
      {
        "key": "area",
        "name": "地区",
        "init": "",
        "value": [
          {
            "n": "全部",
            "v": ""
          },
          {
            "n": "大陆",
            "v": "大陆"
          },
          {
            "n": "港台",
            "v": "港台"
          },
          {
            "n": "日韩",
            "v": "日韩"
          },
          {
            "n": "欧美",
            "v": "欧美"
          }
        ]
      },
      {
        "key": "class",
        "name": "主题",
        "init": "",
        "value": [
          {
            "n": "全部",
            "v": ""
          },
          {
            "n": "自然",
            "v": "自然"
          },
          {
            "n": "历史",
            "v": "历史"
          },
          {
            "n": "人文",
            "v": "人文"
          },
          {
            "n": "科技",
            "v": "科技"
          },
          {
            "n": "社会",
            "v": "社会"
          },
          {
            "n": "人物",
            "v": "人物"
          }
        ]
      },
      {
        "key": "form",
        "name": "内容形态",
        "init": "",
        "value": [
          {
            "n": "全部",
            "v": ""
          },
          {
            "n": "正片",
            "v": "正片"
          },
          {
            "n": "解说",
            "v": "解说"
          },
          {
            "n": "合集",
            "v": "合集"
          },
          {
            "n": "现场",
            "v": "现场"
          },
          {
            "n": "片段",
            "v": "片段"
          }
        ]
      },
      {
        "key": "quality",
        "name": "清晰度",
        "init": "",
        "value": [
          {
            "n": "全部",
            "v": ""
          },
          {
            "n": "高清",
            "v": "hd"
          },
          {
            "n": "正片",
            "v": "正片"
          }
        ]
      }
    ]
  },
  "code": 1,
  "msg": "ok",
  "page": 1,
  "pagecount": 1,
  "limit": 24,
  "total": 2,
  "class": [
    {
      "type_id": "0",
      "type_name": "推荐",
      "key": "recommend"
    },
    {
      "type_id": "10",
      "type_name": "院线电影",
      "key": "theatrical_movie"
    },
    {
      "type_id": "11",
      "type_name": "网络电影",
      "key": "web_movie"
    },
    {
      "type_id": "12",
      "type_name": "其他电影",
      "key": "other_movie"
    },
    {
      "type_id": "20",
      "type_name": "电视剧",
      "key": "tv_series"
    },
    {
      "type_id": "21",
      "type_name": "网络剧",
      "key": "web_series"
    },
    {
      "type_id": "6",
      "type_name": "网络短剧",
      "key": "web_short"
    },
    {
      "type_id": "3",
      "type_name": "综艺",
      "key": "variety"
    },
    {
      "type_id": "4",
      "type_name": "动漫",
      "key": "anime"
    },
    {
      "type_id": "5",
      "type_name": "纪录片",
      "key": "documentary"
    },
    {
      "type_id": "7",
      "type_name": "解说",
      "key": "explainer"
    },
    {
      "type_id": "8",
      "type_name": "文娱知识",
      "key": "knowledge"
    },
    {
      "type_id": "9",
      "type_name": "成人伦理",
      "key": "adult"
    }
  ],
  "list": [
    {
      "vod_id": "agg_W3sicyI6Imd1YW5nc3UiLCJpZCI6IjUzMzIyIn0seyJzIjoiaGh6eSIsImlkIjoiNDgzNDUifSx7InMiOiJob25nbml1IiwiaWQiOiIzMTcwMCJ9LHsicyI6Imh1eWEiLCJpZCI6IjE5MjgxIn0seyJzIjoieGlubGFuZyIsImlkIjoiNDY5MjcifV0",
      "type_id": "16",
      "type_id_1": 2,
      "group_id": 0,
      "vod_name": "哈利·波特20周年：回到霍格沃茨",
      "vod_sub": "英国 / 美国",
      "vod_en": "halibote20zhounianhuidaohuogewoci",
      "vod_status": 1,
      "vod_letter": "H",
      "vod_color": "",
      "vod_tag": "纪录片",
      "vod_class": "纪录片",
      "vod_pic": "https://hhmage.com/cover/6a6caa12c63ac1c2f2b7d967b512887d.jpg",
      "vod_pic_thumb": "",
      "vod_pic_slide": "",
      "vod_pic_screenshot": null,
      "vod_actor": "丹尼尔·雷德克里夫,艾玛·沃森,鲁伯特·格林特,海伦娜·伯翰·卡特,加里·奥德曼",
      "vod_director": "伊兰·克里维",
      "vod_writer": "",
      "vod_behind": "",
      "vod_blurb": "　　“哈利波特”电影全系列的演职员在一场特别的回顾活动中重逢，庆祝第一部电影的周年纪念，其中包括采访和演员对话。",
      "vod_remarks": "正片",
      "vod_pubdate": "103分钟",
      "vod_total": "1",
      "vod_serial": "0",
      "vod_tv": "",
      "vod_weekday": "",
      "vod_area": "英国",
      "vod_lang": "",
      "vod_year": "2022",
      "vod_version": "",
      "vod_state": "",
      "vod_author": "",
      "vod_jumpurl": "",
      "vod_tpl": "",
      "vod_tpl_play": "",
      "vod_tpl_down": "",
      "vod_isend": 1,
      "vod_lock": 0,
      "vod_level": 0,
      "vod_copyright": 0,
      "vod_points": 0,
      "vod_points_play": 0,
      "vod_points_down": 0,
      "vod_hits": 481,
      "vod_hits_day": 720,
      "vod_hits_week": 805,
      "vod_hits_month": 123,
      "vod_duration": "",
      "vod_up": 996,
      "vod_down": 232,
      "vod_score": "4.0",
      "vod_score_all": 1764,
      "vod_score_num": 441,
      "vod_time": "2026-06-30 18:18:01",
      "vod_time_add": "1685438199",
      "vod_time_hits": 0,
      "vod_time_make": 0,
      "vod_trysee": 0,
      "vod_douban_id": 35663020,
      "vod_douban_score": "8.7",
      "vod_reurl": "",
      "vod_rel_vod": "",
      "vod_rel_art": "",
      "vod_pwd": "",
      "vod_pwd_url": "",
      "vod_pwd_play": "",
      "vod_pwd_play_url": "",
      "vod_pwd_down": "",
      "vod_pwd_down_url": "",
      "vod_content": "　　“哈利波特”电影全系列的演职员在一场特别的回顾活动中重逢，庆祝第一部电影的周年纪念，其中包括采访和演员对话。\n",
      "vod_play_from": "hhyun$$$hhm3u8",
      "vod_play_server": "$$$",
      "vod_play_note": "$$$",
      "vod_play_url": "正片$https://play.hhuus.com/play/aQWk9Eqd$$$正片$https://play.hhuus.com/play/aQWk9Eqd/index.m3u8",
      "vod_down_from": "",
      "vod_down_server": "",
      "vod_down_note": "",
      "vod_down_url": "",
      "vod_plot": 0,
      "vod_plot_name": "",
      "vod_plot_detail": "",
      "type_name": "记录片",
      "source_category_id": "5",
      "source_category_name": "记录片",
      "_sourceSlug": "huya",
      "_sourceShort": "虎牙",
      "source_url": "https://www.huyaapi.com/api.php/provide/vod/from/hym3u8/",
      "canonical_id": "ext:douban:35663020",
      "primary_category": "documentary",
      "movie_release_channel": "unknown",
      "classification_evidence": [
        {
          "source": "source_category_id",
          "priority": 1,
          "category": "documentary",
          "field": "source_category_id",
          "value": "5",
          "signal": "documentary"
        }
      ],
      "classification_confidence": 0.99,
      "classification_confidence_level": "high",
      "classification_confidence_score": 0.99,
      "source_candidates": [
        {
          "source": "huya",
          "id": "19281",
          "url": "https://www.huyaapi.com/api.php/provide/vod/from/hym3u8/",
          "updated_at": ""
        },
        {
          "source": "hhzy",
          "id": "48345",
          "url": "https://hhzyapi.com/api.php/provide/vod/",
          "updated_at": ""
        },
        {
          "source": "hongniu",
          "id": "31700",
          "url": "https://www.hongniuzy2.com/api.php/provide/vod/",
          "updated_at": ""
        },
        {
          "source": "guangsu",
          "id": "53322",
          "url": "https://api.guangsuapi.com/api.php/provide/vod/",
          "updated_at": ""
        },
        {
          "source": "xinlang",
          "id": "46927",
          "url": "https://api.xinlangapi.com/xinlangapi.php/provide/vod/",
          "updated_at": ""
        }
      ],
      "play_lines": [
        {
          "source": "huya",
          "name": "hym3u8",
          "url": "正片$https://1080p.huyall.com/play/dPNj3Dla/index.m3u8"
        },
        {
          "source": "huya",
          "name": "hhyun",
          "url": "正片$https://play.hhuus.com/play/aQWk9Eqd"
        },
        {
          "source": "huya",
          "name": "hhm3u8",
          "url": "正片$https://play.hhuus.com/play/aQWk9Eqd/index.m3u8"
        },
        {
          "source": "hhzy",
          "name": "hhyun",
          "url": "正片$https://play.hhuus.com/play/aQWk9Eqd"
        },
        {
          "source": "hhzy",
          "name": "hhm3u8",
          "url": "正片$https://play.hhuus.com/play/aQWk9Eqd/index.m3u8"
        },
        {
          "source": "hongniu",
          "name": "hnyun",
          "url": "正片$https://hn.bfvvs.com/play/aM8Z3zBe"
        },
        {
          "source": "hongniu",
          "name": "hnm3u8",
          "url": "正片$https://hn.bfvvs.com/play/aM8Z3zBe/index.m3u8"
        },
        {
          "source": "hongniu",
          "name": "hhyun",
          "url": "正片$https://play.hhuus.com/play/aQWk9Eqd"
        },
        {
          "source": "hongniu",
          "name": "hhm3u8",
          "url": "正片$https://play.hhuus.com/play/aQWk9Eqd/index.m3u8"
        },
        {
          "source": "guangsu",
          "name": "gsyun",
          "url": "正片$https://v.gsuus.com/play/dNkO3AKe"
        },
        {
          "source": "guangsu",
          "name": "gsm3u8",
          "url": "正片$https://v.gsuus.com/play/dNkO3AKe/index.m3u8"
        },
        {
          "source": "guangsu",
          "name": "hhyun",
          "url": "正片$https://play.hhuus.com/play/aQWk9Eqd"
        },
        {
          "source": "guangsu",
          "name": "hhm3u8",
          "url": "正片$https://play.hhuus.com/play/aQWk9Eqd/index.m3u8"
        },
        {
          "source": "xinlang",
          "name": "xlyun",
          "url": "正片$https://play.xluuss.com/play/aOYg3BGd"
        },
        {
          "source": "xinlang",
          "name": "xlm3u8",
          "url": "正片$https://play.xluuss.com/play/aOYg3BGd/index.m3u8"
        },
        {
          "source": "xinlang",
          "name": "hhyun",
          "url": "正片$https://play.hhuus.com/play/aQWk9Eqd"
        },
        {
          "source": "xinlang",
          "name": "hhm3u8",
          "url": "正片$https://play.hhuus.com/play/aQWk9Eqd/index.m3u8"
        }
      ],
      "episode_count": 1,
      "latest_episode": "0",
      "semantic_tags": "year 2020-2022 年份",
      "snapshot_filter_evidence": "catalog-derived"
    },
    {
      "vod_id": "agg_W3sicyI6ImZmenlfZGlyZWN0IiwiaWQiOiI5NzQxNyJ9XQ",
      "type_id": "20",
      "type_id_1": 1,
      "group_id": 0,
      "vod_name": "数学漫步之旅",
      "vod_sub": "Voyages au pays des maths,Journey into Maths Country",
      "vod_en": "shuxuemanbuzhilv",
      "vod_status": 1,
      "vod_letter": "S",
      "vod_color": "",
      "vod_tag": "",
      "vod_class": "动画,纪录片,短片",
      "vod_pic": "https://tupian.ffeiimg.com/upload/vod/20260509-1/d7a9dd5a8598b47d521b3895ad5625f0.jpg",
      "vod_pic_thumb": "",
      "vod_pic_slide": "",
      "vod_pic_screenshot": "",
      "vod_actor": "",
      "vod_director": "Denis Van Waerebeke",
      "vod_writer": "",
      "vod_behind": "",
      "vod_blurb": "&amp;nbsp;我们将尝试解释数学，并非学校里教的那样，而是一种诗意的、神秘的思维结构。它强调逻辑，即数学让我们掌握的现实中的实际应用。这个系列旨在让好奇的观众发现数学新奇的一面，让他们觉得数学是思考的一",
      "vod_remarks": "已完结",
      "vod_pubdate": "2021-01-21",
      "vod_total": "10",
      "vod_serial": "",
      "vod_tv": "",
      "vod_weekday": "",
      "vod_area": "法国",
      "vod_lang": "英语",
      "vod_year": "2021",
      "vod_version": "",
      "vod_state": "正片",
      "vod_author": "",
      "vod_jumpurl": "",
      "vod_tpl": "",
      "vod_tpl_play": "",
      "vod_tpl_down": "",
      "vod_isend": 0,
      "vod_lock": 0,
      "vod_level": 0,
      "vod_copyright": 0,
      "vod_points": 0,
      "vod_points_play": 0,
      "vod_points_down": 0,
      "vod_hits": 0,
      "vod_hits_day": 0,
      "vod_hits_week": 0,
      "vod_hits_month": 0,
      "vod_duration": "",
      "vod_up": 0,
      "vod_down": 0,
      "vod_score": "9.5",
      "vod_score_all": 0,
      "vod_score_num": 0,
      "vod_time": "2026-05-09 16:28:15",
      "vod_time_add": "1778315295",
      "vod_time_hits": 0,
      "vod_time_make": 0,
      "vod_trysee": 0,
      "vod_douban_id": 36001280,
      "vod_douban_score": "9.5",
      "vod_reurl": "",
      "vod_rel_vod": "",
      "vod_rel_art": "",
      "vod_pwd": "",
      "vod_pwd_url": "",
      "vod_pwd_play": "",
      "vod_pwd_play_url": "",
      "vod_pwd_down": "",
      "vod_pwd_down_url": "",
      "vod_content": "<p>&nbsp;我们将尝试解释数学，并非学校里教的那样，而是一种诗意的、神秘的思维结构。它强调逻辑，即数学让我们掌握的现实中的实际应用。这个系列旨在让好奇的观众发现数学新奇的一面，让他们觉得数学是思考的一部分，是文化的一部分。</p>",
      "vod_play_from": "feifan$$$ffm3u8",
      "vod_play_server": "no$$$no",
      "vod_play_note": "$$$",
      "vod_play_url": "第01集$https://vip.ffzy-play9.com/share/6c1aec706ffc46d4bb34dadd5b853be9#第02集$https://vip.ffzy-play9.com/share/95b4738e0867cc64385b42e3cb13d3b6#第03集$https://vip.ffzy-play9.com/share/001f35b87b35111bcaf1087426d2884e#第04集$https://vip.ffzy-play9.com/share/dcf5cd105900373d89923a5bc7b34452#第05集$https://vip.ffzy-play9.com/share/f593b9ead8801922f74f0a5329e31486#第06集$https://vip.ffzy-play9.com/share/48bbfd2497b88edea00746d7c8cb96bf#第07集$https://vip.ffzy-play9.com/share/1cba40e3efa7040ac28c0f065f7cacd1#第08集$https://vip.ffzy-play9.com/share/248e0936054f0ff1fa6135969174f162#第09集$https://vip.ffzy-play9.com/share/44ab8b63c8f165307233810152191c89#第10集$https://vip.ffzy-play9.com/share/14ca45894cf46dffdf23b38cde42ee8b$$$第01集$https://vip.ffzy-play9.com/20260509/40370_6c1aec70/index.m3u8#第02集$https://vip.ffzy-play9.com/20260509/40371_95b4738e/index.m3u8#第03集$https://vip.ffzy-play9.com/20260509/40372_001f35b8/index.m3u8#第04集$https://vip.ffzy-play9.com/20260509/40373_dcf5cd10/index.m3u8#第05集$https://vip.ffzy-play9.com/20260509/40374_f593b9ea/index.m3u8#第06集$https://vip.ffzy-play9.com/20260509/40375_48bbfd24/index.m3u8#第07集$https://vip.ffzy-play9.com/20260509/40376_1cba40e3/index.m3u8#第08集$https://vip.ffzy-play9.com/20260509/40377_248e0936/index.m3u8#第09集$https://vip.ffzy-play9.com/20260509/40378_44ab8b63/index.m3u8#第10集$https://vip.ffzy-play9.com/20260509/40379_14ca4589/index.m3u8",
      "vod_down_from": "no",
      "vod_down_server": "no",
      "vod_down_note": "",
      "vod_down_url": "",
      "vod_plot": 0,
      "vod_plot_name": "",
      "vod_plot_detail": "",
      "type_name": "记录片",
      "source_category_id": "5",
      "source_category_name": "记录片",
      "_sourceSlug": "ffzy_direct",
      "_sourceShort": "非凡直连",
      "source_url": "http://ffzy.tv/api.php/provide/vod/",
      "canonical_id": "ext:douban:36001280",
      "primary_category": "documentary",
      "movie_release_channel": "unknown",
      "classification_evidence": [
        {
          "source": "source_category_id",
          "priority": 1,
          "category": "documentary",
          "field": "source_category_id",
          "value": "5",
          "signal": "documentary"
        }
      ],
      "classification_confidence": 0.99,
      "classification_confidence_level": "high",
      "classification_confidence_score": 0.99,
      "source_candidates": [
        {
          "source": "ffzy_direct",
          "id": "97417",
          "url": "http://ffzy.tv/api.php/provide/vod/",
          "updated_at": ""
        }
      ],
      "play_lines": [
        {
          "source": "ffzy_direct",
          "name": "feifan",
          "url": "第01集$https://vip.ffzy-play9.com/share/6c1aec706ffc46d4bb34dadd5b853be9#第02集$https://vip.ffzy-play9.com/share/95b4738e0867cc64385b42e3cb13d3b6#第03集$https://vip.ffzy-play9.com/share/001f35b87b35111bcaf1087426d2884e#第04集$https://vip.ffzy-play9.com/share/dcf5cd105900373d89923a5bc7b34452#第05集$https://vip.ffzy-play9.com/share/f593b9ead8801922f74f0a5329e31486#第06集$https://vip.ffzy-play9.com/share/48bbfd2497b88edea00746d7c8cb96bf#第07集$https://vip.ffzy-play9.com/share/1cba40e3efa7040ac28c0f065f7cacd1#第08集$https://vip.ffzy-play9.com/share/248e0936054f0ff1fa6135969174f162#第09集$https://vip.ffzy-play9.com/share/44ab8b63c8f165307233810152191c89#第10集$https://vip.ffzy-play9.com/share/14ca45894cf46dffdf23b38cde42ee8b"
        },
        {
          "source": "ffzy_direct",
          "name": "ffm3u8",
          "url": "第01集$https://vip.ffzy-play9.com/20260509/40370_6c1aec70/index.m3u8#第02集$https://vip.ffzy-play9.com/20260509/40371_95b4738e/index.m3u8#第03集$https://vip.ffzy-play9.com/20260509/40372_001f35b8/index.m3u8#第04集$https://vip.ffzy-play9.com/20260509/40373_dcf5cd10/index.m3u8#第05集$https://vip.ffzy-play9.com/20260509/40374_f593b9ea/index.m3u8#第06集$https://vip.ffzy-play9.com/20260509/40375_48bbfd24/index.m3u8#第07集$https://vip.ffzy-play9.com/20260509/40376_1cba40e3/index.m3u8#第08集$https://vip.ffzy-play9.com/20260509/40377_248e0936/index.m3u8#第09集$https://vip.ffzy-play9.com/20260509/40378_44ab8b63/index.m3u8#第10集$https://vip.ffzy-play9.com/20260509/40379_14ca4589/index.m3u8"
        }
      ],
      "semantic_tags": "year 2020-2022 年份",
      "snapshot_filter_evidence": "catalog-derived"
    }
  ],
  "content_revision": "snapshot-b693cb2ce1ea39323d02",
  "snapshot_mode": "generated-filter-pack",
  "snapshot_filter": {
    "key": "year",
    "value": "2020-2022"
  }
}