{
  "filters": {
    "12": [
      {
        "key": "sort",
        "name": "排序",
        "init": "latest",
        "value": [
          {
            "n": "最新",
            "v": "latest"
          },
          {
            "n": "高清优先",
            "v": "quality"
          },
          {
            "n": "多线路优先",
            "v": "lines"
          },
          {
            "n": "片名排序",
            "v": "name"
          }
        ]
      },
      {
        "key": "year",
        "name": "年份",
        "init": "",
        "value": [
          {
            "n": "全部",
            "v": ""
          },
          {
            "n": "2027",
            "v": "2027"
          },
          {
            "n": "2026",
            "v": "2026"
          },
          {
            "n": "2025",
            "v": "2025"
          },
          {
            "n": "2024",
            "v": "2024"
          },
          {
            "n": "2023",
            "v": "2023"
          },
          {
            "n": "2020-2022",
            "v": "2020-2022"
          },
          {
            "n": "2010年代",
            "v": "2010s"
          },
          {
            "n": "更早",
            "v": "older"
          }
        ]
      },
      {
        "key": "area",
        "name": "地区",
        "init": "",
        "value": [
          {
            "n": "全部",
            "v": ""
          },
          {
            "n": "大陆",
            "v": "大陆"
          },
          {
            "n": "港台",
            "v": "港台"
          },
          {
            "n": "日韩",
            "v": "日韩"
          },
          {
            "n": "欧美",
            "v": "欧美"
          },
          {
            "n": "泰国",
            "v": "泰国"
          }
        ]
      },
      {
        "key": "class",
        "name": "类型",
        "init": "",
        "value": [
          {
            "n": "全部",
            "v": ""
          },
          {
            "n": "动作",
            "v": "动作"
          },
          {
            "n": "喜剧",
            "v": "喜剧"
          },
          {
            "n": "爱情",
            "v": "爱情"
          },
          {
            "n": "悬疑犯罪",
            "v": "悬疑犯罪"
          },
          {
            "n": "科幻奇幻",
            "v": "科幻奇幻"
          },
          {
            "n": "恐怖惊悚",
            "v": "恐怖惊悚"
          },
          {
            "n": "剧情",
            "v": "剧情"
          },
          {
            "n": "战争历史",
            "v": "战争历史"
          }
        ]
      },
      {
        "key": "form",
        "name": "内容形态",
        "init": "",
        "value": [
          {
            "n": "全部",
            "v": ""
          },
          {
            "n": "正片",
            "v": "正片"
          },
          {
            "n": "解说",
            "v": "解说"
          },
          {
            "n": "合集",
            "v": "合集"
          },
          {
            "n": "现场",
            "v": "现场"
          },
          {
            "n": "课程",
            "v": "课程"
          },
          {
            "n": "片段",
            "v": "片段"
          }
        ]
      },
      {
        "key": "quality",
        "name": "清晰度",
        "init": "",
        "value": [
          {
            "n": "全部",
            "v": ""
          },
          {
            "n": "高清",
            "v": "hd"
          },
          {
            "n": "4K",
            "v": "4K"
          },
          {
            "n": "正片",
            "v": "正片"
          },
          {
            "n": "抢先",
            "v": "抢先"
          }
        ]
      }
    ]
  },
  "code": 1,
  "msg": "ok",
  "page": 16,
  "pagecount": 17,
  "limit": 24,
  "total": 392,
  "class": [
    {
      "type_id": "0",
      "type_name": "推荐",
      "key": "recommend"
    },
    {
      "type_id": "10",
      "type_name": "院线电影",
      "key": "theatrical_movie"
    },
    {
      "type_id": "11",
      "type_name": "网络电影",
      "key": "web_movie"
    },
    {
      "type_id": "12",
      "type_name": "其他电影",
      "key": "other_movie"
    },
    {
      "type_id": "20",
      "type_name": "电视剧",
      "key": "tv_series"
    },
    {
      "type_id": "21",
      "type_name": "网络剧",
      "key": "web_series"
    },
    {
      "type_id": "6",
      "type_name": "网络短剧",
      "key": "web_short"
    },
    {
      "type_id": "3",
      "type_name": "综艺",
      "key": "variety"
    },
    {
      "type_id": "4",
      "type_name": "动漫",
      "key": "anime"
    },
    {
      "type_id": "5",
      "type_name": "纪录片",
      "key": "documentary"
    },
    {
      "type_id": "7",
      "type_name": "解说",
      "key": "explainer"
    },
    {
      "type_id": "8",
      "type_name": "文娱知识",
      "key": "knowledge"
    },
    {
      "type_id": "9",
      "type_name": "成人伦理",
      "key": "adult"
    }
  ],
  "list": [
    {
      "vod_id": "agg_W3sicyI6InRhb3BpYW4iLCJpZCI6IjE1MzI0NDcifV0",
      "vod_name": "大话神捕",
      "vod_sub": "",
      "vod_remarks": "",
      "vod_serial": "1",
      "type_id": "15007744",
      "vod_actor": "包贝尔/许君聪/卜钰",
      "vod_director": "浦宇",
      "vod_pic": "https://taopianimage.xyz:43333/fd605b659cbcv.jpeg",
      "vod_content": "影片讲述了一起“女鬼”深夜伸冤索命，小镇百姓人心惶惶，小捕快郭幻（许君聪 饰）为查清案件真相，竟误抓了假扮女鬼的夏虫（卜钰 饰），还意外发现一起蹊跷血案。寡妇离奇失踪，尸体现身荒郊野外，幕后真凶势力猖狂，捕快郭幻能否查清幕后真相，将恶霸绳之以法。",
      "vod_time": "2025-01-30 00:00:00",
      "vod_area": "中国大陆",
      "vod_lang": "汉语普通话",
      "vod_year": 2021,
      "type_name": "电影/喜剧片",
      "vod_keywords": "包贝尔,许君聪,卜钰,浦宇,喜剧片,包贝尔,许君聪,卜钰,汉语普通话,汉语普通话,剧情,喜剧,大话神捕",
      "vod_tag": "剧情/喜剧",
      "vod_play_server": "",
      "vod_play_from": "tpm3u8$$$tpiframe",
      "vod_play_url": "大话神捕$https://sd8.taopianplay1.com:43333/c56b1bc09da3/HD/2025-01-30/1/fd605b659cbc/7d510e031cab/playlist.m3u8$$$大话神捕$https://www.tpvod.com/player.html?uri=https%3A%2F%2Fsd8.taopianplay1.com%3A43333%2Fc56b1bc09da3%2FHD%2F2025-01-30%2F1%2Ffd605b659cbc%2F7d510e031cab%2Fplaylist.m3u8",
      "vod_play_note": "",
      "vod_down_server": "",
      "vod_down_from": "tpm3u8$$$tpiframe",
      "vod_down_url": "大话神捕$https://sd8.taopianplay1.com:43333/c56b1bc09da3/HD/2025-01-30/1/fd605b659cbc/7d510e031cab/playlist.m3u8$$$大话神捕$https://www.tpvod.com/player.html?uri=https%3A%2F%2Fsd8.taopianplay1.com%3A43333%2Fc56b1bc09da3%2FHD%2F2025-01-30%2F1%2Ffd605b659cbc%2F7d510e031cab%2Fplaylist.m3u8",
      "vod_down_note": "",
      "vod_length": 4920,
      "vod_weekday": "周一",
      "vod_copyright": "",
      "vod_state_": 1,
      "vod_version": "高清版",
      "vod_tv": "",
      "vod_total": "1",
      "vod_continu": 0,
      "vod_status": 1,
      "vod_stars": 0,
      "vod_hits": 0,
      "vod_isend": 0,
      "vod_douban_id": 0,
      "list_name": "电影/喜剧片",
      "imdb": 0,
      "extra_type": "",
      "origin": "tpm3u8$$$tpiframe",
      "vod_state": "",
      "vod_duration": "82",
      "vod_pubdate": "2021-09-11 00:00:00",
      "vod_douban_score": 0,
      "vod_ename": "",
      "source_category_id": "12",
      "source_category_name": "电影/喜剧片",
      "_sourceSlug": "taopian",
      "_sourceShort": "淘片",
      "source_url": "https://taopianapi.com/cjapi/mc/vod/json.html",
      "vod_time_add": "",
      "canonical_id": "meta:%E5%A4%A7%E8%AF%9D%E7%A5%9E%E6%8D%95:2021:0:%E6%B5%A6%E5%AE%87",
      "primary_category": "other_movie",
      "movie_release_channel": "unknown",
      "classification_evidence": [
        {
          "source": "source_category_id",
          "priority": 1,
          "category": "other_movie",
          "field": "source_category_id",
          "value": "12",
          "signal": "other_movie"
        }
      ],
      "classification_confidence": 0.99,
      "classification_confidence_level": "high",
      "classification_confidence_score": 0.99,
      "source_candidates": [
        {
          "source": "taopian",
          "id": "1532447",
          "url": "https://taopianapi.com/cjapi/mc/vod/json.html",
          "updated_at": ""
        }
      ],
      "play_lines": [
        {
          "source": "taopian",
          "name": "tpm3u8",
          "url": "大话神捕$https://sd8.taopianplay1.com:43333/c56b1bc09da3/HD/2025-01-30/1/fd605b659cbc/7d510e031cab/playlist.m3u8"
        },
        {
          "source": "taopian",
          "name": "tpiframe",
          "url": "大话神捕$https://www.tpvod.com/player.html?uri=https%3A%2F%2Fsd8.taopianplay1.com%3A43333%2Fc56b1bc09da3%2FHD%2F2025-01-30%2F1%2Ffd605b659cbc%2F7d510e031cab%2Fplaylist.m3u8"
        }
      ],
      "semantic_tags": "class 喜剧 类型",
      "snapshot_filter_evidence": "catalog-derived"
    },
    {
      "vod_id": "agg_W3sicyI6ImJhaWR1IiwiaWQiOiI1MDE4MyJ9XQ",
      "type_id": "7",
      "type_id_1": 1,
      "group_id": 0,
      "vod_name": "第三声钟响",
      "vod_sub": "",
      "vod_en": "disanshengzhongxiang",
      "vod_status": 1,
      "vod_letter": "D",
      "vod_color": "",
      "vod_tag": "",
      "vod_class": "",
      "vod_pic": "https://img.bdzyimg1.com/upload/vod/20260708-1/bdbc80e86803b797624aa7750e09efb6.jpg",
      "vod_pic_thumb": "",
      "vod_pic_slide": "",
      "vod_pic_screenshot": "",
      "vod_actor": "斯琴高丽,熊乃瑾,马闻远,陶平",
      "vod_director": "姚庆涛",
      "vod_writer": "",
      "vod_behind": "",
      "vod_blurb": "影片讲述明星钟言阴差阳错来到老挝拍广告，被女主安雅卷入湄公河，与团队失联后身无一物，不得不与安雅开始一场疯狂冒险之旅，殊不知被狗仔盯上并被曝光于众的故事。",
      "vod_remarks": "更新HD",
      "vod_pubdate": "",
      "vod_total": "0",
      "vod_serial": "",
      "vod_tv": "",
      "vod_weekday": "",
      "vod_area": "中国大陆",
      "vod_lang": "汉语普通话",
      "vod_year": "2021",
      "vod_version": "",
      "vod_state": "",
      "vod_author": "",
      "vod_jumpurl": "",
      "vod_tpl": "",
      "vod_tpl_play": "",
      "vod_tpl_down": "",
      "vod_isend": 0,
      "vod_lock": 0,
      "vod_level": 0,
      "vod_copyright": 0,
      "vod_points": 0,
      "vod_points_play": 0,
      "vod_points_down": 0,
      "vod_hits": 0,
      "vod_hits_day": 0,
      "vod_hits_week": 0,
      "vod_hits_month": 0,
      "vod_duration": "",
      "vod_up": 0,
      "vod_down": 0,
      "vod_score": "0.0",
      "vod_score_all": 0,
      "vod_score_num": 0,
      "vod_time": "2026-07-08 19:53:23",
      "vod_time_add": "1783511603",
      "vod_time_hits": 0,
      "vod_time_make": 0,
      "vod_trysee": 0,
      "vod_douban_id": 0,
      "vod_douban_score": "0.0",
      "vod_reurl": "",
      "vod_rel_vod": "",
      "vod_rel_art": "",
      "vod_pwd": "",
      "vod_pwd_url": "",
      "vod_pwd_play": "",
      "vod_pwd_play_url": "",
      "vod_pwd_down": "",
      "vod_pwd_down_url": "",
      "vod_content": "<p>影片讲述明星钟言阴差阳错来到老挝拍广告，被女主安雅卷入湄公河，与团队失联后身无一物，不得不与安雅开始一场疯狂冒险之旅，殊不知被狗仔盯上并被曝光于众的故事。</p>",
      "vod_play_from": "dbm3u8",
      "vod_play_server": "no",
      "vod_play_note": "",
      "vod_play_url": "HD$https://b3.bdzybf22.com/videos/202607/08/6a4e2c490452185f598a89af/ag92f7/index.m3u8",
      "vod_down_from": "",
      "vod_down_server": "",
      "vod_down_note": "",
      "vod_down_url": "",
      "vod_plot": 0,
      "vod_plot_name": "",
      "vod_plot_detail": "",
      "type_name": "喜剧片",
      "source_category_id": "12",
      "source_category_name": "喜剧片",
      "_sourceSlug": "baidu",
      "_sourceShort": "百度",
      "source_url": "https://api.apibdzy.com/api.php/provide/vod/",
      "canonical_id": "meta:%E7%AC%AC%E4%B8%89%E5%A3%B0%E9%92%9F%E5%93%8D:2021:0:%E5%A7%9A%E5%BA%86%E6%B6%9B",
      "primary_category": "other_movie",
      "movie_release_channel": "unknown",
      "classification_evidence": [
        {
          "source": "source_category_id",
          "priority": 1,
          "category": "other_movie",
          "field": "source_category_id",
          "value": "12",
          "signal": "other_movie"
        }
      ],
      "classification_confidence": 0.99,
      "classification_confidence_level": "high",
      "classification_confidence_score": 0.99,
      "source_candidates": [
        {
          "source": "baidu",
          "id": "50183",
          "url": "https://api.apibdzy.com/api.php/provide/vod/",
          "updated_at": ""
        }
      ],
      "play_lines": [
        {
          "source": "baidu",
          "name": "dbm3u8",
          "url": "HD$https://b3.bdzybf22.com/videos/202607/08/6a4e2c490452185f598a89af/ag92f7/index.m3u8"
        }
      ],
      "semantic_tags": "class 喜剧 类型",
      "snapshot_filter_evidence": "catalog-derived"
    },
    {
      "vod_id": "agg_W3sicyI6InRhb3BpYW4iLCJpZCI6IjE1MzI0MzEifV0",
      "vod_name": "我爱喵星人",
      "vod_sub": "Catman",
      "vod_remarks": "",
      "vod_serial": "1",
      "type_id": "15007744",
      "vod_actor": "于波/孙宁/吴世勋/吴倩/鞠婧祎/宋威龙/徐可/李昕亮/许佳琪",
      "vod_director": "刘希坤",
      "vod_pic": "https://taopianimage.xyz:43333/26734686.jpg",
      "vod_content": "意外受到猫咪诅咒的少年，被迫离开心爱的女孩，开始了半人半猫的生活。9年后，诅咒即将破除，少年和女孩再次相遇，一面是“如果对人类心动，诅咒就无法解除”的困境，一面是深陷险境的女孩，少年该如何选择…",
      "vod_time": "2025-01-29 00:00:00",
      "vod_area": "中国大陆/韩国",
      "vod_lang": "汉语普通话",
      "vod_year": 2021,
      "type_name": "电影/喜剧片",
      "vod_keywords": "于波,孙宁,吴世勋,吴倩,鞠婧祎,宋威龙,徐可,李昕亮,许佳琪,刘希坤,喜剧片,于波,孙宁,吴世勋,吴倩,鞠婧祎,宋威龙,徐可,李昕亮,许佳琪,汉语普通话,汉语普通话,爱情,喜剧,奇幻,我爱喵星人",
      "vod_tag": "爱情/喜剧/奇幻",
      "vod_play_server": "",
      "vod_play_from": "tpm3u8$$$tpiframe",
      "vod_play_url": "我爱喵星人$https://sd8.taopianplay1.com:43333/c56b1bc09da3/HD/2025-01-29/1/1908221c956c/5770d52feab8/playlist.m3u8$$$我爱喵星人$https://www.tpvod.com/player.html?uri=https%3A%2F%2Fsd8.taopianplay1.com%3A43333%2Fc56b1bc09da3%2FHD%2F2025-01-29%2F1%2F1908221c956c%2F5770d52feab8%2Fplaylist.m3u8",
      "vod_play_note": "",
      "vod_down_server": "",
      "vod_down_from": "tpm3u8$$$tpiframe",
      "vod_down_url": "我爱喵星人$https://sd8.taopianplay1.com:43333/c56b1bc09da3/HD/2025-01-29/1/1908221c956c/5770d52feab8/playlist.m3u8$$$我爱喵星人$https://www.tpvod.com/player.html?uri=https%3A%2F%2Fsd8.taopianplay1.com%3A43333%2Fc56b1bc09da3%2FHD%2F2025-01-29%2F1%2F1908221c956c%2F5770d52feab8%2Fplaylist.m3u8",
      "vod_down_note": "",
      "vod_length": 5460,
      "vod_weekday": "周一",
      "vod_copyright": "",
      "vod_state_": 1,
      "vod_version": "高清版",
      "vod_tv": "",
      "vod_total": "1",
      "vod_continu": 0,
      "vod_status": 1,
      "vod_stars": 0,
      "vod_hits": 0,
      "vod_isend": 0,
      "vod_douban_id": 0,
      "list_name": "电影/喜剧片",
      "imdb": 6.5,
      "extra_type": "",
      "origin": "tpm3u8$$$tpiframe",
      "vod_state": "",
      "vod_duration": "91",
      "vod_pubdate": "2021-05-18 00:00:00",
      "vod_douban_score": 0,
      "vod_ename": "",
      "source_category_id": "12",
      "source_category_name": "电影/喜剧片",
      "_sourceSlug": "taopian",
      "_sourceShort": "淘片",
      "source_url": "https://taopianapi.com/cjapi/mc/vod/json.html",
      "vod_time_add": "",
      "canonical_id": "meta:%E6%88%91%E7%88%B1%E5%96%B5%E6%98%9F%E4%BA%BA:2021:0:%E5%88%98%E5%B8%8C%E5%9D%A4",
      "primary_category": "other_movie",
      "movie_release_channel": "unknown",
      "classification_evidence": [
        {
          "source": "source_category_id",
          "priority": 1,
          "category": "other_movie",
          "field": "source_category_id",
          "value": "12",
          "signal": "other_movie"
        }
      ],
      "classification_confidence": 0.99,
      "classification_confidence_level": "high",
      "classification_confidence_score": 0.99,
      "source_candidates": [
        {
          "source": "taopian",
          "id": "1532431",
          "url": "https://taopianapi.com/cjapi/mc/vod/json.html",
          "updated_at": ""
        }
      ],
      "play_lines": [
        {
          "source": "taopian",
          "name": "tpm3u8",
          "url": "我爱喵星人$https://sd8.taopianplay1.com:43333/c56b1bc09da3/HD/2025-01-29/1/1908221c956c/5770d52feab8/playlist.m3u8"
        },
        {
          "source": "taopian",
          "name": "tpiframe",
          "url": "我爱喵星人$https://www.tpvod.com/player.html?uri=https%3A%2F%2Fsd8.taopianplay1.com%3A43333%2Fc56b1bc09da3%2FHD%2F2025-01-29%2F1%2F1908221c956c%2F5770d52feab8%2Fplaylist.m3u8"
        }
      ],
      "semantic_tags": "class 喜剧 类型",
      "snapshot_filter_evidence": "catalog-derived"
    },
    {
      "vod_id": "agg_W3sicyI6ImJhaWR1IiwiaWQiOiI1MDEyMSJ9XQ",
      "type_id": "7",
      "type_id_1": 1,
      "group_id": 0,
      "vod_name": "最萌卧底",
      "vod_sub": "",
      "vod_en": "zuimengwodi",
      "vod_status": 1,
      "vod_letter": "Z",
      "vod_color": "",
      "vod_tag": "",
      "vod_class": "",
      "vod_pic": "https://img.bdzyimg1.com/upload/vod/20260705-1/5fbc1bf7e460eee4fc0e07d347633d32.jpg",
      "vod_pic_thumb": "",
      "vod_pic_slide": "",
      "vod_pic_screenshot": "",
      "vod_actor": "阿玉松·玛尼提,Bell·Sawanya·Liangprasit,Best·Nathasit·Kotimanuswanich,Pim·Latkamon·Pinrojkirati",
      "vod_director": "Aekasit·Sompech",
      "vod_writer": "",
      "vod_behind": "",
      "vod_blurb": "Shisu, a reporter, is good at everything, but she is only 155 cm tall, so she is often teased. One d",
      "vod_remarks": "更新HD",
      "vod_pubdate": "",
      "vod_total": "0",
      "vod_serial": "",
      "vod_tv": "",
      "vod_weekday": "",
      "vod_area": "泰国",
      "vod_lang": "泰语",
      "vod_year": "2020",
      "vod_version": "",
      "vod_state": "",
      "vod_author": "",
      "vod_jumpurl": "",
      "vod_tpl": "",
      "vod_tpl_play": "",
      "vod_tpl_down": "",
      "vod_isend": 0,
      "vod_lock": 0,
      "vod_level": 0,
      "vod_copyright": 0,
      "vod_points": 0,
      "vod_points_play": 0,
      "vod_points_down": 0,
      "vod_hits": 0,
      "vod_hits_day": 0,
      "vod_hits_week": 0,
      "vod_hits_month": 0,
      "vod_duration": "",
      "vod_up": 0,
      "vod_down": 0,
      "vod_score": "0.0",
      "vod_score_all": 0,
      "vod_score_num": 0,
      "vod_time": "2026-07-05 21:31:34",
      "vod_time_add": "1783258294",
      "vod_time_hits": 0,
      "vod_time_make": 0,
      "vod_trysee": 0,
      "vod_douban_id": 0,
      "vod_douban_score": "0.0",
      "vod_reurl": "",
      "vod_rel_vod": "",
      "vod_rel_art": "",
      "vod_pwd": "",
      "vod_pwd_url": "",
      "vod_pwd_play": "",
      "vod_pwd_play_url": "",
      "vod_pwd_down": "",
      "vod_pwd_down_url": "",
      "vod_content": "<p>Shisu, a reporter, is good at everything, but she is only 155 cm tall, so she is often teased. One day, she happened to meet Fayfa, a tall policeman who she has secretly admired since university days. The two together investigated the case by allowing Shisu to disguise herself as an idol in a club. But will the work lead to her fulfilment of the heart or not?</p>",
      "vod_play_from": "dbm3u8",
      "vod_play_server": "no",
      "vod_play_note": "",
      "vod_play_url": "HD$https://b3.bdzybf22.com/videos/202607/05/6a4a4ffb2394fd5f7050c95f/g2b4e5/index.m3u8",
      "vod_down_from": "",
      "vod_down_server": "",
      "vod_down_note": "",
      "vod_down_url": "",
      "vod_plot": 0,
      "vod_plot_name": "",
      "vod_plot_detail": "",
      "type_name": "喜剧片",
      "source_category_id": "12",
      "source_category_name": "喜剧片",
      "_sourceSlug": "baidu",
      "_sourceShort": "百度",
      "source_url": "https://api.apibdzy.com/api.php/provide/vod/",
      "canonical_id": "meta:%E6%9C%80%E8%90%8C%E5%8D%A7%E5%BA%95:2020:0:aekasitsompech",
      "primary_category": "other_movie",
      "movie_release_channel": "unknown",
      "classification_evidence": [
        {
          "source": "source_category_id",
          "priority": 1,
          "category": "other_movie",
          "field": "source_category_id",
          "value": "12",
          "signal": "other_movie"
        }
      ],
      "classification_confidence": 0.99,
      "classification_confidence_level": "high",
      "classification_confidence_score": 0.99,
      "source_candidates": [
        {
          "source": "baidu",
          "id": "50121",
          "url": "https://api.apibdzy.com/api.php/provide/vod/",
          "updated_at": ""
        }
      ],
      "play_lines": [
        {
          "source": "baidu",
          "name": "dbm3u8",
          "url": "HD$https://b3.bdzybf22.com/videos/202607/05/6a4a4ffb2394fd5f7050c95f/g2b4e5/index.m3u8"
        }
      ],
      "semantic_tags": "class 喜剧 类型",
      "snapshot_filter_evidence": "catalog-derived"
    },
    {
      "vod_id": "agg_W3sicyI6InRhb3BpYW4iLCJpZCI6IjgzNDk5In1d",
      "vod_name": "不加滤镜",
      "vod_sub": "No Filter,親友現實批(台)",
      "vod_remarks": "",
      "vod_serial": "1",
      "type_id": "15007744",
      "vod_actor": "何塞·加西亚/安·玛丽文/亚历山德拉·拉米/迈克尔·扬",
      "vod_director": "Eric Lavaine",
      "vod_pic": "https://taopianimage.xyz:43333/e79a2932fbd9.jpg",
      "vod_content": "碧翠絲的新書出版了，書中記錄了她老公的不幸意外，也提及她最好的一群朋友。那場意外徹底改變了他們的生活。碧翠絲沒想到的是，這本書竟會引來一場風暴。雖然她已使用虛構的角色名字，但好友們仍然紛紛對號入座，彼此間的感情也因此出現了裂痕。究竟這場暴風雨之後會不會出現晴天呢？",
      "vod_time": "2025-03-22 00:00:00",
      "vod_area": "法国",
      "vod_lang": "法语",
      "vod_year": 2019,
      "type_name": "电影/喜剧片",
      "vod_keywords": "何塞·加西亚,安·玛丽文,亚历山德拉·拉米,迈克尔·扬,Eric Lavaine,喜剧片,何塞·加西亚,安·玛丽文,亚历山德拉·拉米,迈克尔·扬,法语,法语,喜剧,不加滤镜",
      "vod_tag": "喜剧",
      "vod_play_server": "",
      "vod_play_from": "tpm3u8$$$tpiframe",
      "vod_play_url": "不加滤镜$https://m1.taopianplay1.com:43333/c56b1bc09da3/HD/2023-02-06/1/e79a2932fbd9/45fc854c0eb6/playlist.m3u8$$$不加滤镜$https://www.tpvod.com/player.html?uri=https%3A%2F%2Fm1.taopianplay1.com%3A43333%2Fc56b1bc09da3%2FHD%2F2023-02-06%2F1%2Fe79a2932fbd9%2F45fc854c0eb6%2Fplaylist.m3u8",
      "vod_play_note": "",
      "vod_down_server": "",
      "vod_down_from": "tpm3u8$$$tpiframe",
      "vod_down_url": "不加滤镜$https://m1.taopianplay1.com:43333/c56b1bc09da3/HD/2023-02-06/1/e79a2932fbd9/45fc854c0eb6/playlist.m3u8$$$不加滤镜$https://www.tpvod.com/player.html?uri=https%3A%2F%2Fm1.taopianplay1.com%3A43333%2Fc56b1bc09da3%2FHD%2F2023-02-06%2F1%2Fe79a2932fbd9%2F45fc854c0eb6%2Fplaylist.m3u8",
      "vod_down_note": "",
      "vod_length": 6060,
      "vod_weekday": "周一",
      "vod_copyright": "",
      "vod_state_": 1,
      "vod_version": "高清版",
      "vod_tv": "",
      "vod_total": "1",
      "vod_continu": 0,
      "vod_status": 1,
      "vod_stars": 0,
      "vod_hits": 0,
      "vod_isend": 0,
      "vod_douban_id": 0,
      "list_name": "电影/喜剧片",
      "imdb": 5.9,
      "extra_type": "",
      "origin": "tpm3u8$$$tpiframe",
      "vod_state": "",
      "vod_duration": "101",
      "vod_pubdate": "2019-04-03 08:00:00",
      "vod_douban_score": 0,
      "vod_ename": "",
      "source_category_id": "12",
      "source_category_name": "电影/喜剧片",
      "_sourceSlug": "taopian",
      "_sourceShort": "淘片",
      "source_url": "https://taopianapi.com/cjapi/mc/vod/json.html",
      "vod_time_add": "",
      "canonical_id": "meta:%E4%B8%8D%E5%8A%A0%E6%BB%A4%E9%95%9C:2019:0:ericlavaine",
      "primary_category": "other_movie",
      "movie_release_channel": "unknown",
      "classification_evidence": [
        {
          "source": "source_category_id",
          "priority": 1,
          "category": "other_movie",
          "field": "source_category_id",
          "value": "12",
          "signal": "other_movie"
        }
      ],
      "classification_confidence": 0.99,
      "classification_confidence_level": "high",
      "classification_confidence_score": 0.99,
      "source_candidates": [
        {
          "source": "taopian",
          "id": "83499",
          "url": "https://taopianapi.com/cjapi/mc/vod/json.html",
          "updated_at": ""
        }
      ],
      "play_lines": [
        {
          "source": "taopian",
          "name": "tpm3u8",
          "url": "不加滤镜$https://m1.taopianplay1.com:43333/c56b1bc09da3/HD/2023-02-06/1/e79a2932fbd9/45fc854c0eb6/playlist.m3u8"
        },
        {
          "source": "taopian",
          "name": "tpiframe",
          "url": "不加滤镜$https://www.tpvod.com/player.html?uri=https%3A%2F%2Fm1.taopianplay1.com%3A43333%2Fc56b1bc09da3%2FHD%2F2023-02-06%2F1%2Fe79a2932fbd9%2F45fc854c0eb6%2Fplaylist.m3u8"
        }
      ],
      "semantic_tags": "class 喜剧 类型",
      "snapshot_filter_evidence": "catalog-derived"
    },
    {
      "vod_id": "agg_W3sicyI6InRhb3BpYW4iLCJpZCI6IjE1MzI0NTUifV0",
      "vod_name": "屠宰场准则 2018",
      "vod_sub": "",
      "vod_remarks": "",
      "vod_serial": "1",
      "type_id": "15007744",
      "vod_actor": "阿萨·巴特菲尔德/芬恩·科尔",
      "vod_director": "克利斯宾·米尔斯",
      "vod_pic": "https://taopianimage.xyz:43333/c5328abdb1e4v.jpeg",
      "vod_content": "一所英国寄宿学校附近的水力压裂地出现了一个神秘陷坑，被释放出的恐怖力量令整个学校变成了一个血腥的杀戮战场。",
      "vod_time": "2025-01-30 00:00:00",
      "vod_area": "英国",
      "vod_lang": "英语",
      "vod_year": 2018,
      "type_name": "电影/喜剧片",
      "vod_keywords": "阿萨·巴特菲尔德,芬恩·科尔,克利斯宾·米尔斯,喜剧片,阿萨·巴特菲尔德,芬恩·科尔,英语,英语,恐怖,动作,喜剧,屠宰场准则 2018",
      "vod_tag": "恐怖/动作/喜剧",
      "vod_play_server": "",
      "vod_play_from": "tpm3u8$$$tpiframe",
      "vod_play_url": "屠宰场准则 2018$https://sd8.taopianplay1.com:43333/c56b1bc09da3/HD/2025-01-30/1/c5328abdb1e4/852a364d67d2/playlist.m3u8$$$屠宰场准则 2018$https://www.tpvod.com/player.html?uri=https%3A%2F%2Fsd8.taopianplay1.com%3A43333%2Fc56b1bc09da3%2FHD%2F2025-01-30%2F1%2Fc5328abdb1e4%2F852a364d67d2%2Fplaylist.m3u8",
      "vod_play_note": "",
      "vod_down_server": "",
      "vod_down_from": "tpm3u8$$$tpiframe",
      "vod_down_url": "屠宰场准则 2018$https://sd8.taopianplay1.com:43333/c56b1bc09da3/HD/2025-01-30/1/c5328abdb1e4/852a364d67d2/playlist.m3u8$$$屠宰场准则 2018$https://www.tpvod.com/player.html?uri=https%3A%2F%2Fsd8.taopianplay1.com%3A43333%2Fc56b1bc09da3%2FHD%2F2025-01-30%2F1%2Fc5328abdb1e4%2F852a364d67d2%2Fplaylist.m3u8",
      "vod_down_note": "",
      "vod_length": 6240,
      "vod_weekday": "周一",
      "vod_copyright": "",
      "vod_state_": 1,
      "vod_version": "高清版",
      "vod_tv": "",
      "vod_total": "1",
      "vod_continu": 0,
      "vod_status": 1,
      "vod_stars": 0,
      "vod_hits": 0,
      "vod_isend": 0,
      "vod_douban_id": 0,
      "list_name": "电影/喜剧片",
      "imdb": 5.3,
      "extra_type": "",
      "origin": "tpm3u8$$$tpiframe",
      "vod_state": "",
      "vod_duration": "104",
      "vod_pubdate": "2018-10-31 00:00:00",
      "vod_douban_score": 0,
      "vod_ename": "",
      "source_category_id": "12",
      "source_category_name": "电影/喜剧片",
      "_sourceSlug": "taopian",
      "_sourceShort": "淘片",
      "source_url": "https://taopianapi.com/cjapi/mc/vod/json.html",
      "vod_time_add": "",
      "canonical_id": "meta:%E5%B1%A0%E5%AE%B0%E5%9C%BA%E5%87%86%E5%88%992018:2018:0:%E5%85%8B%E5%88%A9%E6%96%AF%E5%AE%BE%E7%B1%B3%E5%B0%94%E6%96%AF",
      "primary_category": "other_movie",
      "movie_release_channel": "unknown",
      "classification_evidence": [
        {
          "source": "source_category_id",
          "priority": 1,
          "category": "other_movie",
          "field": "source_category_id",
          "value": "12",
          "signal": "other_movie"
        }
      ],
      "classification_confidence": 0.99,
      "classification_confidence_level": "high",
      "classification_confidence_score": 0.99,
      "source_candidates": [
        {
          "source": "taopian",
          "id": "1532455",
          "url": "https://taopianapi.com/cjapi/mc/vod/json.html",
          "updated_at": ""
        }
      ],
      "play_lines": [
        {
          "source": "taopian",
          "name": "tpm3u8",
          "url": "屠宰场准则 2018$https://sd8.taopianplay1.com:43333/c56b1bc09da3/HD/2025-01-30/1/c5328abdb1e4/852a364d67d2/playlist.m3u8"
        },
        {
          "source": "taopian",
          "name": "tpiframe",
          "url": "屠宰场准则 2018$https://www.tpvod.com/player.html?uri=https%3A%2F%2Fsd8.taopianplay1.com%3A43333%2Fc56b1bc09da3%2FHD%2F2025-01-30%2F1%2Fc5328abdb1e4%2F852a364d67d2%2Fplaylist.m3u8"
        }
      ],
      "semantic_tags": "class 喜剧 类型",
      "snapshot_filter_evidence": "catalog-derived"
    },
    {
      "vod_id": "agg_W3sicyI6ImJhaWR1IiwiaWQiOiI0NTk1MiJ9XQ",
      "type_id": "11",
      "type_id_1": 1,
      "group_id": 0,
      "vod_name": "笑神穷不怕",
      "vod_sub": "",
      "vod_en": "xiaoshenqiongbupa",
      "vod_status": 1,
      "vod_letter": "X",
      "vod_color": "",
      "vod_tag": "",
      "vod_class": "",
      "vod_pic": "https://img.bdzyimg1.com/upload/vod/20250912-1/53212074d82a97478846b36efbb2de6d.jpg",
      "vod_pic_thumb": "",
      "vod_pic_slide": "",
      "vod_pic_screenshot": "",
      "vod_actor": "武宾,苏婷婷,诸燕,乔卫东,南光,王文林",
      "vod_director": "南光,吴志国",
      "vod_writer": "",
      "vod_behind": "",
      "vod_blurb": "影片讲述相声始祖朱绍文（武宾 饰）在清末不畏强权，坎坷的艺术人生。相声祖师爷朱绍文在天桥下根据字意谈古论今说笑话，每解释完一个字定能使人发笑。王府的格格爱上了朱绍文，却遭到王爷的反对，被许配到将军府。",
      "vod_remarks": "更新HD中字",
      "vod_pubdate": "",
      "vod_total": "0",
      "vod_serial": "",
      "vod_tv": "",
      "vod_weekday": "",
      "vod_area": "大陆",
      "vod_lang": "国语",
      "vod_year": "2018",
      "vod_version": "",
      "vod_state": "",
      "vod_author": "",
      "vod_jumpurl": "",
      "vod_tpl": "",
      "vod_tpl_play": "",
      "vod_tpl_down": "",
      "vod_isend": 0,
      "vod_lock": 0,
      "vod_level": 0,
      "vod_copyright": 0,
      "vod_points": 0,
      "vod_points_play": 0,
      "vod_points_down": 0,
      "vod_hits": 0,
      "vod_hits_day": 0,
      "vod_hits_week": 0,
      "vod_hits_month": 0,
      "vod_duration": "",
      "vod_up": 0,
      "vod_down": 0,
      "vod_score": "0.0",
      "vod_score_all": 0,
      "vod_score_num": 0,
      "vod_time": "2025-09-12 00:00:27",
      "vod_time_add": "1757606427",
      "vod_time_hits": 0,
      "vod_time_make": 0,
      "vod_trysee": 0,
      "vod_douban_id": 0,
      "vod_douban_score": "0.0",
      "vod_reurl": "",
      "vod_rel_vod": "",
      "vod_rel_art": "",
      "vod_pwd": "",
      "vod_pwd_url": "",
      "vod_pwd_play": "",
      "vod_pwd_play_url": "",
      "vod_pwd_down": "",
      "vod_pwd_down_url": "",
      "vod_content": "影片讲述相声始祖朱绍文（武宾 饰）在清末不畏强权，坎坷的艺术人生。相声祖师爷朱绍文在天桥下根据字意谈古论今说笑话，每解释完一个字定能使人发笑。王府的格格爱上了朱绍文，却遭到王爷的反对，被许配到将军府。王爷处处刁难陷害朱绍文，可朱绍文还是因相声红遍了北京城，被老佛爷封为天桥八大怪之首……　　本片运用演艺与事件相结合的手法，集喜剧、爱情、动作、传统文化于一身，再现相声这一门传统艺术的起源，活灵活现的展示了相声行业公认的祖师爷—朱绍文坎坷的艺术人生",
      "vod_play_from": "dbm3u8",
      "vod_play_server": "no",
      "vod_play_note": "",
      "vod_play_url": "HD中字$https://b2.bdzybf22.com/videos/202509/11/68b36ff08bcb3e0950847203/a878cc/index.m3u8",
      "vod_down_from": "",
      "vod_down_server": "",
      "vod_down_note": "",
      "vod_down_url": "",
      "vod_plot": 0,
      "vod_plot_name": "",
      "vod_plot_detail": "",
      "type_name": "剧情片",
      "source_category_id": "12",
      "source_category_name": "剧情片",
      "_sourceSlug": "baidu",
      "_sourceShort": "百度",
      "source_url": "https://api.apibdzy.com/api.php/provide/vod/",
      "canonical_id": "meta:%E7%AC%91%E7%A5%9E%E7%A9%B7%E4%B8%8D%E6%80%95:2018:0:%E5%8D%97%E5%85%89%2C%E5%90%B4%E5%BF%97%E5%9B%BD",
      "primary_category": "other_movie",
      "movie_release_channel": "unknown",
      "classification_evidence": [
        {
          "source": "source_category_id",
          "priority": 1,
          "category": "other_movie",
          "field": "source_category_id",
          "value": "12",
          "signal": "other_movie"
        }
      ],
      "classification_confidence": 0.99,
      "classification_confidence_level": "high",
      "classification_confidence_score": 0.99,
      "source_candidates": [
        {
          "source": "baidu",
          "id": "45952",
          "url": "https://api.apibdzy.com/api.php/provide/vod/",
          "updated_at": ""
        }
      ],
      "play_lines": [
        {
          "source": "baidu",
          "name": "dbm3u8",
          "url": "HD中字$https://b2.bdzybf22.com/videos/202509/11/68b36ff08bcb3e0950847203/a878cc/index.m3u8"
        }
      ],
      "semantic_tags": "class 喜剧 类型",
      "snapshot_filter_evidence": "catalog-derived"
    },
    {
      "vod_id": "agg_W3sicyI6InRhb3BpYW4iLCJpZCI6IjgwNTU1In1d",
      "vod_name": "春宵苦短，少女前进吧",
      "vod_sub": "夜短梦长，少女前进吧！(港),The Night is Short, Walk on Girl",
      "vod_remarks": "",
      "vod_serial": "1",
      "type_id": "15007744",
      "vod_actor": "花泽香菜/诹访部顺一/星野源/虎岛贵明",
      "vod_director": "汤浅政明",
      "vod_pic": "https://taopianimage.xyz:43333/2b8d83fbbb34v.jpg",
      "vod_content": "古色古香的京都，奇妙的恋爱之旅正在展开。春天，黑发少女踏上寻找伪电气白兰地的夜之旅，学长却被从天而降的锦鲤砸晕；夏天，少女在旧书市寻找心爱的童年绘本，学长则面临残酷的火锅地狱；秋天，身背红鲤鱼的少女化身不倒翁公主，与拼死出演顽固王的学长相遇在学园祭的舞台；冬天，手持梦幻感冒药的少女打倒感冒之神，与学长一起向京都的天空飞去……",
      "vod_time": "2026-01-04 00:00:00",
      "vod_area": "日本",
      "vod_lang": "日语",
      "vod_year": 2017,
      "type_name": "电影/喜剧片",
      "vod_keywords": "花泽香菜,诹访部顺一,星野源,虎岛贵明,汤浅政明,喜剧片,花泽香菜,诹访部顺一,星野源,虎岛贵明,日语,日语,动画,爱情,喜剧,奇幻,春宵苦短，少女前进吧",
      "vod_tag": "动画/爱情/喜剧/奇幻",
      "vod_play_server": "",
      "vod_play_from": "tpm3u8$$$tpiframe",
      "vod_play_url": "春宵苦短，少女前进吧$https://m1.taopianplay1.com:43333/c56b1bc09da3/HD/2023-01-09/1/2b8d83fbbb34/7d61a8c6d089/playlist.m3u8$$$春宵苦短，少女前进吧$https://www.tpvod.com/player.html?uri=https%3A%2F%2Fm1.taopianplay1.com%3A43333%2Fc56b1bc09da3%2FHD%2F2023-01-09%2F1%2F2b8d83fbbb34%2F7d61a8c6d089%2Fplaylist.m3u8",
      "vod_play_note": "",
      "vod_down_server": "",
      "vod_down_from": "tpm3u8$$$tpiframe",
      "vod_down_url": "春宵苦短，少女前进吧$https://m1.taopianplay1.com:43333/c56b1bc09da3/HD/2023-01-09/1/2b8d83fbbb34/7d61a8c6d089/playlist.m3u8$$$春宵苦短，少女前进吧$https://www.tpvod.com/player.html?uri=https%3A%2F%2Fm1.taopianplay1.com%3A43333%2Fc56b1bc09da3%2FHD%2F2023-01-09%2F1%2F2b8d83fbbb34%2F7d61a8c6d089%2Fplaylist.m3u8",
      "vod_down_note": "",
      "vod_length": 5520,
      "vod_weekday": "周一",
      "vod_copyright": "",
      "vod_state_": 1,
      "vod_version": "高清版",
      "vod_tv": "",
      "vod_total": "1",
      "vod_continu": 0,
      "vod_status": 1,
      "vod_stars": 0,
      "vod_hits": 0,
      "vod_isend": 0,
      "vod_douban_id": 0,
      "list_name": "电影/喜剧片",
      "imdb": 7.5,
      "extra_type": "",
      "origin": "tpm3u8$$$tpiframe",
      "vod_state": "",
      "vod_duration": "92",
      "vod_pubdate": "2017-04-07 08:00:00",
      "vod_douban_score": 0,
      "vod_ename": "",
      "source_category_id": "12",
      "source_category_name": "电影/喜剧片",
      "_sourceSlug": "taopian",
      "_sourceShort": "淘片",
      "source_url": "https://taopianapi.com/cjapi/mc/vod/json.html",
      "vod_time_add": "",
      "canonical_id": "meta:%E6%98%A5%E5%AE%B5%E8%8B%A6%E7%9F%AD%E5%B0%91%E5%A5%B3%E5%89%8D%E8%BF%9B%E5%90%A7:2017:0:%E6%B1%A4%E6%B5%85%E6%94%BF%E6%98%8E",
      "primary_category": "other_movie",
      "movie_release_channel": "unknown",
      "classification_evidence": [
        {
          "source": "source_category_id",
          "priority": 1,
          "category": "other_movie",
          "field": "source_category_id",
          "value": "12",
          "signal": "other_movie"
        }
      ],
      "classification_confidence": 0.99,
      "classification_confidence_level": "high",
      "classification_confidence_score": 0.99,
      "source_candidates": [
        {
          "source": "taopian",
          "id": "80555",
          "url": "https://taopianapi.com/cjapi/mc/vod/json.html",
          "updated_at": ""
        }
      ],
      "play_lines": [
        {
          "source": "taopian",
          "name": "tpm3u8",
          "url": "春宵苦短,少女前进吧$https://m1.taopianplay1.com:43333/c56b1bc09da3/HD/2023-01-09/1/2b8d83fbbb34/7d61a8c6d089/playlist.m3u8"
        },
        {
          "source": "taopian",
          "name": "tpiframe",
          "url": "春宵苦短,少女前进吧$https://www.tpvod.com/player.html?uri=https%3A%2F%2Fm1.taopianplay1.com%3A43333%2Fc56b1bc09da3%2FHD%2F2023-01-09%2F1%2F2b8d83fbbb34%2F7d61a8c6d089%2Fplaylist.m3u8"
        }
      ],
      "semantic_tags": "class 喜剧 类型",
      "snapshot_filter_evidence": "catalog-derived"
    },
    {
      "vod_id": "agg_W3sicyI6ImJhaWR1IiwiaWQiOiI0NjM0OCJ9XQ",
      "type_id": "7",
      "type_id_1": 1,
      "group_id": 0,
      "vod_name": "怪物岛(英语版)",
      "vod_sub": "",
      "vod_en": "guaiwudaoyingyuban",
      "vod_status": 1,
      "vod_letter": "G",
      "vod_color": "",
      "vod_tag": "",
      "vod_class": "",
      "vod_pic": "https://img.bdzyimg1.com/upload/vod/20250925-1/b7a02d3605276a2a7618a5c5d38a2ffb.jpg",
      "vod_pic_thumb": "",
      "vod_pic_slide": "",
      "vod_pic_screenshot": "",
      "vod_actor": "",
      "vod_director": "Leopoldo,Aguilar",
      "vod_writer": "",
      "vod_behind": "",
      "vod_blurb": "一场华丽的化妆舞会，青春小正太Lucas却吓跑了所有朋aaa。因为短短几秒钟，乖巧懂事的他变成了一个长着翅膀的超级大怪物！而他自己也被吓得张皇失措。气愤父亲隐瞒家族身世之余，Lucas偷拿到一张神秘地",
      "vod_remarks": "更新HD中字",
      "vod_pubdate": "",
      "vod_total": "0",
      "vod_serial": "",
      "vod_tv": "",
      "vod_weekday": "",
      "vod_area": "墨西哥",
      "vod_lang": "英语",
      "vod_year": "2017",
      "vod_version": "",
      "vod_state": "",
      "vod_author": "",
      "vod_jumpurl": "",
      "vod_tpl": "",
      "vod_tpl_play": "",
      "vod_tpl_down": "",
      "vod_isend": 0,
      "vod_lock": 0,
      "vod_level": 0,
      "vod_copyright": 0,
      "vod_points": 0,
      "vod_points_play": 0,
      "vod_points_down": 0,
      "vod_hits": 0,
      "vod_hits_day": 0,
      "vod_hits_week": 0,
      "vod_hits_month": 0,
      "vod_duration": "",
      "vod_up": 0,
      "vod_down": 0,
      "vod_score": "0.0",
      "vod_score_all": 0,
      "vod_score_num": 0,
      "vod_time": "2025-09-25 15:55:31",
      "vod_time_add": "1758786931",
      "vod_time_hits": 0,
      "vod_time_make": 0,
      "vod_trysee": 0,
      "vod_douban_id": 0,
      "vod_douban_score": "0.0",
      "vod_reurl": "",
      "vod_rel_vod": "",
      "vod_rel_art": "",
      "vod_pwd": "",
      "vod_pwd_url": "",
      "vod_pwd_play": "",
      "vod_pwd_play_url": "",
      "vod_pwd_down": "",
      "vod_pwd_down_url": "",
      "vod_content": "一场华丽的化妆舞会，青春小正太Lucas却吓跑了所有朋aaa。因为短短几秒钟，乖巧懂事的他变成了一个长着翅膀的超级大怪物！而他自己也被吓得张皇失措。气愤父亲隐瞒家族身世之余，Lucas偷拿到一张神秘地图，决心靠自己找到父亲偶然提及过的真正家乡——怪物岛。当他历经艰险完成远航，眼前的所有景象都足以让他目瞪口呆。可没想到，这场寻根之旅，让他找回亲人的同时，也让他自己和岛中居民陷入了一场生死大考验……",
      "vod_play_from": "dbm3u8",
      "vod_play_server": "no",
      "vod_play_note": "",
      "vod_play_url": "HD中字$https://b2.bdzybf22.com/videos/202504/13/67edf914296ce36fb75b763e/5f26db/index.m3u8",
      "vod_down_from": "",
      "vod_down_server": "",
      "vod_down_note": "",
      "vod_down_url": "",
      "vod_plot": 0,
      "vod_plot_name": "",
      "vod_plot_detail": "",
      "type_name": "喜剧片",
      "source_category_id": "12",
      "source_category_name": "喜剧片",
      "_sourceSlug": "baidu",
      "_sourceShort": "百度",
      "source_url": "https://api.apibdzy.com/api.php/provide/vod/",
      "canonical_id": "meta:%E6%80%AA%E7%89%A9%E5%B2%9B%E8%8B%B1%E8%AF%AD%E7%89%88:2017:0:aguilar%2Cleopoldo",
      "primary_category": "other_movie",
      "movie_release_channel": "unknown",
      "classification_evidence": [
        {
          "source": "source_category_id",
          "priority": 1,
          "category": "other_movie",
          "field": "source_category_id",
          "value": "12",
          "signal": "other_movie"
        }
      ],
      "classification_confidence": 0.99,
      "classification_confidence_level": "high",
      "classification_confidence_score": 0.99,
      "source_candidates": [
        {
          "source": "baidu",
          "id": "46348",
          "url": "https://api.apibdzy.com/api.php/provide/vod/",
          "updated_at": ""
        }
      ],
      "play_lines": [
        {
          "source": "baidu",
          "name": "dbm3u8",
          "url": "HD中字$https://b2.bdzybf22.com/videos/202504/13/67edf914296ce36fb75b763e/5f26db/index.m3u8"
        }
      ],
      "semantic_tags": "class 喜剧 类型",
      "snapshot_filter_evidence": "catalog-derived"
    },
    {
      "vod_id": "agg_W3sicyI6ImJhaWR1IiwiaWQiOiI0NjE4MSJ9XQ",
      "type_id": "11",
      "type_id_1": 1,
      "group_id": 0,
      "vod_name": "疯狂的钥匙",
      "vod_sub": "",
      "vod_en": "fengkuangdeyuechi",
      "vod_status": 1,
      "vod_letter": "F",
      "vod_color": "",
      "vod_tag": "",
      "vod_class": "",
      "vod_pic": "https://img.bdzyimg1.com/upload/vod/20250917-1/cc7857de1925db3c51cfe147ba11315b.jpg",
      "vod_pic_thumb": "",
      "vod_pic_slide": "",
      "vod_pic_screenshot": "",
      "vod_actor": "陈秋实,张洋,李宝松,甘晟泽,沈鑫",
      "vod_director": "郑文宇",
      "vod_writer": "",
      "vod_behind": "",
      "vod_blurb": "一群三流演员，一个骗子导演和一个心怀不轨的制片人，荒废的旧工厂，空白的剧本，晃晃悠悠的摄像。一场荒诞的喜剧，就此展开。",
      "vod_remarks": "更新HD中字",
      "vod_pubdate": "",
      "vod_total": "0",
      "vod_serial": "",
      "vod_tv": "",
      "vod_weekday": "",
      "vod_area": "大陆",
      "vod_lang": "国语",
      "vod_year": "2016",
      "vod_version": "",
      "vod_state": "",
      "vod_author": "",
      "vod_jumpurl": "",
      "vod_tpl": "",
      "vod_tpl_play": "",
      "vod_tpl_down": "",
      "vod_isend": 0,
      "vod_lock": 0,
      "vod_level": 0,
      "vod_copyright": 0,
      "vod_points": 0,
      "vod_points_play": 0,
      "vod_points_down": 0,
      "vod_hits": 0,
      "vod_hits_day": 0,
      "vod_hits_week": 0,
      "vod_hits_month": 0,
      "vod_duration": "",
      "vod_up": 0,
      "vod_down": 0,
      "vod_score": "0.0",
      "vod_score_all": 0,
      "vod_score_num": 0,
      "vod_time": "2025-09-17 06:46:51",
      "vod_time_add": "1758062811",
      "vod_time_hits": 0,
      "vod_time_make": 0,
      "vod_trysee": 0,
      "vod_douban_id": 0,
      "vod_douban_score": "0.0",
      "vod_reurl": "",
      "vod_rel_vod": "",
      "vod_rel_art": "",
      "vod_pwd": "",
      "vod_pwd_url": "",
      "vod_pwd_play": "",
      "vod_pwd_play_url": "",
      "vod_pwd_down": "",
      "vod_pwd_down_url": "",
      "vod_content": "一群三流演员，一个骗子导演和一个心怀不轨的制片人，荒废的旧工厂，空白的剧本，晃晃悠悠的摄像。一场荒诞的喜剧，就此展开。",
      "vod_play_from": "dbm3u8",
      "vod_play_server": "no",
      "vod_play_note": "",
      "vod_play_url": "HD中字$https://b2.bdzybf22.com/videos/202509/17/68b1a2f613363f094666b88c/11e67g/index.m3u8",
      "vod_down_from": "",
      "vod_down_server": "",
      "vod_down_note": "",
      "vod_down_url": "",
      "vod_plot": 0,
      "vod_plot_name": "",
      "vod_plot_detail": "",
      "type_name": "剧情片",
      "source_category_id": "12",
      "source_category_name": "剧情片",
      "_sourceSlug": "baidu",
      "_sourceShort": "百度",
      "source_url": "https://api.apibdzy.com/api.php/provide/vod/",
      "canonical_id": "meta:%E7%96%AF%E7%8B%82%E7%9A%84%E9%92%A5%E5%8C%99:2016:0:%E9%83%91%E6%96%87%E5%AE%87",
      "primary_category": "other_movie",
      "movie_release_channel": "unknown",
      "classification_evidence": [
        {
          "source": "source_category_id",
          "priority": 1,
          "category": "other_movie",
          "field": "source_category_id",
          "value": "12",
          "signal": "other_movie"
        }
      ],
      "classification_confidence": 0.99,
      "classification_confidence_level": "high",
      "classification_confidence_score": 0.99,
      "source_candidates": [
        {
          "source": "baidu",
          "id": "46181",
          "url": "https://api.apibdzy.com/api.php/provide/vod/",
          "updated_at": ""
        }
      ],
      "play_lines": [
        {
          "source": "baidu",
          "name": "dbm3u8",
          "url": "HD中字$https://b2.bdzybf22.com/videos/202509/17/68b1a2f613363f094666b88c/11e67g/index.m3u8"
        }
      ],
      "semantic_tags": "class 喜剧 类型",
      "snapshot_filter_evidence": "catalog-derived"
    },
    {
      "vod_id": "agg_W3sicyI6ImJhaWR1IiwiaWQiOiI0NjYzNSJ9XQ",
      "type_id": "7",
      "type_id_1": 1,
      "group_id": 0,
      "vod_name": "圣诞屠杀夜",
      "vod_sub": "",
      "vod_en": "shengdantushaye",
      "vod_status": 1,
      "vod_letter": "S",
      "vod_color": "",
      "vod_tag": "",
      "vod_class": "",
      "vod_pic": "https://img.bdzyimg1.com/upload/vod/20251010-1/8297bf41e361c96479a98b6fc9d7c15b.jpg",
      "vod_pic_thumb": "",
      "vod_pic_slide": "",
      "vod_pic_screenshot": "",
      "vod_actor": "Annette Wozniak,Geoff Almond,Keegan Chambers,Brent Baird,Nicole Kawalez",
      "vod_director": "Mike McMurran",
      "vod_writer": "",
      "vod_behind": "",
      "vod_blurb": "Secret Santa is a feature length film that tells the story of a group of eccentric college kids, str",
      "vod_remarks": "更新HD",
      "vod_pubdate": "",
      "vod_total": "0",
      "vod_serial": "",
      "vod_tv": "",
      "vod_weekday": "",
      "vod_area": "加拿大Canada",
      "vod_lang": "英语",
      "vod_year": "2015",
      "vod_version": "",
      "vod_state": "",
      "vod_author": "",
      "vod_jumpurl": "",
      "vod_tpl": "",
      "vod_tpl_play": "",
      "vod_tpl_down": "",
      "vod_isend": 0,
      "vod_lock": 0,
      "vod_level": 0,
      "vod_copyright": 0,
      "vod_points": 0,
      "vod_points_play": 0,
      "vod_points_down": 0,
      "vod_hits": 0,
      "vod_hits_day": 0,
      "vod_hits_week": 0,
      "vod_hits_month": 0,
      "vod_duration": "",
      "vod_up": 0,
      "vod_down": 0,
      "vod_score": "0.0",
      "vod_score_all": 0,
      "vod_score_num": 0,
      "vod_time": "2025-10-10 04:00:29",
      "vod_time_add": "1760040029",
      "vod_time_hits": 0,
      "vod_time_make": 0,
      "vod_trysee": 0,
      "vod_douban_id": 0,
      "vod_douban_score": "0.0",
      "vod_reurl": "",
      "vod_rel_vod": "",
      "vod_rel_art": "",
      "vod_pwd": "",
      "vod_pwd_url": "",
      "vod_pwd_play": "",
      "vod_pwd_play_url": "",
      "vod_pwd_down": "",
      "vod_pwd_down_url": "",
      "vod_content": "<p>Secret Santa is a feature length film that tells the story of a group of eccentric college kids, struggling to get through the hectic exam period. This Horror/Comedy is a tribute to B-Movie Slashers but also takes the conventions and turns them upside down. A liquor filled party is planned. Adding a Secret Santa exchange for fun. Little do our characters know... A killer is in ...</p>",
      "vod_play_from": "dbm3u8",
      "vod_play_server": "no",
      "vod_play_note": "",
      "vod_play_url": "HD$https://b2.bdzybf22.com/videos/202510/10/68e802c89364de088850425f/a7g8ae/index.m3u8",
      "vod_down_from": "",
      "vod_down_server": "",
      "vod_down_note": "",
      "vod_down_url": "",
      "vod_plot": 0,
      "vod_plot_name": "",
      "vod_plot_detail": "",
      "type_name": "喜剧片",
      "source_category_id": "12",
      "source_category_name": "喜剧片",
      "_sourceSlug": "baidu",
      "_sourceShort": "百度",
      "source_url": "https://api.apibdzy.com/api.php/provide/vod/",
      "canonical_id": "meta:%E5%9C%A3%E8%AF%9E%E5%B1%A0%E6%9D%80%E5%A4%9C:2015:0:mikemcmurran",
      "primary_category": "other_movie",
      "movie_release_channel": "unknown",
      "classification_evidence": [
        {
          "source": "source_category_id",
          "priority": 1,
          "category": "other_movie",
          "field": "source_category_id",
          "value": "12",
          "signal": "other_movie"
        }
      ],
      "classification_confidence": 0.99,
      "classification_confidence_level": "high",
      "classification_confidence_score": 0.99,
      "source_candidates": [
        {
          "source": "baidu",
          "id": "46635",
          "url": "https://api.apibdzy.com/api.php/provide/vod/",
          "updated_at": ""
        }
      ],
      "play_lines": [
        {
          "source": "baidu",
          "name": "dbm3u8",
          "url": "HD$https://b2.bdzybf22.com/videos/202510/10/68e802c89364de088850425f/a7g8ae/index.m3u8"
        }
      ],
      "semantic_tags": "class 喜剧 类型",
      "snapshot_filter_evidence": "catalog-derived"
    },
    {
      "vod_id": "agg_W3sicyI6ImJhaWR1IiwiaWQiOiI1MDEwMyJ9XQ",
      "type_id": "7",
      "type_id_1": 1,
      "group_id": 0,
      "vod_name": "我们的未来",
      "vod_sub": "",
      "vod_en": "womendeweilai",
      "vod_status": 1,
      "vod_letter": "W",
      "vod_color": "",
      "vod_tag": "",
      "vod_class": "",
      "vod_pic": "https://img.bdzyimg1.com/upload/vod/20260705-1/199d5f48b0dfd67b2aa40b5e1d994a42.jpg",
      "vod_pic_thumb": "",
      "vod_pic_slide": "",
      "vod_pic_screenshot": "",
      "vod_actor": "皮埃尔·罗谢夫,皮奥·马麦,梅兰妮·贝尔内尔,凯恩·科贾迪,卡米尔·科坦,洛朗斯·阿尔内,罗克珊·梅斯基达,米沙·莱斯科特,奥雷利昂·维依科,让-皮耶·罗利特,Estéban,马克西姆·德瑞森,Ulysse,Teytaud,塞缪尔·泰斯,Angélique,Pleau,汤姆·诺姆贝尔,阿贝尔·贾夫里,梅琳·杜波瓦,扎布·布雷特曼,阿克塞勒·奥赫扬,Vincent,Jasinskij",
      "vod_director": "雷米·贝占松",
      "vod_writer": "",
      "vod_behind": "",
      "vod_blurb": "亚纳继承了父亲的保险经纪公司，有一个关心他的妻子，却还是过得不快乐。在一次生日会上，妻子埃斯特勒找出了他以前的照片，勾起了他年轻时的回忆。",
      "vod_remarks": "更新HD",
      "vod_pubdate": "",
      "vod_total": "0",
      "vod_serial": "",
      "vod_tv": "",
      "vod_weekday": "",
      "vod_area": "法国",
      "vod_lang": "法语",
      "vod_year": "2015",
      "vod_version": "",
      "vod_state": "",
      "vod_author": "",
      "vod_jumpurl": "",
      "vod_tpl": "",
      "vod_tpl_play": "",
      "vod_tpl_down": "",
      "vod_isend": 0,
      "vod_lock": 0,
      "vod_level": 0,
      "vod_copyright": 0,
      "vod_points": 0,
      "vod_points_play": 0,
      "vod_points_down": 0,
      "vod_hits": 0,
      "vod_hits_day": 0,
      "vod_hits_week": 0,
      "vod_hits_month": 0,
      "vod_duration": "",
      "vod_up": 0,
      "vod_down": 0,
      "vod_score": "0.0",
      "vod_score_all": 0,
      "vod_score_num": 0,
      "vod_time": "2026-07-05 04:06:15",
      "vod_time_add": "1783195575",
      "vod_time_hits": 0,
      "vod_time_make": 0,
      "vod_trysee": 0,
      "vod_douban_id": 0,
      "vod_douban_score": "0.0",
      "vod_reurl": "",
      "vod_rel_vod": "",
      "vod_rel_art": "",
      "vod_pwd": "",
      "vod_pwd_url": "",
      "vod_pwd_play": "",
      "vod_pwd_play_url": "",
      "vod_pwd_down": "",
      "vod_pwd_down_url": "",
      "vod_content": "<p>亚纳继承了父亲的保险经纪公司，有一个关心他的妻子，却还是过得不快乐。在一次生日会上，妻子埃斯特勒找出了他以前的照片，勾起了他年轻时的回忆。</p>",
      "vod_play_from": "dbm3u8",
      "vod_play_server": "no",
      "vod_play_note": "",
      "vod_play_url": "HD$https://b3.bdzybf22.com/videos/202607/05/6a4957b09ed9215f5840e131/6f7974/index.m3u8",
      "vod_down_from": "",
      "vod_down_server": "",
      "vod_down_note": "",
      "vod_down_url": "",
      "vod_plot": 0,
      "vod_plot_name": "",
      "vod_plot_detail": "",
      "type_name": "喜剧片",
      "source_category_id": "12",
      "source_category_name": "喜剧片",
      "_sourceSlug": "baidu",
      "_sourceShort": "百度",
      "source_url": "https://api.apibdzy.com/api.php/provide/vod/",
      "canonical_id": "meta:%E6%88%91%E4%BB%AC%E7%9A%84%E6%9C%AA%E6%9D%A5:2015:0:%E9%9B%B7%E7%B1%B3%E8%B4%9D%E5%8D%A0%E6%9D%BE",
      "primary_category": "other_movie",
      "movie_release_channel": "unknown",
      "classification_evidence": [
        {
          "source": "source_category_id",
          "priority": 1,
          "category": "other_movie",
          "field": "source_category_id",
          "value": "12",
          "signal": "other_movie"
        }
      ],
      "classification_confidence": 0.99,
      "classification_confidence_level": "high",
      "classification_confidence_score": 0.99,
      "source_candidates": [
        {
          "source": "baidu",
          "id": "50103",
          "url": "https://api.apibdzy.com/api.php/provide/vod/",
          "updated_at": ""
        }
      ],
      "play_lines": [
        {
          "source": "baidu",
          "name": "dbm3u8",
          "url": "HD$https://b3.bdzybf22.com/videos/202607/05/6a4957b09ed9215f5840e131/6f7974/index.m3u8"
        }
      ],
      "semantic_tags": "class 喜剧 类型",
      "snapshot_filter_evidence": "catalog-derived"
    },
    {
      "vod_id": "agg_W3sicyI6ImJhaWR1IiwiaWQiOiI0NjQ3OSJ9XQ",
      "type_id": "11",
      "type_id_1": 1,
      "group_id": 0,
      "vod_name": "我们都是超能力者番外篇：超能力者进城",
      "vod_sub": "",
      "vod_en": "womendushichaonenglizhefanwaipianchaonenglizhejincheng",
      "vod_status": 1,
      "vod_letter": "W",
      "vod_color": "",
      "vod_tag": "",
      "vod_class": "",
      "vod_pic": "https://img.bdzyimg1.com/upload/vod/20251004-1/cbb0207b16ebdce6609466d014f80de2.jpg",
      "vod_pic_thumb": "",
      "vod_pic_slide": "",
      "vod_pic_screenshot": "",
      "vod_actor": "染谷将太,真野惠里菜,槙田雄司,深水元基,柾木玲弥,神乐坂惠,安田显,北原里英,片桐仁,桥本爱实,平冈亚希,樱井由纪",
      "vod_director": "园子温",
      "vod_writer": "",
      "vod_behind": "",
      "vod_blurb": "平凡的高中生突然能使用超能力听到别人心声的科幻喜剧，这次番外篇中主角嘉郎收到在东京上学的浅见沙英求救信件，转校前往东京的嘉郎却陷入了意想不到的高中各派阀斗争之中",
      "vod_remarks": "更新HD",
      "vod_pubdate": "",
      "vod_total": "0",
      "vod_serial": "",
      "vod_tv": "",
      "vod_weekday": "",
      "vod_area": "日本",
      "vod_lang": "日语",
      "vod_year": "2015",
      "vod_version": "",
      "vod_state": "",
      "vod_author": "",
      "vod_jumpurl": "",
      "vod_tpl": "",
      "vod_tpl_play": "",
      "vod_tpl_down": "",
      "vod_isend": 0,
      "vod_lock": 0,
      "vod_level": 0,
      "vod_copyright": 0,
      "vod_points": 0,
      "vod_points_play": 0,
      "vod_points_down": 0,
      "vod_hits": 0,
      "vod_hits_day": 0,
      "vod_hits_week": 0,
      "vod_hits_month": 0,
      "vod_duration": "",
      "vod_up": 0,
      "vod_down": 0,
      "vod_score": "0.0",
      "vod_score_all": 0,
      "vod_score_num": 0,
      "vod_time": "2025-10-04 06:57:05",
      "vod_time_add": "1759532225",
      "vod_time_hits": 0,
      "vod_time_make": 0,
      "vod_trysee": 0,
      "vod_douban_id": 0,
      "vod_douban_score": "0.0",
      "vod_reurl": "",
      "vod_rel_vod": "",
      "vod_rel_art": "",
      "vod_pwd": "",
      "vod_pwd_url": "",
      "vod_pwd_play": "",
      "vod_pwd_play_url": "",
      "vod_pwd_down": "",
      "vod_pwd_down_url": "",
      "vod_content": "<p>平凡的高中生突然能使用超能力听到别人心声的科幻喜剧，这次番外篇中主角嘉郎收到在东京上学的浅见沙英求救信件，转校前往东京的嘉郎却陷入了意想不到的高中各派阀斗争之中</p>",
      "vod_play_from": "dbm3u8",
      "vod_play_server": "no",
      "vod_play_note": "",
      "vod_play_url": "HD$https://b2.bdzybf22.com/videos/202510/04/68e051d39364de088833592f/cb3536/index.m3u8",
      "vod_down_from": "",
      "vod_down_server": "",
      "vod_down_note": "",
      "vod_down_url": "",
      "vod_plot": 0,
      "vod_plot_name": "",
      "vod_plot_detail": "",
      "type_name": "剧情片",
      "source_category_id": "12",
      "source_category_name": "剧情片",
      "_sourceSlug": "baidu",
      "_sourceShort": "百度",
      "source_url": "https://api.apibdzy.com/api.php/provide/vod/",
      "canonical_id": "meta:%E6%88%91%E4%BB%AC%E9%83%BD%E6%98%AF%E8%B6%85%E8%83%BD%E5%8A%9B%E8%80%85%E7%95%AA%E5%A4%96%E7%AF%87%E8%B6%85%E8%83%BD%E5%8A%9B%E8%80%85%E8%BF%9B%E5%9F%8E:2015:0:%E5%9B%AD%E5%AD%90%E6%B8%A9",
      "primary_category": "other_movie",
      "movie_release_channel": "unknown",
      "classification_evidence": [
        {
          "source": "source_category_id",
          "priority": 1,
          "category": "other_movie",
          "field": "source_category_id",
          "value": "12",
          "signal": "other_movie"
        }
      ],
      "classification_confidence": 0.99,
      "classification_confidence_level": "high",
      "classification_confidence_score": 0.99,
      "source_candidates": [
        {
          "source": "baidu",
          "id": "46479",
          "url": "https://api.apibdzy.com/api.php/provide/vod/",
          "updated_at": ""
        }
      ],
      "play_lines": [
        {
          "source": "baidu",
          "name": "dbm3u8",
          "url": "HD$https://b2.bdzybf22.com/videos/202510/04/68e051d39364de088833592f/cb3536/index.m3u8"
        }
      ],
      "semantic_tags": "class 喜剧 类型",
      "snapshot_filter_evidence": "catalog-derived"
    },
    {
      "vod_id": "agg_W3sicyI6InRhb3BpYW4iLCJpZCI6IjE1MzI3MDMifV0",
      "vod_name": "有种你爱我",
      "vod_sub": "一夜种马,One Night Stud",
      "vod_remarks": "",
      "vod_serial": "1",
      "type_id": "15007744",
      "vod_actor": "江一燕/郑恺/于笑",
      "vod_director": "李欣蔓",
      "vod_pic": "https://taopianimage.xyz:43333/0941eb61eea4v.jpeg",
      "vod_content": "左小欣（江一燕 饰）是一位小有名气的建筑师，快乐充实而又衣食无忧的生活让她无需拿婚姻当“饭碗”，目睹过感情脆弱的她对男人亦失去了最基本的信任。然而，随着时间的推移，左小欣想要一个孩子了，如何跳过“男人”和“婚姻”得到“孩子”？这成为了左小欣目前正在研究的最大难题。\n　　一次偶然中，左小欣结识了名叫查义（郑凯 饰）节目主持人，一来二去之中，左小欣的腹中怀上了查义的骨肉，然而对于这一切以及左小欣的“阴谋”，单纯懵懂的查义一无所知。一晃眼一年过去，左小欣将一切的真相告诉了查义，在震惊和愤怒的同时，血浓于水的亲情亦在查义的内心中荡漾开来。",
      "vod_time": "2025-02-21 00:00:00",
      "vod_area": "中国大陆",
      "vod_lang": "汉语普通话",
      "vod_year": 2015,
      "type_name": "电影/喜剧片",
      "vod_keywords": "江一燕,郑恺,于笑,李欣蔓,喜剧片,江一燕,郑恺,于笑,汉语普通话,汉语普通话,爱情,喜剧,有种你爱我",
      "vod_tag": "爱情/喜剧",
      "vod_play_server": "",
      "vod_play_from": "tpm3u8$$$tpiframe",
      "vod_play_url": "有种你爱我$https://sd8.taopianplay1.com:43333/c56b1bc09da3/HD/2025-02-21/1/0941eb61eea4/955fd60def7f/playlist.m3u8$$$有种你爱我$https://www.tpvod.com/player.html?uri=https%3A%2F%2Fsd8.taopianplay1.com%3A43333%2Fc56b1bc09da3%2FHD%2F2025-02-21%2F1%2F0941eb61eea4%2F955fd60def7f%2Fplaylist.m3u8",
      "vod_play_note": "",
      "vod_down_server": "",
      "vod_down_from": "tpm3u8$$$tpiframe",
      "vod_down_url": "有种你爱我$https://sd8.taopianplay1.com:43333/c56b1bc09da3/HD/2025-02-21/1/0941eb61eea4/955fd60def7f/playlist.m3u8$$$有种你爱我$https://www.tpvod.com/player.html?uri=https%3A%2F%2Fsd8.taopianplay1.com%3A43333%2Fc56b1bc09da3%2FHD%2F2025-02-21%2F1%2F0941eb61eea4%2F955fd60def7f%2Fplaylist.m3u8",
      "vod_down_note": "",
      "vod_length": 6360,
      "vod_weekday": "周一",
      "vod_copyright": "",
      "vod_state_": 1,
      "vod_version": "高清版",
      "vod_tv": "",
      "vod_total": "1",
      "vod_continu": 0,
      "vod_status": 1,
      "vod_stars": 0,
      "vod_hits": 0,
      "vod_isend": 0,
      "vod_douban_id": 0,
      "list_name": "电影/喜剧片",
      "imdb": 4.9,
      "extra_type": "",
      "origin": "tpm3u8$$$tpiframe",
      "vod_state": "",
      "vod_duration": "106",
      "vod_pubdate": "2015-02-06 00:00:00",
      "vod_douban_score": 0,
      "vod_ename": "",
      "source_category_id": "12",
      "source_category_name": "电影/喜剧片",
      "_sourceSlug": "taopian",
      "_sourceShort": "淘片",
      "source_url": "https://taopianapi.com/cjapi/mc/vod/json.html",
      "vod_time_add": "",
      "canonical_id": "meta:%E6%9C%89%E7%A7%8D%E4%BD%A0%E7%88%B1%E6%88%91:2015:0:%E6%9D%8E%E6%AC%A3%E8%94%93",
      "primary_category": "other_movie",
      "movie_release_channel": "unknown",
      "classification_evidence": [
        {
          "source": "source_category_id",
          "priority": 1,
          "category": "other_movie",
          "field": "source_category_id",
          "value": "12",
          "signal": "other_movie"
        }
      ],
      "classification_confidence": 0.99,
      "classification_confidence_level": "high",
      "classification_confidence_score": 0.99,
      "source_candidates": [
        {
          "source": "taopian",
          "id": "1532703",
          "url": "https://taopianapi.com/cjapi/mc/vod/json.html",
          "updated_at": ""
        }
      ],
      "play_lines": [
        {
          "source": "taopian",
          "name": "tpm3u8",
          "url": "有种你爱我$https://sd8.taopianplay1.com:43333/c56b1bc09da3/HD/2025-02-21/1/0941eb61eea4/955fd60def7f/playlist.m3u8"
        },
        {
          "source": "taopian",
          "name": "tpiframe",
          "url": "有种你爱我$https://www.tpvod.com/player.html?uri=https%3A%2F%2Fsd8.taopianplay1.com%3A43333%2Fc56b1bc09da3%2FHD%2F2025-02-21%2F1%2F0941eb61eea4%2F955fd60def7f%2Fplaylist.m3u8"
        }
      ],
      "semantic_tags": "class 喜剧 类型",
      "snapshot_filter_evidence": "catalog-derived"
    },
    {
      "vod_id": "agg_W3sicyI6ImJhaWR1IiwiaWQiOiI0OTc1MyJ9XQ",
      "type_id": "7",
      "type_id_1": 1,
      "group_id": 0,
      "vod_name": "分手大师",
      "vod_sub": "",
      "vod_en": "fenshoudashi",
      "vod_status": 1,
      "vod_letter": "F",
      "vod_color": "",
      "vod_tag": "",
      "vod_class": "",
      "vod_pic": "https://img.bdzyimg1.com/upload/vod/20260617-1/d23424e6f758e6473d47b3fcf52e25f6.jpg",
      "vod_pic_thumb": "",
      "vod_pic_slide": "",
      "vod_pic_screenshot": "",
      "vod_actor": "邓超,杨幂,古力娜扎,栾元晖,秦越,许可嘉,梁超,赵曼竹,孙俪,柳岩,谢楠",
      "vod_director": "俞白眉,邓超",
      "vod_writer": "",
      "vod_behind": "",
      "vod_blurb": "梅远贵（邓超 饰）是一个情感经历极为丰富的男人，虽然有过这样那样的失败恋情，却也帮他铺就了一条通往荣华复归的康庄大道。现如今的梅远贵生活在首都北京，与其精英团队操办起帮人分手的奇葩业务，无论你有着怎样",
      "vod_remarks": "更新HD",
      "vod_pubdate": "",
      "vod_total": "0",
      "vod_serial": "",
      "vod_tv": "",
      "vod_weekday": "",
      "vod_area": "大陆",
      "vod_lang": "国语",
      "vod_year": "2014",
      "vod_version": "",
      "vod_state": "",
      "vod_author": "",
      "vod_jumpurl": "",
      "vod_tpl": "",
      "vod_tpl_play": "",
      "vod_tpl_down": "",
      "vod_isend": 0,
      "vod_lock": 0,
      "vod_level": 0,
      "vod_copyright": 0,
      "vod_points": 0,
      "vod_points_play": 0,
      "vod_points_down": 0,
      "vod_hits": 0,
      "vod_hits_day": 0,
      "vod_hits_week": 0,
      "vod_hits_month": 0,
      "vod_duration": "",
      "vod_up": 0,
      "vod_down": 0,
      "vod_score": "0.0",
      "vod_score_all": 0,
      "vod_score_num": 0,
      "vod_time": "2026-06-17 20:20:18",
      "vod_time_add": "1781698818",
      "vod_time_hits": 0,
      "vod_time_make": 0,
      "vod_trysee": 0,
      "vod_douban_id": 0,
      "vod_douban_score": "0.0",
      "vod_reurl": "",
      "vod_rel_vod": "",
      "vod_rel_art": "",
      "vod_pwd": "",
      "vod_pwd_url": "",
      "vod_pwd_play": "",
      "vod_pwd_play_url": "",
      "vod_pwd_down": "",
      "vod_pwd_down_url": "",
      "vod_content": "梅远贵（邓超 饰）是一个情感经历极为丰富的男人，虽然有过这样那样的失败恋情，却也帮他铺就了一条通往荣华复归的康庄大道。现如今的梅远贵生活在首都北京，与其精英团队操办起帮人分手的奇葩业务，无论你有着怎样的感情和生活，只要票子给足，他总会高效率地完成任务。爱情那么虚幻的东西太不可靠，还是钱最让他放心。这一天，梅照例接了一单生意，那就是帮客户甩掉美丽女孩叶小春（杨幂 饰）。小春是一个自强不息的北漂姑娘，她渴望可以让之依靠休息的港湾，同时也为了美好的明天奋力打拼。原本踌躇满志的梅远贵，从和小春接触的第一天起，他们彼此的人生就发生了改变……　　本片根据同名人气话剧改编。",
      "vod_play_from": "dbm3u8",
      "vod_play_server": "no",
      "vod_play_note": "",
      "vod_play_url": "HD$https://b3.bdzybf22.com/videos/202606/17/6a3282132394fd5f7045ed60/b01371/index.m3u8",
      "vod_down_from": "",
      "vod_down_server": "",
      "vod_down_note": "",
      "vod_down_url": "",
      "vod_plot": 0,
      "vod_plot_name": "",
      "vod_plot_detail": "",
      "type_name": "喜剧片",
      "source_category_id": "12",
      "source_category_name": "喜剧片",
      "_sourceSlug": "baidu",
      "_sourceShort": "百度",
      "source_url": "https://api.apibdzy.com/api.php/provide/vod/",
      "canonical_id": "meta:%E5%88%86%E6%89%8B%E5%A4%A7%E5%B8%88:2014:0:%E4%BF%9E%E7%99%BD%E7%9C%89%2C%E9%82%93%E8%B6%85",
      "primary_category": "other_movie",
      "movie_release_channel": "unknown",
      "classification_evidence": [
        {
          "source": "source_category_id",
          "priority": 1,
          "category": "other_movie",
          "field": "source_category_id",
          "value": "12",
          "signal": "other_movie"
        }
      ],
      "classification_confidence": 0.99,
      "classification_confidence_level": "high",
      "classification_confidence_score": 0.99,
      "source_candidates": [
        {
          "source": "baidu",
          "id": "49753",
          "url": "https://api.apibdzy.com/api.php/provide/vod/",
          "updated_at": ""
        }
      ],
      "play_lines": [
        {
          "source": "baidu",
          "name": "dbm3u8",
          "url": "HD$https://b3.bdzybf22.com/videos/202606/17/6a3282132394fd5f7045ed60/b01371/index.m3u8"
        }
      ],
      "semantic_tags": "class 喜剧 类型",
      "snapshot_filter_evidence": "catalog-derived"
    },
    {
      "vod_id": "agg_W3sicyI6ImJmenkiLCJpZCI6IjE1MDU4MCJ9XQ",
      "type_id": "22",
      "type_id_1": 20,
      "group_id": 0,
      "vod_name": "你的温和与可爱",
      "vod_sub": "荡女痴男",
      "vod_en": "nidewenheyukeai",
      "vod_status": 1,
      "vod_letter": "N",
      "vod_color": "",
      "vod_tag": "",
      "vod_class": "喜剧,爱情,悬疑,惊悚",
      "vod_pic": "https://img.picbf.com/upload/vod/20260629-1/8f3d0b1a78e38dad0425ae132e5416c6.webp",
      "vod_pic_thumb": "",
      "vod_pic_slide": "",
      "vod_pic_screenshot": "",
      "vod_actor": "乔·斯万博格,Sophie Traub,罗伯特·朗斯特里特,克里斯汀·思莱蒙,Matt Orme,杰夫·马斯莱特,Erica McClure,Shelley Delaney,布鲁克琳·沙克,Raleigh Shuck,Bennett Alderdice",
      "vod_director": "约瑟芬·戴克",
      "vod_writer": "约瑟芬·戴克,大卫·巴克",
      "vod_behind": "",
      "vod_blurb": "远离尘世，欲望不能升华只能释放，不过这里恍如伊甸园东，善恶到头会现形。他的欲望眼神，到这里工作的头一天便没法遏止，农场主人的女儿绽放的肉体，野外气息中特别芳香。只三人走动的空间，他眼睛碰到的，总都是她",
      "vod_remarks": "更新至HD",
      "vod_pubdate": "2014-02-07(柏林电影节)",
      "vod_total": "0",
      "vod_serial": "0",
      "vod_tv": "",
      "vod_weekday": "",
      "vod_area": "美国",
      "vod_lang": "英语",
      "vod_year": "2014",
      "vod_version": "",
      "vod_state": "",
      "vod_author": "",
      "vod_jumpurl": "",
      "vod_tpl": "",
      "vod_tpl_play": "",
      "vod_tpl_down": "",
      "vod_isend": 0,
      "vod_lock": 0,
      "vod_level": 0,
      "vod_copyright": 0,
      "vod_points": 0,
      "vod_points_play": 0,
      "vod_points_down": 0,
      "vod_hits": 457,
      "vod_hits_day": 342,
      "vod_hits_week": 86,
      "vod_hits_month": 82,
      "vod_duration": "78分钟",
      "vod_up": 282,
      "vod_down": 228,
      "vod_score": "10.0",
      "vod_score_all": 6690,
      "vod_score_num": 669,
      "vod_time": "2026-06-29 20:48:47",
      "vod_time_add": "1782737322",
      "vod_time_hits": 0,
      "vod_time_make": 0,
      "vod_trysee": 0,
      "vod_douban_id": 25824285,
      "vod_douban_score": "6.3",
      "vod_reurl": "",
      "vod_rel_vod": "",
      "vod_rel_art": "",
      "vod_pwd": "",
      "vod_pwd_url": "",
      "vod_pwd_play": "",
      "vod_pwd_play_url": "",
      "vod_pwd_down": "",
      "vod_pwd_down_url": "",
      "vod_content": "远离尘世，欲望不能升华只能释放，不过这里恍如伊甸园东，善恶到头会现形。他的欲望眼神，到这里工作的头一天便没法遏止，农场主人的女儿绽放的肉体，野外气息中特别芳香。只三人走动的空间，他眼睛碰到的，总都是她的身影。她张开大腿，解下钮扣，早料到他会偷看。谁是谁的饵，你不会清楚。镜头有时借来牛羊的眼睛，不只乱冲乱撞，而且景深浅，视野窄，他看不远却看得真，他看到她的幻象、她残忍下的温柔。虚实互通的世界，爱和残暴在两性体内体外延展又延展。",
      "vod_play_from": "bfzym3u8",
      "vod_play_server": "",
      "vod_play_note": "",
      "vod_play_url": "HD$https://v.baofeng11.com/video/nidewenheyukeai/6fa022f4cfde/index.m3u8",
      "vod_down_from": "",
      "vod_down_server": "",
      "vod_down_note": "",
      "vod_down_url": "",
      "vod_plot": 0,
      "vod_plot_name": "",
      "vod_plot_detail": "",
      "type_name": "喜剧片",
      "source_category_id": "12",
      "source_category_name": "喜剧片",
      "_sourceSlug": "bfzy",
      "_sourceShort": "暴风",
      "source_url": "https://bfzyapi.com/api.php/provide/vod/",
      "canonical_id": "ext:douban:25824285",
      "primary_category": "other_movie",
      "movie_release_channel": "unknown",
      "classification_evidence": [
        {
          "source": "source_category_id",
          "priority": 1,
          "category": "other_movie",
          "field": "source_category_id",
          "value": "12",
          "signal": "other_movie"
        }
      ],
      "classification_confidence": 0.99,
      "classification_confidence_level": "high",
      "classification_confidence_score": 0.99,
      "source_candidates": [
        {
          "source": "bfzy",
          "id": "150580",
          "url": "https://bfzyapi.com/api.php/provide/vod/",
          "updated_at": ""
        }
      ],
      "play_lines": [
        {
          "source": "bfzy",
          "name": "bfzym3u8",
          "url": "HD$https://v.baofeng11.com/video/nidewenheyukeai/6fa022f4cfde/index.m3u8"
        }
      ],
      "douban_id": "25824285",
      "external_release_metadata": {
        "id": "25824285",
        "title": "你的温和与可爱",
        "original_title": "Thou Wast Mild and Lovely",
        "subtype": "movie",
        "is_tv": false,
        "pubdate": [
          "2014-02-07(柏林电影节)"
        ],
        "release_date": [],
        "pre_release_desc": "",
        "year": "2014"
      },
      "semantic_tags": "class 喜剧 类型",
      "snapshot_filter_evidence": "catalog-derived"
    },
    {
      "vod_id": "agg_W3sicyI6ImJhaWR1IiwiaWQiOiI0OTk1MSJ9XQ",
      "type_id": "7",
      "type_id_1": 1,
      "group_id": 0,
      "vod_name": "戏曲小子",
      "vod_sub": "",
      "vod_en": "xiquxiaozi",
      "vod_status": 1,
      "vod_letter": "X",
      "vod_color": "",
      "vod_tag": "",
      "vod_class": "",
      "vod_pic": "https://img.bdzyimg1.com/upload/vod/20260628-1/7398504bdeb56898fb738d1a16e23a91.jpg",
      "vod_pic_thumb": "",
      "vod_pic_slide": "",
      "vod_pic_screenshot": "",
      "vod_actor": "罗家英,刘香慈",
      "vod_director": "Raymond·Tan",
      "vod_writer": "",
      "vod_behind": "",
      "vod_blurb": "暂无剧情简介",
      "vod_remarks": "更新HD",
      "vod_pubdate": "",
      "vod_total": "0",
      "vod_serial": "",
      "vod_tv": "",
      "vod_weekday": "",
      "vod_area": "新加坡",
      "vod_lang": "汉语普通话",
      "vod_year": "2014",
      "vod_version": "",
      "vod_state": "",
      "vod_author": "",
      "vod_jumpurl": "",
      "vod_tpl": "",
      "vod_tpl_play": "",
      "vod_tpl_down": "",
      "vod_isend": 0,
      "vod_lock": 0,
      "vod_level": 0,
      "vod_copyright": 0,
      "vod_points": 0,
      "vod_points_play": 0,
      "vod_points_down": 0,
      "vod_hits": 0,
      "vod_hits_day": 0,
      "vod_hits_week": 0,
      "vod_hits_month": 0,
      "vod_duration": "",
      "vod_up": 0,
      "vod_down": 0,
      "vod_score": "0.0",
      "vod_score_all": 0,
      "vod_score_num": 0,
      "vod_time": "2026-06-28 18:31:35",
      "vod_time_add": "1782642695",
      "vod_time_hits": 0,
      "vod_time_make": 0,
      "vod_trysee": 0,
      "vod_douban_id": 0,
      "vod_douban_score": "0.0",
      "vod_reurl": "",
      "vod_rel_vod": "",
      "vod_rel_art": "",
      "vod_pwd": "",
      "vod_pwd_url": "",
      "vod_pwd_play": "",
      "vod_pwd_play_url": "",
      "vod_pwd_down": "",
      "vod_pwd_down_url": "",
      "vod_content": "<p>暂无剧情简介</p>",
      "vod_play_from": "dbm3u8",
      "vod_play_server": "no",
      "vod_play_note": "",
      "vod_play_url": "HD$https://b3.bdzybf22.com/videos/202606/28/6a40e7032394fd5f704c95b2/5d3g50/index.m3u8",
      "vod_down_from": "",
      "vod_down_server": "",
      "vod_down_note": "",
      "vod_down_url": "",
      "vod_plot": 0,
      "vod_plot_name": "",
      "vod_plot_detail": "",
      "type_name": "喜剧片",
      "source_category_id": "12",
      "source_category_name": "喜剧片",
      "_sourceSlug": "baidu",
      "_sourceShort": "百度",
      "source_url": "https://api.apibdzy.com/api.php/provide/vod/",
      "canonical_id": "meta:%E6%88%8F%E6%9B%B2%E5%B0%8F%E5%AD%90:2014:0:raymondtan",
      "primary_category": "other_movie",
      "movie_release_channel": "unknown",
      "classification_evidence": [
        {
          "source": "source_category_id",
          "priority": 1,
          "category": "other_movie",
          "field": "source_category_id",
          "value": "12",
          "signal": "other_movie"
        }
      ],
      "classification_confidence": 0.99,
      "classification_confidence_level": "high",
      "classification_confidence_score": 0.99,
      "source_candidates": [
        {
          "source": "baidu",
          "id": "49951",
          "url": "https://api.apibdzy.com/api.php/provide/vod/",
          "updated_at": ""
        }
      ],
      "play_lines": [
        {
          "source": "baidu",
          "name": "dbm3u8",
          "url": "HD$https://b3.bdzybf22.com/videos/202606/28/6a40e7032394fd5f704c95b2/5d3g50/index.m3u8"
        }
      ],
      "semantic_tags": "class 喜剧 类型",
      "snapshot_filter_evidence": "catalog-derived"
    },
    {
      "vod_id": "agg_W3sicyI6ImJhaWR1IiwiaWQiOiI0NjUxMSJ9XQ",
      "type_id": "7",
      "type_id_1": 1,
      "group_id": 0,
      "vod_name": "白色驯鹿",
      "vod_sub": "",
      "vod_en": "baisexunlu",
      "vod_status": 1,
      "vod_letter": "B",
      "vod_color": "",
      "vod_tag": "",
      "vod_class": "",
      "vod_pic": "https://img.bdzyimg1.com/upload/vod/20251004-1/65ca2e69c27c6317e0d96ee2215d7fd8.jpg",
      "vod_pic_thumb": "",
      "vod_pic_slide": "",
      "vod_pic_screenshot": "",
      "vod_actor": "安娜·玛格丽特·霍利曼,Laura Lemar-Goldsborough,乔·斯万博格,Chris Doubek,Lydia Hyslop",
      "vod_director": "Zach Clark",
      "vod_writer": "",
      "vod_behind": "",
      "vod_blurb": "After an unexpected tragedy, Suzanne struggles to put her life back together during a sad, strange C",
      "vod_remarks": "更新HD",
      "vod_pubdate": "",
      "vod_total": "0",
      "vod_serial": "",
      "vod_tv": "",
      "vod_weekday": "",
      "vod_area": "美国",
      "vod_lang": "英语",
      "vod_year": "2013",
      "vod_version": "",
      "vod_state": "",
      "vod_author": "",
      "vod_jumpurl": "",
      "vod_tpl": "",
      "vod_tpl_play": "",
      "vod_tpl_down": "",
      "vod_isend": 0,
      "vod_lock": 0,
      "vod_level": 0,
      "vod_copyright": 0,
      "vod_points": 0,
      "vod_points_play": 0,
      "vod_points_down": 0,
      "vod_hits": 0,
      "vod_hits_day": 0,
      "vod_hits_week": 0,
      "vod_hits_month": 0,
      "vod_duration": "",
      "vod_up": 0,
      "vod_down": 0,
      "vod_score": "0.0",
      "vod_score_all": 0,
      "vod_score_num": 0,
      "vod_time": "2025-10-04 20:53:55",
      "vod_time_add": "1759582435",
      "vod_time_hits": 0,
      "vod_time_make": 0,
      "vod_trysee": 0,
      "vod_douban_id": 0,
      "vod_douban_score": "0.0",
      "vod_reurl": "",
      "vod_rel_vod": "",
      "vod_rel_art": "",
      "vod_pwd": "",
      "vod_pwd_url": "",
      "vod_pwd_play": "",
      "vod_pwd_play_url": "",
      "vod_pwd_down": "",
      "vod_pwd_down_url": "",
      "vod_content": "<p>After an unexpected tragedy, Suzanne struggles to put her life back together during a sad, strange Christmastime in suburban Virginia.</p>",
      "vod_play_from": "dbm3u8",
      "vod_play_server": "no",
      "vod_play_note": "",
      "vod_play_url": "HD$https://b2.bdzybf22.com/videos/202510/04/68e110264203f608c33ecb47/5gg2cf/index.m3u8",
      "vod_down_from": "",
      "vod_down_server": "",
      "vod_down_note": "",
      "vod_down_url": "",
      "vod_plot": 0,
      "vod_plot_name": "",
      "vod_plot_detail": "",
      "type_name": "喜剧片",
      "source_category_id": "12",
      "source_category_name": "喜剧片",
      "_sourceSlug": "baidu",
      "_sourceShort": "百度",
      "source_url": "https://api.apibdzy.com/api.php/provide/vod/",
      "canonical_id": "meta:%E7%99%BD%E8%89%B2%E9%A9%AF%E9%B9%BF:2013:0:zachclark",
      "primary_category": "other_movie",
      "movie_release_channel": "unknown",
      "classification_evidence": [
        {
          "source": "source_category_id",
          "priority": 1,
          "category": "other_movie",
          "field": "source_category_id",
          "value": "12",
          "signal": "other_movie"
        }
      ],
      "classification_confidence": 0.99,
      "classification_confidence_level": "high",
      "classification_confidence_score": 0.99,
      "source_candidates": [
        {
          "source": "baidu",
          "id": "46511",
          "url": "https://api.apibdzy.com/api.php/provide/vod/",
          "updated_at": ""
        }
      ],
      "play_lines": [
        {
          "source": "baidu",
          "name": "dbm3u8",
          "url": "HD$https://b2.bdzybf22.com/videos/202510/04/68e110264203f608c33ecb47/5gg2cf/index.m3u8"
        }
      ],
      "semantic_tags": "class 喜剧 类型",
      "snapshot_filter_evidence": "catalog-derived"
    },
    {
      "vod_id": "agg_W3sicyI6ImJhaWR1IiwiaWQiOiI0NjkxNyJ9XQ",
      "type_id": "7",
      "type_id_1": 1,
      "group_id": 0,
      "vod_name": "樱兰高校男公关部",
      "vod_sub": "",
      "vod_en": "yinglangaoxiaonangongguanbu",
      "vod_status": 1,
      "vod_letter": "Y",
      "vod_color": "",
      "vod_tag": "",
      "vod_class": "",
      "vod_pic": "https://img.bdzyimg1.com/upload/vod/20251026-1/c099ecea2746723558d4b9455410d70f.jpg",
      "vod_pic_thumb": "",
      "vod_pic_slide": "",
      "vod_pic_screenshot": "",
      "vod_actor": "川口春奈,山本裕典,竜星涼,中村昌也,千葉雄大,高木心平,高木万平,大東俊介,篠田麻里子,尼坤",
      "vod_director": "韩哲",
      "vod_writer": "",
      "vod_behind": "",
      "vod_blurb": "因为打破了号称价值高达800万日元的名贵花瓶，倒霉女孩藤冈治绯（川口春奈 饰）被迫加入由须王环（山本裕典 饰）、凤镜夜（大东骏介 饰）、常陆院光（高木心平 饰）、常陆院馨（高木万平 饰）、埴之冢光邦（",
      "vod_remarks": "更新HD",
      "vod_pubdate": "",
      "vod_total": "0",
      "vod_serial": "",
      "vod_tv": "",
      "vod_weekday": "",
      "vod_area": "日本",
      "vod_lang": "日语",
      "vod_year": "2012",
      "vod_version": "",
      "vod_state": "",
      "vod_author": "",
      "vod_jumpurl": "",
      "vod_tpl": "",
      "vod_tpl_play": "",
      "vod_tpl_down": "",
      "vod_isend": 0,
      "vod_lock": 0,
      "vod_level": 0,
      "vod_copyright": 0,
      "vod_points": 0,
      "vod_points_play": 0,
      "vod_points_down": 0,
      "vod_hits": 0,
      "vod_hits_day": 0,
      "vod_hits_week": 0,
      "vod_hits_month": 0,
      "vod_duration": "",
      "vod_up": 0,
      "vod_down": 0,
      "vod_score": "0.0",
      "vod_score_all": 0,
      "vod_score_num": 0,
      "vod_time": "2025-10-26 12:50:57",
      "vod_time_add": "1761454257",
      "vod_time_hits": 0,
      "vod_time_make": 0,
      "vod_trysee": 0,
      "vod_douban_id": 0,
      "vod_douban_score": "0.0",
      "vod_reurl": "",
      "vod_rel_vod": "",
      "vod_rel_art": "",
      "vod_pwd": "",
      "vod_pwd_url": "",
      "vod_pwd_play": "",
      "vod_pwd_play_url": "",
      "vod_pwd_down": "",
      "vod_pwd_down_url": "",
      "vod_content": "<p>因为打破了号称价值高达800万日元的名贵花瓶，倒霉女孩藤冈治绯（川口春奈 饰）被迫加入由须王环（山本裕典 饰）、凤镜夜（大东骏介 饰）、常陆院光（高木心平 饰）、常陆院馨（高木万平 饰）、埴之冢光邦（千叶雄大 饰）、铦之冢崇（中村昌也 饰）这六名系出名门的美男子组成的男公关部，每日里她与前辈们精心修饰打扮，巧妙周旋在私立樱兰学院那群高贵华丽的大小姐中间。在此期间，治绯的心中对须王环渐渐产生了好感。一年一度樱兰祭即将举行，公关部信心满满，势要在对战中拔得头筹。与此同时，美丽的米歇尔（篠田麻里子 饰）转入樱兰，她的到来似乎引起了环极大的兴趣。别样有趣的故事在樱兰拉开序幕……\r\n　　本片根据同名漫画改编，是电视剧的电影版。</p>",
      "vod_play_from": "dbm3u8",
      "vod_play_server": "no",
      "vod_play_note": "",
      "vod_play_url": "HD$https://b2.bdzybf22.com/videos/202510/26/68fd9dbd4203f608c390709a/ag93b4/index.m3u8",
      "vod_down_from": "",
      "vod_down_server": "",
      "vod_down_note": "",
      "vod_down_url": "",
      "vod_plot": 0,
      "vod_plot_name": "",
      "vod_plot_detail": "",
      "type_name": "喜剧片",
      "source_category_id": "12",
      "source_category_name": "喜剧片",
      "_sourceSlug": "baidu",
      "_sourceShort": "百度",
      "source_url": "https://api.apibdzy.com/api.php/provide/vod/",
      "canonical_id": "meta:%E6%A8%B1%E5%85%B0%E9%AB%98%E6%A0%A1%E7%94%B7%E5%85%AC%E5%85%B3%E9%83%A8:2012:0:%E9%9F%A9%E5%93%B2",
      "primary_category": "other_movie",
      "movie_release_channel": "unknown",
      "classification_evidence": [
        {
          "source": "source_category_id",
          "priority": 1,
          "category": "other_movie",
          "field": "source_category_id",
          "value": "12",
          "signal": "other_movie"
        }
      ],
      "classification_confidence": 0.99,
      "classification_confidence_level": "high",
      "classification_confidence_score": 0.99,
      "source_candidates": [
        {
          "source": "baidu",
          "id": "46917",
          "url": "https://api.apibdzy.com/api.php/provide/vod/",
          "updated_at": ""
        }
      ],
      "play_lines": [
        {
          "source": "baidu",
          "name": "dbm3u8",
          "url": "HD$https://b2.bdzybf22.com/videos/202510/26/68fd9dbd4203f608c390709a/ag93b4/index.m3u8"
        }
      ],
      "semantic_tags": "class 喜剧 类型",
      "snapshot_filter_evidence": "catalog-derived"
    },
    {
      "vod_id": "agg_W3sicyI6InRhb3BpYW4iLCJpZCI6IjE1MTU5NjYifV0",
      "vod_name": "上帝保佑美国",
      "vod_sub": "临死玩转美利坚(港),天佑美利坚",
      "vod_remarks": "",
      "vod_serial": "1",
      "type_id": "15007744",
      "vod_actor": "拉里·米勒/麦蒂·哈森/乔尔·默里/塔拉·林内·巴尔",
      "vod_director": "博卡·格德斯维特",
      "vod_pic": "https://taopianimage.xyz:43333/6768838.jpg",
      "vod_content": "中年男子弗兰克（乔尔·默里 Joel Murray 饰）对聒噪的世界深感麻木，他的生活如同一潭死水，每天浑噩度日。他对自私邻居的侵扰忍辱退让，对前妻再婚和女儿叛逆感到无奈，对不知廉耻的电视真人秀选手反感厌恶。终于被诊断出脑瘤和丢掉工作的现实把弗兰克彻底击垮。正当他想以自杀了结此生时，真人秀里贪得无厌的选秀女孩激发出了他潜藏已久的憎恨，他决定以自己的方式让正义得到伸张。于是弗兰克出门杀死了他自认为该死的邻家女孩克洛伊，这一幕被另一个女孩洛克西（塔拉·林内·巴尔 Tara Lynne Barr 饰）目睹。洛克西同样厌恶着充斥弊病的社会，她主动参与到弗兰克的杀人计划。两人携带枪支走上大街，大张旗鼓的玩起杀人游戏，成为新闻追踪的焦点……",
      "vod_time": "2024-07-11 00:00:00",
      "vod_area": "美国",
      "vod_lang": "英语",
      "vod_year": 2011,
      "type_name": "电影/喜剧片",
      "vod_keywords": "拉里·米勒,麦蒂·哈森,乔尔·默里,塔拉·林内·巴尔,博卡·格德斯维特,喜剧片,拉里·米勒,麦蒂·哈森,乔尔·默里,塔拉·林内·巴尔,英语,英语,犯罪,喜剧,上帝保佑美国",
      "vod_tag": "犯罪/喜剧",
      "vod_play_server": "",
      "vod_play_from": "tpm3u8$$$tpiframe",
      "vod_play_url": "上帝保佑美国$https://m1.taopianplay1.com:43333/c56b1bc09da3/HD/2024-07-11/1/85910ec97072/3d1d38af9a30/playlist.m3u8$$$上帝保佑美国$https://www.tpvod.com/player.html?uri=https%3A%2F%2Fm1.taopianplay1.com%3A43333%2Fc56b1bc09da3%2FHD%2F2024-07-11%2F1%2F85910ec97072%2F3d1d38af9a30%2Fplaylist.m3u8",
      "vod_play_note": "",
      "vod_down_server": "",
      "vod_down_from": "tpm3u8$$$tpiframe",
      "vod_down_url": "上帝保佑美国$https://m1.taopianplay1.com:43333/c56b1bc09da3/HD/2024-07-11/1/85910ec97072/3d1d38af9a30/playlist.m3u8$$$上帝保佑美国$https://www.tpvod.com/player.html?uri=https%3A%2F%2Fm1.taopianplay1.com%3A43333%2Fc56b1bc09da3%2FHD%2F2024-07-11%2F1%2F85910ec97072%2F3d1d38af9a30%2Fplaylist.m3u8",
      "vod_down_note": "",
      "vod_length": 6240,
      "vod_weekday": "周一",
      "vod_copyright": "",
      "vod_state_": 1,
      "vod_version": "高清版",
      "vod_tv": "",
      "vod_total": "1",
      "vod_continu": 0,
      "vod_status": 1,
      "vod_stars": 0,
      "vod_hits": 0,
      "vod_isend": 0,
      "vod_douban_id": 0,
      "list_name": "电影/喜剧片",
      "imdb": 7.1,
      "extra_type": "",
      "origin": "tpm3u8$$$tpiframe",
      "vod_state": "",
      "vod_duration": "104",
      "vod_pubdate": "2011-09-09 00:00:00",
      "vod_douban_score": 0,
      "vod_ename": "",
      "source_category_id": "12",
      "source_category_name": "电影/喜剧片",
      "_sourceSlug": "taopian",
      "_sourceShort": "淘片",
      "source_url": "https://taopianapi.com/cjapi/mc/vod/json.html",
      "vod_time_add": "",
      "canonical_id": "meta:%E4%B8%8A%E5%B8%9D%E4%BF%9D%E4%BD%91%E7%BE%8E%E5%9B%BD:2011:0:%E5%8D%9A%E5%8D%A1%E6%A0%BC%E5%BE%B7%E6%96%AF%E7%BB%B4%E7%89%B9",
      "primary_category": "other_movie",
      "movie_release_channel": "unknown",
      "classification_evidence": [
        {
          "source": "source_category_id",
          "priority": 1,
          "category": "other_movie",
          "field": "source_category_id",
          "value": "12",
          "signal": "other_movie"
        }
      ],
      "classification_confidence": 0.99,
      "classification_confidence_level": "high",
      "classification_confidence_score": 0.99,
      "source_candidates": [
        {
          "source": "taopian",
          "id": "1515966",
          "url": "https://taopianapi.com/cjapi/mc/vod/json.html",
          "updated_at": ""
        }
      ],
      "play_lines": [
        {
          "source": "taopian",
          "name": "tpm3u8",
          "url": "上帝保佑美国$https://m1.taopianplay1.com:43333/c56b1bc09da3/HD/2024-07-11/1/85910ec97072/3d1d38af9a30/playlist.m3u8"
        },
        {
          "source": "taopian",
          "name": "tpiframe",
          "url": "上帝保佑美国$https://www.tpvod.com/player.html?uri=https%3A%2F%2Fm1.taopianplay1.com%3A43333%2Fc56b1bc09da3%2FHD%2F2024-07-11%2F1%2F85910ec97072%2F3d1d38af9a30%2Fplaylist.m3u8"
        }
      ],
      "semantic_tags": "class 喜剧 类型",
      "snapshot_filter_evidence": "catalog-derived"
    },
    {
      "vod_id": "agg_W3sicyI6ImJhaWR1IiwiaWQiOiI0NTkwNyJ9XQ",
      "type_id": "11",
      "type_id_1": 1,
      "group_id": 0,
      "vod_name": "美丽的谎言",
      "vod_sub": "",
      "vod_en": "meilidehuangyan",
      "vod_status": 1,
      "vod_letter": "M",
      "vod_color": "",
      "vod_tag": "",
      "vod_class": "",
      "vod_pic": "https://img.bdzyimg1.com/upload/vod/20250911-1/217d89a4872ce451e0ef45ad1319d165.jpg",
      "vod_pic_thumb": "",
      "vod_pic_slide": "",
      "vod_pic_screenshot": "",
      "vod_actor": "Audrey,Tautou,Nathalie,Baye,Sami,Bouajila",
      "vod_director": "Pierre,Salvadori",
      "vod_writer": "",
      "vod_behind": "",
      "vod_blurb": "埃米莉·当德里厄（奥黛丽·塔图 Audrey Tautou饰），一位前卫的年轻女理发师。她独居的母亲麦蒂·当德里厄（娜塔莉·贝伊 Nathalie Baye饰）患有抑郁症。为了让母亲开心，重燃对生活的",
      "vod_remarks": "更新HD中字",
      "vod_pubdate": "",
      "vod_total": "0",
      "vod_serial": "",
      "vod_tv": "",
      "vod_weekday": "",
      "vod_area": "法国",
      "vod_lang": "法语",
      "vod_year": "2010",
      "vod_version": "",
      "vod_state": "",
      "vod_author": "",
      "vod_jumpurl": "",
      "vod_tpl": "",
      "vod_tpl_play": "",
      "vod_tpl_down": "",
      "vod_isend": 0,
      "vod_lock": 0,
      "vod_level": 0,
      "vod_copyright": 0,
      "vod_points": 0,
      "vod_points_play": 0,
      "vod_points_down": 0,
      "vod_hits": 0,
      "vod_hits_day": 0,
      "vod_hits_week": 0,
      "vod_hits_month": 0,
      "vod_duration": "",
      "vod_up": 0,
      "vod_down": 0,
      "vod_score": "0.0",
      "vod_score_all": 0,
      "vod_score_num": 0,
      "vod_time": "2025-09-11 21:20:07",
      "vod_time_add": "1757596807",
      "vod_time_hits": 0,
      "vod_time_make": 0,
      "vod_trysee": 0,
      "vod_douban_id": 0,
      "vod_douban_score": "0.0",
      "vod_reurl": "",
      "vod_rel_vod": "",
      "vod_rel_art": "",
      "vod_pwd": "",
      "vod_pwd_url": "",
      "vod_pwd_play": "",
      "vod_pwd_play_url": "",
      "vod_pwd_down": "",
      "vod_pwd_down_url": "",
      "vod_content": "埃米莉·当德里厄（奥黛丽·塔图 Audrey Tautou饰），一位前卫的年轻女理发师。她独居的母亲麦蒂·当德里厄（娜塔莉·贝伊 Nathalie Baye饰）患有抑郁症。为了让母亲开心，重燃对生活的信心，埃米莉使出浑身解数，居然给母亲写了一封激情洋溢的情书。女儿善意的谎言只是想让妈妈得到幸福，然而夹在母女间的男人吉恩（塞米·鲍亚吉拉 Sami Bouajila饰）却因为阴差阳错的误会而一头雾水。　　皮埃尔·萨尔瓦多执导的法国喜剧电影《美丽的谎言》，由古灵精怪的奥黛丽·塔图、优美高雅的娜塔莉·贝伊与塞米·鲍亚吉拉联袂主演。",
      "vod_play_from": "dbm3u8",
      "vod_play_server": "no",
      "vod_play_note": "",
      "vod_play_url": "HD中字$https://b2.bdzybf22.com/videos/202509/11/68b53ece8bcb3e0950b14310/ac5fg8/index.m3u8",
      "vod_down_from": "",
      "vod_down_server": "",
      "vod_down_note": "",
      "vod_down_url": "",
      "vod_plot": 0,
      "vod_plot_name": "",
      "vod_plot_detail": "",
      "type_name": "剧情片",
      "source_category_id": "12",
      "source_category_name": "剧情片",
      "_sourceSlug": "baidu",
      "_sourceShort": "百度",
      "source_url": "https://api.apibdzy.com/api.php/provide/vod/",
      "canonical_id": "meta:%E7%BE%8E%E4%B8%BD%E7%9A%84%E8%B0%8E%E8%A8%80:2010:0:pierre%2Csalvadori",
      "primary_category": "other_movie",
      "movie_release_channel": "unknown",
      "classification_evidence": [
        {
          "source": "source_category_id",
          "priority": 1,
          "category": "other_movie",
          "field": "source_category_id",
          "value": "12",
          "signal": "other_movie"
        }
      ],
      "classification_confidence": 0.99,
      "classification_confidence_level": "high",
      "classification_confidence_score": 0.99,
      "source_candidates": [
        {
          "source": "baidu",
          "id": "45907",
          "url": "https://api.apibdzy.com/api.php/provide/vod/",
          "updated_at": ""
        }
      ],
      "play_lines": [
        {
          "source": "baidu",
          "name": "dbm3u8",
          "url": "HD中字$https://b2.bdzybf22.com/videos/202509/11/68b53ece8bcb3e0950b14310/ac5fg8/index.m3u8"
        }
      ],
      "semantic_tags": "class 喜剧 类型",
      "snapshot_filter_evidence": "catalog-derived"
    },
    {
      "vod_id": "agg_W3sicyI6InRhb3BpYW4iLCJpZCI6IjE1MzI0NDgifV0",
      "vod_name": "即日启程",
      "vod_sub": "Set Off",
      "vod_remarks": "",
      "vod_serial": "1",
      "type_id": "15007744",
      "vod_actor": "居文沛/范伟/刘桦",
      "vod_director": "刘江",
      "vod_pic": "https://taopianimage.xyz:43333/31c9d872bc76v.jpeg",
      "vod_content": "在塞浦路斯开餐馆的中年男人老崔（范伟 饰）回国跟妻子办离婚，却发现让自己后院起火的罪魁祸首是自己的朋友。老崔得知合伙人要卖掉塞浦路斯的餐馆，情场失意的老崔只想快点回到塞浦路斯挽救自己的事业。不料倒霉的事情并没有完，在老崔前往飞机场的途中，一个醉酒的女孩子小夏（居文沛 饰）忽然拦住了老崔的乘坐的出租车，好心的老崔本想只送小夏回家，没想后面却发生了一连串事情，搞到身无分文、护照失窍，曾至衣不遮体。情急之下，老崔只得和小夏合作，相互帮助，不料一波未平，一波又起，两人历经磨难，曾至还卷入到一场盗窃国宝的阴谋之中。在相处的过程中，两人的内心似乎也种下了一颗在渐渐发芽的种子……",
      "vod_time": "2025-01-30 00:00:00",
      "vod_area": "中国大陆",
      "vod_lang": "汉语普通话",
      "vod_year": 2008,
      "type_name": "电影/喜剧片",
      "vod_keywords": "居文沛,范伟,刘桦,刘江,喜剧片,居文沛,范伟,刘桦,汉语普通话,汉语普通话,剧情,喜剧,即日启程",
      "vod_tag": "剧情/喜剧",
      "vod_play_server": "",
      "vod_play_from": "tpm3u8$$$tpiframe",
      "vod_play_url": "即日启程$https://sd8.taopianplay1.com:43333/c56b1bc09da3/HD/2025-01-30/1/31c9d872bc76/1a39687048a2/playlist.m3u8$$$即日启程$https://www.tpvod.com/player.html?uri=https%3A%2F%2Fsd8.taopianplay1.com%3A43333%2Fc56b1bc09da3%2FHD%2F2025-01-30%2F1%2F31c9d872bc76%2F1a39687048a2%2Fplaylist.m3u8",
      "vod_play_note": "",
      "vod_down_server": "",
      "vod_down_from": "tpm3u8$$$tpiframe",
      "vod_down_url": "即日启程$https://sd8.taopianplay1.com:43333/c56b1bc09da3/HD/2025-01-30/1/31c9d872bc76/1a39687048a2/playlist.m3u8$$$即日启程$https://www.tpvod.com/player.html?uri=https%3A%2F%2Fsd8.taopianplay1.com%3A43333%2Fc56b1bc09da3%2FHD%2F2025-01-30%2F1%2F31c9d872bc76%2F1a39687048a2%2Fplaylist.m3u8",
      "vod_down_note": "",
      "vod_length": 5760,
      "vod_weekday": "周一",
      "vod_copyright": "",
      "vod_state_": 1,
      "vod_version": "高清版",
      "vod_tv": "",
      "vod_total": "1",
      "vod_continu": 0,
      "vod_status": 1,
      "vod_stars": 0,
      "vod_hits": 0,
      "vod_isend": 0,
      "vod_douban_id": 0,
      "list_name": "电影/喜剧片",
      "imdb": 5.6,
      "extra_type": "",
      "origin": "tpm3u8$$$tpiframe",
      "vod_state": "",
      "vod_duration": "96",
      "vod_pubdate": "2008-09-30 00:00:00",
      "vod_douban_score": 0,
      "vod_ename": "",
      "source_category_id": "12",
      "source_category_name": "电影/喜剧片",
      "_sourceSlug": "taopian",
      "_sourceShort": "淘片",
      "source_url": "https://taopianapi.com/cjapi/mc/vod/json.html",
      "vod_time_add": "",
      "canonical_id": "meta:%E5%8D%B3%E6%97%A5%E5%90%AF%E7%A8%8B:2008:0:%E5%88%98%E6%B1%9F",
      "primary_category": "other_movie",
      "movie_release_channel": "unknown",
      "classification_evidence": [
        {
          "source": "source_category_id",
          "priority": 1,
          "category": "other_movie",
          "field": "source_category_id",
          "value": "12",
          "signal": "other_movie"
        }
      ],
      "classification_confidence": 0.99,
      "classification_confidence_level": "high",
      "classification_confidence_score": 0.99,
      "source_candidates": [
        {
          "source": "taopian",
          "id": "1532448",
          "url": "https://taopianapi.com/cjapi/mc/vod/json.html",
          "updated_at": ""
        }
      ],
      "play_lines": [
        {
          "source": "taopian",
          "name": "tpm3u8",
          "url": "即日启程$https://sd8.taopianplay1.com:43333/c56b1bc09da3/HD/2025-01-30/1/31c9d872bc76/1a39687048a2/playlist.m3u8"
        },
        {
          "source": "taopian",
          "name": "tpiframe",
          "url": "即日启程$https://www.tpvod.com/player.html?uri=https%3A%2F%2Fsd8.taopianplay1.com%3A43333%2Fc56b1bc09da3%2FHD%2F2025-01-30%2F1%2F31c9d872bc76%2F1a39687048a2%2Fplaylist.m3u8"
        }
      ],
      "semantic_tags": "class 喜剧 类型",
      "snapshot_filter_evidence": "catalog-derived"
    },
    {
      "vod_id": "agg_W3sicyI6ImJhaWR1IiwiaWQiOiI0NzkyMSJ9XQ",
      "type_id": "7",
      "type_id_1": 1,
      "group_id": 0,
      "vod_name": "精舞门",
      "vod_sub": "",
      "vod_en": "jingwumen",
      "vod_status": 1,
      "vod_letter": "J",
      "vod_color": "",
      "vod_tag": "",
      "vod_class": "",
      "vod_pic": "https://img.bdzyimg1.com/upload/vod/20260120-1/87c9db3b587227d82b3fd5e1b46ef00e.jpg",
      "vod_pic_thumb": "",
      "vod_pic_slide": "",
      "vod_pic_screenshot": "",
      "vod_actor": "范冰冰,陈小春,南贤俊,潘晓婷,杨扬,陈观泰,高敏,邢傲伟,张翰,王玥兮,吴振天,赵文琪\\t\\t\\t",
      "vod_director": "傅华阳\\t\\t\\t",
      "vod_writer": "",
      "vod_behind": "",
      "vod_blurb": "首部融合中国功夫和地道街舞，融入大量时尚要素的励志动感巨制。",
      "vod_remarks": "更新HD",
      "vod_pubdate": "",
      "vod_total": "0",
      "vod_serial": "",
      "vod_tv": "",
      "vod_weekday": "",
      "vod_area": "香港",
      "vod_lang": "粤语",
      "vod_year": "2008",
      "vod_version": "",
      "vod_state": "",
      "vod_author": "",
      "vod_jumpurl": "",
      "vod_tpl": "",
      "vod_tpl_play": "",
      "vod_tpl_down": "",
      "vod_isend": 0,
      "vod_lock": 0,
      "vod_level": 0,
      "vod_copyright": 0,
      "vod_points": 0,
      "vod_points_play": 0,
      "vod_points_down": 0,
      "vod_hits": 0,
      "vod_hits_day": 0,
      "vod_hits_week": 0,
      "vod_hits_month": 0,
      "vod_duration": "",
      "vod_up": 0,
      "vod_down": 0,
      "vod_score": "0.0",
      "vod_score_all": 0,
      "vod_score_num": 0,
      "vod_time": "2026-01-20 21:33:48",
      "vod_time_add": "1768916028",
      "vod_time_hits": 0,
      "vod_time_make": 0,
      "vod_trysee": 0,
      "vod_douban_id": 0,
      "vod_douban_score": "0.0",
      "vod_reurl": "",
      "vod_rel_vod": "",
      "vod_rel_art": "",
      "vod_pwd": "",
      "vod_pwd_url": "",
      "vod_pwd_play": "",
      "vod_pwd_play_url": "",
      "vod_pwd_down": "",
      "vod_pwd_down_url": "",
      "vod_content": "<p><br/></p><p>首部融合中国功夫和地道街舞，融入大量时尚要素的励志动感巨制。</p><p><br/></p>",
      "vod_play_from": "dbm3u8",
      "vod_play_server": "no",
      "vod_play_note": "",
      "vod_play_url": "HD$https://b3.bdzybf22.com/videos/202601/20/696f7134f6eb7916107dddff/0eadab/index.m3u8",
      "vod_down_from": "",
      "vod_down_server": "",
      "vod_down_note": "",
      "vod_down_url": "",
      "vod_plot": 0,
      "vod_plot_name": "",
      "vod_plot_detail": "",
      "type_name": "喜剧片",
      "source_category_id": "12",
      "source_category_name": "喜剧片",
      "_sourceSlug": "baidu",
      "_sourceShort": "百度",
      "source_url": "https://api.apibdzy.com/api.php/provide/vod/",
      "canonical_id": "meta:%E7%B2%BE%E8%88%9E%E9%97%A8:2008:0:%E5%82%85%E5%8D%8E%E9%98%B3ttt",
      "primary_category": "other_movie",
      "movie_release_channel": "unknown",
      "classification_evidence": [
        {
          "source": "source_category_id",
          "priority": 1,
          "category": "other_movie",
          "field": "source_category_id",
          "value": "12",
          "signal": "other_movie"
        }
      ],
      "classification_confidence": 0.99,
      "classification_confidence_level": "high",
      "classification_confidence_score": 0.99,
      "source_candidates": [
        {
          "source": "baidu",
          "id": "47921",
          "url": "https://api.apibdzy.com/api.php/provide/vod/",
          "updated_at": ""
        }
      ],
      "play_lines": [
        {
          "source": "baidu",
          "name": "dbm3u8",
          "url": "HD$https://b3.bdzybf22.com/videos/202601/20/696f7134f6eb7916107dddff/0eadab/index.m3u8"
        }
      ],
      "semantic_tags": "class 喜剧 类型",
      "snapshot_filter_evidence": "catalog-derived"
    },
    {
      "vod_id": "agg_W3sicyI6InRhb3BpYW4iLCJpZCI6IjE1MzI0NzMifV0",
      "vod_name": "我的老婆是赌圣",
      "vod_sub": "",
      "vod_remarks": "",
      "vod_serial": "1",
      "type_id": "15007744",
      "vod_actor": "张家辉/陈国坤/孟瑶",
      "vod_director": "王晶",
      "vod_pic": "https://taopianimage.xyz:43333/e1750c8eadabv.jpeg",
      "vod_content": "赌坛高人龙天九（王晶 饰）之妹龙盈盈（孟瑶 饰）青出于蓝，号称“美女赌神”。龙盈盈为取回宿敌仇曼联（陈国坤 饰）的欠款，前往对方赌船却遭暗算，被自己的保镖兼恋人亨利击落坠海。这边厢，不成器的财务公司讨债主任周姐轮（张家辉 饰）与两名死党同事终日只是在工作中犯锉与被自己女友欺骗、殴打。郁闷的三人在海边散心，却捡回失忆美女一名。自此周姐轮与失忆的龙盈盈共处一室，经历了前任女友的周姐轮得温柔的盈盈照顾，倍感爱情的甜蜜。不久仇曼联不甘失败再出阴谋，组织亚洲赌神大赛逼龙盈盈出现。终于明了龙盈盈真实身份的周姐轮连同死党也一起被卷入了这场赌局",
      "vod_time": "2025-01-31 00:00:00",
      "vod_area": "中国香港",
      "vod_lang": "粤语",
      "vod_year": 2008,
      "type_name": "电影/喜剧片",
      "vod_keywords": "张家辉,陈国坤,孟瑶,王晶,喜剧片,张家辉,陈国坤,孟瑶,粤语,粤语,喜剧,我的老婆是赌圣",
      "vod_tag": "喜剧",
      "vod_play_server": "",
      "vod_play_from": "tpm3u8$$$tpiframe",
      "vod_play_url": "我的老婆是赌圣$https://sd8.taopianplay1.com:43333/c56b1bc09da3/HD/2025-01-31/1/e1750c8eadab/ca0f86ccb1b1/playlist.m3u8$$$我的老婆是赌圣$https://www.tpvod.com/player.html?uri=https%3A%2F%2Fsd8.taopianplay1.com%3A43333%2Fc56b1bc09da3%2FHD%2F2025-01-31%2F1%2Fe1750c8eadab%2Fca0f86ccb1b1%2Fplaylist.m3u8",
      "vod_play_note": "",
      "vod_down_server": "",
      "vod_down_from": "tpm3u8$$$tpiframe",
      "vod_down_url": "我的老婆是赌圣$https://sd8.taopianplay1.com:43333/c56b1bc09da3/HD/2025-01-31/1/e1750c8eadab/ca0f86ccb1b1/playlist.m3u8$$$我的老婆是赌圣$https://www.tpvod.com/player.html?uri=https%3A%2F%2Fsd8.taopianplay1.com%3A43333%2Fc56b1bc09da3%2FHD%2F2025-01-31%2F1%2Fe1750c8eadab%2Fca0f86ccb1b1%2Fplaylist.m3u8",
      "vod_down_note": "",
      "vod_length": 5940,
      "vod_weekday": "周一",
      "vod_copyright": "",
      "vod_state_": 1,
      "vod_version": "高清版",
      "vod_tv": "",
      "vod_total": "1",
      "vod_continu": 0,
      "vod_status": 1,
      "vod_stars": 0,
      "vod_hits": 0,
      "vod_isend": 0,
      "vod_douban_id": 0,
      "list_name": "电影/喜剧片",
      "imdb": 4.5,
      "extra_type": "",
      "origin": "tpm3u8$$$tpiframe",
      "vod_state": "",
      "vod_duration": "99",
      "vod_pubdate": "2008-05-01 00:00:00",
      "vod_douban_score": 0,
      "vod_ename": "",
      "source_category_id": "12",
      "source_category_name": "电影/喜剧片",
      "_sourceSlug": "taopian",
      "_sourceShort": "淘片",
      "source_url": "https://taopianapi.com/cjapi/mc/vod/json.html",
      "vod_time_add": "",
      "canonical_id": "meta:%E6%88%91%E7%9A%84%E8%80%81%E5%A9%86%E6%98%AF%E8%B5%8C%E5%9C%A3:2008:0:%E7%8E%8B%E6%99%B6",
      "primary_category": "other_movie",
      "movie_release_channel": "unknown",
      "classification_evidence": [
        {
          "source": "source_category_id",
          "priority": 1,
          "category": "other_movie",
          "field": "source_category_id",
          "value": "12",
          "signal": "other_movie"
        }
      ],
      "classification_confidence": 0.99,
      "classification_confidence_level": "high",
      "classification_confidence_score": 0.99,
      "source_candidates": [
        {
          "source": "taopian",
          "id": "1532473",
          "url": "https://taopianapi.com/cjapi/mc/vod/json.html",
          "updated_at": ""
        }
      ],
      "play_lines": [
        {
          "source": "taopian",
          "name": "tpm3u8",
          "url": "我的老婆是赌圣$https://sd8.taopianplay1.com:43333/c56b1bc09da3/HD/2025-01-31/1/e1750c8eadab/ca0f86ccb1b1/playlist.m3u8"
        },
        {
          "source": "taopian",
          "name": "tpiframe",
          "url": "我的老婆是赌圣$https://www.tpvod.com/player.html?uri=https%3A%2F%2Fsd8.taopianplay1.com%3A43333%2Fc56b1bc09da3%2FHD%2F2025-01-31%2F1%2Fe1750c8eadab%2Fca0f86ccb1b1%2Fplaylist.m3u8"
        }
      ],
      "semantic_tags": "class 喜剧 类型",
      "snapshot_filter_evidence": "catalog-derived"
    }
  ],
  "content_revision": "snapshot-b693cb2ce1ea39323d02",
  "snapshot_mode": "generated-filter-pack",
  "snapshot_filter": {
    "key": "class",
    "value": "喜剧"
  }
}