{
  "filters": {
    "8": [
      {
        "key": "sort",
        "name": "排序",
        "init": "latest",
        "value": [
          {
            "n": "最新",
            "v": "latest"
          },
          {
            "n": "高清优先",
            "v": "quality"
          },
          {
            "n": "多线路优先",
            "v": "lines"
          },
          {
            "n": "片名排序",
            "v": "name"
          }
        ]
      },
      {
        "key": "year",
        "name": "年份",
        "init": "",
        "value": [
          {
            "n": "全部",
            "v": ""
          },
          {
            "n": "2030",
            "v": "2030"
          },
          {
            "n": "2026",
            "v": "2026"
          },
          {
            "n": "2025",
            "v": "2025"
          },
          {
            "n": "2024",
            "v": "2024"
          },
          {
            "n": "2023",
            "v": "2023"
          },
          {
            "n": "2020-2022",
            "v": "2020-2022"
          },
          {
            "n": "2010年代",
            "v": "2010s"
          },
          {
            "n": "更早",
            "v": "older"
          }
        ]
      },
      {
        "key": "area",
        "name": "地区",
        "init": "",
        "value": [
          {
            "n": "全部",
            "v": ""
          },
          {
            "n": "大陆",
            "v": "大陆"
          },
          {
            "n": "港台",
            "v": "港台"
          },
          {
            "n": "日韩",
            "v": "日韩"
          },
          {
            "n": "欧美",
            "v": "欧美"
          },
          {
            "n": "泰国",
            "v": "泰国"
          }
        ]
      },
      {
        "key": "class",
        "name": "类型",
        "init": "",
        "value": [
          {
            "n": "全部",
            "v": ""
          },
          {
            "n": "音乐现场",
            "v": "音乐现场"
          },
          {
            "n": "生活旅行",
            "v": "生活旅行"
          },
          {
            "n": "美食健身",
            "v": "美食健身"
          },
          {
            "n": "游戏科技",
            "v": "游戏科技"
          },
          {
            "n": "体育赛事",
            "v": "体育赛事"
          },
          {
            "n": "少儿亲子",
            "v": "少儿亲子"
          }
        ]
      },
      {
        "key": "form",
        "name": "内容形态",
        "init": "",
        "value": [
          {
            "n": "全部",
            "v": ""
          },
          {
            "n": "正片",
            "v": "正片"
          },
          {
            "n": "合集",
            "v": "合集"
          },
          {
            "n": "现场",
            "v": "现场"
          },
          {
            "n": "课程",
            "v": "课程"
          },
          {
            "n": "片段",
            "v": "片段"
          }
        ]
      },
      {
        "key": "quality",
        "name": "清晰度",
        "init": "",
        "value": [
          {
            "n": "全部",
            "v": ""
          },
          {
            "n": "高清",
            "v": "hd"
          },
          {
            "n": "正片",
            "v": "正片"
          },
          {
            "n": "抢先",
            "v": "抢先"
          }
        ]
      }
    ]
  },
  "code": 1,
  "msg": "ok",
  "page": 76,
  "pagecount": 79,
  "limit": 24,
  "total": 1884,
  "class": [
    {
      "type_id": "0",
      "type_name": "推荐",
      "key": "recommend"
    },
    {
      "type_id": "10",
      "type_name": "院线电影",
      "key": "theatrical_movie"
    },
    {
      "type_id": "11",
      "type_name": "网络电影",
      "key": "web_movie"
    },
    {
      "type_id": "12",
      "type_name": "其他电影",
      "key": "other_movie"
    },
    {
      "type_id": "20",
      "type_name": "电视剧",
      "key": "tv_series"
    },
    {
      "type_id": "21",
      "type_name": "网络剧",
      "key": "web_series"
    },
    {
      "type_id": "6",
      "type_name": "网络短剧",
      "key": "web_short"
    },
    {
      "type_id": "3",
      "type_name": "综艺",
      "key": "variety"
    },
    {
      "type_id": "4",
      "type_name": "动漫",
      "key": "anime"
    },
    {
      "type_id": "5",
      "type_name": "纪录片",
      "key": "documentary"
    },
    {
      "type_id": "7",
      "type_name": "解说",
      "key": "explainer"
    },
    {
      "type_id": "8",
      "type_name": "文娱知识",
      "key": "knowledge"
    },
    {
      "type_id": "9",
      "type_name": "成人伦理",
      "key": "adult"
    }
  ],
  "list": [
    {
      "vod_id": "agg_W3sicyI6ImJmenkiLCJpZCI6IjE1MTU3NyJ9XQ",
      "type_id": "55",
      "type_id_1": 53,
      "group_id": 0,
      "vod_name": "NBA夏季联赛：篮网VS国王20260705",
      "vod_sub": "",
      "vod_en": "NBAxiajiliansailanwangVSguowang20260705",
      "vod_status": 1,
      "vod_letter": "N",
      "vod_color": "",
      "vod_tag": "",
      "vod_class": "篮球",
      "vod_pic": "https://img.picbf.com/upload/vod/20260707-1/a4480104f71b70c9f6d041789c9a0081.jpg",
      "vod_pic_thumb": "",
      "vod_pic_slide": "",
      "vod_pic_screenshot": "",
      "vod_actor": "",
      "vod_director": "",
      "vod_writer": "",
      "vod_behind": "",
      "vod_blurb": "暂无剧情介绍",
      "vod_remarks": "更新至HD",
      "vod_pubdate": "",
      "vod_total": "0",
      "vod_serial": "0",
      "vod_tv": "",
      "vod_weekday": "",
      "vod_area": "",
      "vod_lang": "",
      "vod_year": "0",
      "vod_version": "",
      "vod_state": "",
      "vod_author": "",
      "vod_jumpurl": "",
      "vod_tpl": "",
      "vod_tpl_play": "",
      "vod_tpl_down": "",
      "vod_isend": 0,
      "vod_lock": 0,
      "vod_level": 0,
      "vod_copyright": 0,
      "vod_points": 0,
      "vod_points_play": 0,
      "vod_points_down": 0,
      "vod_hits": 102,
      "vod_hits_day": 521,
      "vod_hits_week": 67,
      "vod_hits_month": 526,
      "vod_duration": "",
      "vod_up": 840,
      "vod_down": 225,
      "vod_score": "10.0",
      "vod_score_all": 3440,
      "vod_score_num": 344,
      "vod_time": "2026-07-07 14:37:20",
      "vod_time_add": "1783406229",
      "vod_time_hits": 0,
      "vod_time_make": 0,
      "vod_trysee": 0,
      "vod_douban_id": 0,
      "vod_douban_score": "0.0",
      "vod_reurl": "",
      "vod_rel_vod": "",
      "vod_rel_art": "",
      "vod_pwd": "",
      "vod_pwd_url": "",
      "vod_pwd_play": "",
      "vod_pwd_play_url": "",
      "vod_pwd_down": "",
      "vod_pwd_down_url": "",
      "vod_content": "暂无简介，敬请期待",
      "vod_play_from": "bfzym3u8",
      "vod_play_server": "",
      "vod_play_note": "",
      "vod_play_url": "HD$https://s3.bfllvip.com/video/NBAxiajiliansailanwangVSguowang20260705/69ea1dd7b0bc/index.m3u8",
      "vod_down_from": "",
      "vod_down_server": "",
      "vod_down_note": "",
      "vod_down_url": "",
      "vod_plot": 0,
      "vod_plot_name": "",
      "vod_plot_detail": "",
      "type_name": "篮球",
      "source_category_id": "8",
      "source_category_name": "篮球",
      "_sourceSlug": "bfzy",
      "_sourceShort": "暴风",
      "source_url": "https://bfzyapi.com/api.php/provide/vod/",
      "canonical_id": "meta:nba%E5%A4%8F%E5%AD%A3%E8%81%94%E8%B5%9B%E7%AF%AE%E7%BD%91vs%E5%9B%BD%E7%8E%8B20260705:0:0:unknown",
      "primary_category": "knowledge",
      "movie_release_channel": "unknown",
      "classification_evidence": [
        {
          "source": "source_category_id",
          "priority": 1,
          "category": "knowledge",
          "field": "source_category_id",
          "value": "8",
          "signal": "knowledge"
        }
      ],
      "classification_confidence": 0.99,
      "classification_confidence_level": "high",
      "classification_confidence_score": 0.99,
      "source_candidates": [
        {
          "source": "bfzy",
          "id": "151577",
          "url": "https://bfzyapi.com/api.php/provide/vod/",
          "updated_at": ""
        }
      ],
      "play_lines": [
        {
          "source": "bfzy",
          "name": "bfzym3u8",
          "url": "HD$https://s3.bfllvip.com/video/NBAxiajiliansailanwangVSguowang20260705/69ea1dd7b0bc/index.m3u8"
        }
      ],
      "semantic_tags": "quality hd 清晰度 高清",
      "snapshot_filter_evidence": "catalog-derived"
    },
    {
      "vod_id": "agg_W3sicyI6ImJmenkiLCJpZCI6IjE1MjEyOCJ9XQ",
      "type_id": "55",
      "type_id_1": 53,
      "group_id": 0,
      "vod_name": "NBA夏季联赛：篮网VS尼克斯20260711",
      "vod_sub": "",
      "vod_en": "NBAxiajiliansailanwangVSnikesi20260711",
      "vod_status": 1,
      "vod_letter": "N",
      "vod_color": "",
      "vod_tag": "",
      "vod_class": "篮球",
      "vod_pic": "https://img.picbf.com/upload/vod/20260713-1/df59cfa6a9309225b160a1eb8b071833.jpg",
      "vod_pic_thumb": "",
      "vod_pic_slide": "",
      "vod_pic_screenshot": "",
      "vod_actor": "",
      "vod_director": "",
      "vod_writer": "",
      "vod_behind": "",
      "vod_blurb": "暂无剧情介绍",
      "vod_remarks": "更新至HD",
      "vod_pubdate": "",
      "vod_total": "0",
      "vod_serial": "0",
      "vod_tv": "",
      "vod_weekday": "",
      "vod_area": "",
      "vod_lang": "",
      "vod_year": "0",
      "vod_version": "",
      "vod_state": "",
      "vod_author": "",
      "vod_jumpurl": "",
      "vod_tpl": "",
      "vod_tpl_play": "",
      "vod_tpl_down": "",
      "vod_isend": 0,
      "vod_lock": 0,
      "vod_level": 0,
      "vod_copyright": 0,
      "vod_points": 0,
      "vod_points_play": 0,
      "vod_points_down": 0,
      "vod_hits": 356,
      "vod_hits_day": 517,
      "vod_hits_week": 34,
      "vod_hits_month": 340,
      "vod_duration": "",
      "vod_up": 140,
      "vod_down": 708,
      "vod_score": "4.0",
      "vod_score_all": 748,
      "vod_score_num": 187,
      "vod_time": "2026-07-13 05:29:13",
      "vod_time_add": "1783891748",
      "vod_time_hits": 0,
      "vod_time_make": 0,
      "vod_trysee": 0,
      "vod_douban_id": 0,
      "vod_douban_score": "0.0",
      "vod_reurl": "",
      "vod_rel_vod": "",
      "vod_rel_art": "",
      "vod_pwd": "",
      "vod_pwd_url": "",
      "vod_pwd_play": "",
      "vod_pwd_play_url": "",
      "vod_pwd_down": "",
      "vod_pwd_down_url": "",
      "vod_content": "暂无简介，敬请期待",
      "vod_play_from": "bfzym3u8",
      "vod_play_server": "",
      "vod_play_note": "",
      "vod_play_url": "HD$https://s3.bfllvip.com/video/NBAxiajiliansailanwangVSnikesi20260711/175b063d5904/index.m3u8",
      "vod_down_from": "",
      "vod_down_server": "",
      "vod_down_note": "",
      "vod_down_url": "",
      "vod_plot": 0,
      "vod_plot_name": "",
      "vod_plot_detail": "",
      "type_name": "篮球",
      "source_category_id": "8",
      "source_category_name": "篮球",
      "_sourceSlug": "bfzy",
      "_sourceShort": "暴风",
      "source_url": "https://bfzyapi.com/api.php/provide/vod/",
      "canonical_id": "meta:nba%E5%A4%8F%E5%AD%A3%E8%81%94%E8%B5%9B%E7%AF%AE%E7%BD%91vs%E5%B0%BC%E5%85%8B%E6%96%AF20260711:0:0:unknown",
      "primary_category": "knowledge",
      "movie_release_channel": "unknown",
      "classification_evidence": [
        {
          "source": "source_category_id",
          "priority": 1,
          "category": "knowledge",
          "field": "source_category_id",
          "value": "8",
          "signal": "knowledge"
        }
      ],
      "classification_confidence": 0.99,
      "classification_confidence_level": "high",
      "classification_confidence_score": 0.99,
      "source_candidates": [
        {
          "source": "bfzy",
          "id": "152128",
          "url": "https://bfzyapi.com/api.php/provide/vod/",
          "updated_at": ""
        }
      ],
      "play_lines": [
        {
          "source": "bfzy",
          "name": "bfzym3u8",
          "url": "HD$https://s3.bfllvip.com/video/NBAxiajiliansailanwangVSnikesi20260711/175b063d5904/index.m3u8"
        }
      ],
      "semantic_tags": "quality hd 清晰度 高清",
      "snapshot_filter_evidence": "catalog-derived"
    },
    {
      "vod_id": "agg_W3sicyI6ImJmenkiLCJpZCI6IjE1MTU4MCJ9XQ",
      "type_id": "55",
      "type_id_1": 53,
      "group_id": 0,
      "vod_name": "NBA夏季联赛：篮网VS雄鹿20260706",
      "vod_sub": "",
      "vod_en": "NBAxiajiliansailanwangVSxionglu20260706",
      "vod_status": 1,
      "vod_letter": "N",
      "vod_color": "",
      "vod_tag": "",
      "vod_class": "篮球",
      "vod_pic": "https://img.picbf.com/upload/vod/20260707-1/22d693f2bb5f71a6db0a66eda2c18e2f.jpg",
      "vod_pic_thumb": "",
      "vod_pic_slide": "",
      "vod_pic_screenshot": "",
      "vod_actor": "",
      "vod_director": "",
      "vod_writer": "",
      "vod_behind": "",
      "vod_blurb": "暂无剧情介绍",
      "vod_remarks": "更新至HD",
      "vod_pubdate": "",
      "vod_total": "0",
      "vod_serial": "0",
      "vod_tv": "",
      "vod_weekday": "",
      "vod_area": "",
      "vod_lang": "",
      "vod_year": "0",
      "vod_version": "",
      "vod_state": "",
      "vod_author": "",
      "vod_jumpurl": "",
      "vod_tpl": "",
      "vod_tpl_play": "",
      "vod_tpl_down": "",
      "vod_isend": 0,
      "vod_lock": 0,
      "vod_level": 0,
      "vod_copyright": 0,
      "vod_points": 0,
      "vod_points_play": 0,
      "vod_points_down": 0,
      "vod_hits": 835,
      "vod_hits_day": 109,
      "vod_hits_week": 308,
      "vod_hits_month": 675,
      "vod_duration": "",
      "vod_up": 85,
      "vod_down": 381,
      "vod_score": "9.0",
      "vod_score_all": 6264,
      "vod_score_num": 696,
      "vod_time": "2026-07-07 14:40:20",
      "vod_time_add": "1783406411",
      "vod_time_hits": 0,
      "vod_time_make": 0,
      "vod_trysee": 0,
      "vod_douban_id": 0,
      "vod_douban_score": "0.0",
      "vod_reurl": "",
      "vod_rel_vod": "",
      "vod_rel_art": "",
      "vod_pwd": "",
      "vod_pwd_url": "",
      "vod_pwd_play": "",
      "vod_pwd_play_url": "",
      "vod_pwd_down": "",
      "vod_pwd_down_url": "",
      "vod_content": "暂无简介，敬请期待",
      "vod_play_from": "bfzym3u8",
      "vod_play_server": "",
      "vod_play_note": "",
      "vod_play_url": "HD$https://s3.bfllvip.com/video/NBAxiajiliansailanwangVSxionglu20260706/9e9727d2e2e8/index.m3u8",
      "vod_down_from": "",
      "vod_down_server": "",
      "vod_down_note": "",
      "vod_down_url": "",
      "vod_plot": 0,
      "vod_plot_name": "",
      "vod_plot_detail": "",
      "type_name": "篮球",
      "source_category_id": "8",
      "source_category_name": "篮球",
      "_sourceSlug": "bfzy",
      "_sourceShort": "暴风",
      "source_url": "https://bfzyapi.com/api.php/provide/vod/",
      "canonical_id": "meta:nba%E5%A4%8F%E5%AD%A3%E8%81%94%E8%B5%9B%E7%AF%AE%E7%BD%91vs%E9%9B%84%E9%B9%BF20260706:0:0:unknown",
      "primary_category": "knowledge",
      "movie_release_channel": "unknown",
      "classification_evidence": [
        {
          "source": "source_category_id",
          "priority": 1,
          "category": "knowledge",
          "field": "source_category_id",
          "value": "8",
          "signal": "knowledge"
        }
      ],
      "classification_confidence": 0.99,
      "classification_confidence_level": "high",
      "classification_confidence_score": 0.99,
      "source_candidates": [
        {
          "source": "bfzy",
          "id": "151580",
          "url": "https://bfzyapi.com/api.php/provide/vod/",
          "updated_at": ""
        }
      ],
      "play_lines": [
        {
          "source": "bfzy",
          "name": "bfzym3u8",
          "url": "HD$https://s3.bfllvip.com/video/NBAxiajiliansailanwangVSxionglu20260706/9e9727d2e2e8/index.m3u8"
        }
      ],
      "semantic_tags": "quality hd 清晰度 高清",
      "snapshot_filter_evidence": "catalog-derived"
    },
    {
      "vod_id": "agg_W3sicyI6ImJmenkiLCJpZCI6IjE1MjExMSJ9XQ",
      "type_id": "55",
      "type_id_1": 53,
      "group_id": 0,
      "vod_name": "NBA夏季联赛：老鹰VS灰熊20260708",
      "vod_sub": "",
      "vod_en": "NBAxiajiliansailaoyingVShuixiong20260708",
      "vod_status": 1,
      "vod_letter": "N",
      "vod_color": "",
      "vod_tag": "",
      "vod_class": "篮球",
      "vod_pic": "https://img.picbf.com/upload/vod/20260713-1/73b564d4733af07452713303112d466f.jpg",
      "vod_pic_thumb": "",
      "vod_pic_slide": "",
      "vod_pic_screenshot": "",
      "vod_actor": "",
      "vod_director": "",
      "vod_writer": "",
      "vod_behind": "",
      "vod_blurb": "暂无剧情介绍",
      "vod_remarks": "更新至HD",
      "vod_pubdate": "",
      "vod_total": "0",
      "vod_serial": "0",
      "vod_tv": "",
      "vod_weekday": "",
      "vod_area": "",
      "vod_lang": "",
      "vod_year": "0",
      "vod_version": "",
      "vod_state": "",
      "vod_author": "",
      "vod_jumpurl": "",
      "vod_tpl": "",
      "vod_tpl_play": "",
      "vod_tpl_down": "",
      "vod_isend": 0,
      "vod_lock": 0,
      "vod_level": 0,
      "vod_copyright": 0,
      "vod_points": 0,
      "vod_points_play": 0,
      "vod_points_down": 0,
      "vod_hits": 212,
      "vod_hits_day": 751,
      "vod_hits_week": 670,
      "vod_hits_month": 443,
      "vod_duration": "",
      "vod_up": 300,
      "vod_down": 549,
      "vod_score": "10.0",
      "vod_score_all": 8810,
      "vod_score_num": 881,
      "vod_time": "2026-07-13 05:21:32",
      "vod_time_add": "1783891286",
      "vod_time_hits": 0,
      "vod_time_make": 0,
      "vod_trysee": 0,
      "vod_douban_id": 0,
      "vod_douban_score": "0.0",
      "vod_reurl": "",
      "vod_rel_vod": "",
      "vod_rel_art": "",
      "vod_pwd": "",
      "vod_pwd_url": "",
      "vod_pwd_play": "",
      "vod_pwd_play_url": "",
      "vod_pwd_down": "",
      "vod_pwd_down_url": "",
      "vod_content": "暂无简介，敬请期待",
      "vod_play_from": "bfzym3u8",
      "vod_play_server": "",
      "vod_play_note": "",
      "vod_play_url": "HD$https://s3.bfllvip.com/video/NBAxiajiliansailaoyingVShuixiong20260708/655f400f39e6/index.m3u8",
      "vod_down_from": "",
      "vod_down_server": "",
      "vod_down_note": "",
      "vod_down_url": "",
      "vod_plot": 0,
      "vod_plot_name": "",
      "vod_plot_detail": "",
      "type_name": "篮球",
      "source_category_id": "8",
      "source_category_name": "篮球",
      "_sourceSlug": "bfzy",
      "_sourceShort": "暴风",
      "source_url": "https://bfzyapi.com/api.php/provide/vod/",
      "canonical_id": "meta:nba%E5%A4%8F%E5%AD%A3%E8%81%94%E8%B5%9B%E8%80%81%E9%B9%B0vs%E7%81%B0%E7%86%8A20260708:0:0:unknown",
      "primary_category": "knowledge",
      "movie_release_channel": "unknown",
      "classification_evidence": [
        {
          "source": "source_category_id",
          "priority": 1,
          "category": "knowledge",
          "field": "source_category_id",
          "value": "8",
          "signal": "knowledge"
        }
      ],
      "classification_confidence": 0.99,
      "classification_confidence_level": "high",
      "classification_confidence_score": 0.99,
      "source_candidates": [
        {
          "source": "bfzy",
          "id": "152111",
          "url": "https://bfzyapi.com/api.php/provide/vod/",
          "updated_at": ""
        }
      ],
      "play_lines": [
        {
          "source": "bfzy",
          "name": "bfzym3u8",
          "url": "HD$https://s3.bfllvip.com/video/NBAxiajiliansailaoyingVShuixiong20260708/655f400f39e6/index.m3u8"
        }
      ],
      "semantic_tags": "quality hd 清晰度 高清",
      "snapshot_filter_evidence": "catalog-derived"
    },
    {
      "vod_id": "agg_W3sicyI6ImJmenkiLCJpZCI6IjE1MTU3OCJ9XQ",
      "type_id": "55",
      "type_id_1": 53,
      "group_id": 0,
      "vod_name": "NBA夏季联赛：老鹰VS爵士20260705",
      "vod_sub": "",
      "vod_en": "NBAxiajiliansailaoyingVSjueshi20260705",
      "vod_status": 1,
      "vod_letter": "N",
      "vod_color": "",
      "vod_tag": "",
      "vod_class": "篮球",
      "vod_pic": "https://img.picbf.com/upload/vod/20260707-1/a55da4f3c759dc65cfdb3bf798ae32f6.jpg",
      "vod_pic_thumb": "",
      "vod_pic_slide": "",
      "vod_pic_screenshot": "",
      "vod_actor": "",
      "vod_director": "",
      "vod_writer": "",
      "vod_behind": "",
      "vod_blurb": "暂无剧情介绍",
      "vod_remarks": "更新至HD",
      "vod_pubdate": "",
      "vod_total": "0",
      "vod_serial": "0",
      "vod_tv": "",
      "vod_weekday": "",
      "vod_area": "",
      "vod_lang": "",
      "vod_year": "0",
      "vod_version": "",
      "vod_state": "",
      "vod_author": "",
      "vod_jumpurl": "",
      "vod_tpl": "",
      "vod_tpl_play": "",
      "vod_tpl_down": "",
      "vod_isend": 0,
      "vod_lock": 0,
      "vod_level": 0,
      "vod_copyright": 0,
      "vod_points": 0,
      "vod_points_play": 0,
      "vod_points_down": 0,
      "vod_hits": 353,
      "vod_hits_day": 62,
      "vod_hits_week": 753,
      "vod_hits_month": 370,
      "vod_duration": "",
      "vod_up": 608,
      "vod_down": 915,
      "vod_score": "5.0",
      "vod_score_all": 1615,
      "vod_score_num": 323,
      "vod_time": "2026-07-07 14:38:00",
      "vod_time_add": "1783406276",
      "vod_time_hits": 0,
      "vod_time_make": 0,
      "vod_trysee": 0,
      "vod_douban_id": 0,
      "vod_douban_score": "0.0",
      "vod_reurl": "",
      "vod_rel_vod": "",
      "vod_rel_art": "",
      "vod_pwd": "",
      "vod_pwd_url": "",
      "vod_pwd_play": "",
      "vod_pwd_play_url": "",
      "vod_pwd_down": "",
      "vod_pwd_down_url": "",
      "vod_content": "暂无简介，敬请期待",
      "vod_play_from": "bfzym3u8",
      "vod_play_server": "",
      "vod_play_note": "",
      "vod_play_url": "HD$https://s3.bfllvip.com/video/NBAxiajiliansailaoyingVSjueshi20260705/678c75bdd60b/index.m3u8",
      "vod_down_from": "",
      "vod_down_server": "",
      "vod_down_note": "",
      "vod_down_url": "",
      "vod_plot": 0,
      "vod_plot_name": "",
      "vod_plot_detail": "",
      "type_name": "篮球",
      "source_category_id": "8",
      "source_category_name": "篮球",
      "_sourceSlug": "bfzy",
      "_sourceShort": "暴风",
      "source_url": "https://bfzyapi.com/api.php/provide/vod/",
      "canonical_id": "meta:nba%E5%A4%8F%E5%AD%A3%E8%81%94%E8%B5%9B%E8%80%81%E9%B9%B0vs%E7%88%B5%E5%A3%AB20260705:0:0:unknown",
      "primary_category": "knowledge",
      "movie_release_channel": "unknown",
      "classification_evidence": [
        {
          "source": "source_category_id",
          "priority": 1,
          "category": "knowledge",
          "field": "source_category_id",
          "value": "8",
          "signal": "knowledge"
        }
      ],
      "classification_confidence": 0.99,
      "classification_confidence_level": "high",
      "classification_confidence_score": 0.99,
      "source_candidates": [
        {
          "source": "bfzy",
          "id": "151578",
          "url": "https://bfzyapi.com/api.php/provide/vod/",
          "updated_at": ""
        }
      ],
      "play_lines": [
        {
          "source": "bfzy",
          "name": "bfzym3u8",
          "url": "HD$https://s3.bfllvip.com/video/NBAxiajiliansailaoyingVSjueshi20260705/678c75bdd60b/index.m3u8"
        }
      ],
      "semantic_tags": "quality hd 清晰度 高清",
      "snapshot_filter_evidence": "catalog-derived"
    },
    {
      "vod_id": "agg_W3sicyI6ImJmenkiLCJpZCI6IjE1MjYwMyJ9XQ",
      "type_id": "55",
      "type_id_1": 53,
      "group_id": 0,
      "vod_name": "NBA夏季联赛：老鹰VS凯尔特人20260714",
      "vod_sub": "",
      "vod_en": "NBAxiajiliansailaoyingVSkaierteren20260714",
      "vod_status": 1,
      "vod_letter": "N",
      "vod_color": "",
      "vod_tag": "",
      "vod_class": "篮球",
      "vod_pic": "https://img.picbf.com/upload/vod/20260715-1/54b2239f9d6cfca6a34d003339dd6507.jpg",
      "vod_pic_thumb": "",
      "vod_pic_slide": "",
      "vod_pic_screenshot": "",
      "vod_actor": "",
      "vod_director": "",
      "vod_writer": "",
      "vod_behind": "",
      "vod_blurb": "暂无剧情介绍",
      "vod_remarks": "更新至HD",
      "vod_pubdate": "",
      "vod_total": "0",
      "vod_serial": "0",
      "vod_tv": "",
      "vod_weekday": "",
      "vod_area": "",
      "vod_lang": "",
      "vod_year": "0",
      "vod_version": "",
      "vod_state": "",
      "vod_author": "",
      "vod_jumpurl": "",
      "vod_tpl": "",
      "vod_tpl_play": "",
      "vod_tpl_down": "",
      "vod_isend": 0,
      "vod_lock": 0,
      "vod_level": 0,
      "vod_copyright": 0,
      "vod_points": 0,
      "vod_points_play": 0,
      "vod_points_down": 0,
      "vod_hits": 145,
      "vod_hits_day": 566,
      "vod_hits_week": 394,
      "vod_hits_month": 520,
      "vod_duration": "",
      "vod_up": 925,
      "vod_down": 148,
      "vod_score": "5.0",
      "vod_score_all": 3975,
      "vod_score_num": 795,
      "vod_time": "2026-07-15 16:09:38",
      "vod_time_add": "1784102974",
      "vod_time_hits": 0,
      "vod_time_make": 0,
      "vod_trysee": 0,
      "vod_douban_id": 0,
      "vod_douban_score": "0.0",
      "vod_reurl": "",
      "vod_rel_vod": "",
      "vod_rel_art": "",
      "vod_pwd": "",
      "vod_pwd_url": "",
      "vod_pwd_play": "",
      "vod_pwd_play_url": "",
      "vod_pwd_down": "",
      "vod_pwd_down_url": "",
      "vod_content": "暂无简介，敬请期待",
      "vod_play_from": "bfzym3u8",
      "vod_play_server": "",
      "vod_play_note": "",
      "vod_play_url": "HD$https://s3.bfllvip.com/video/NBAxiajiliansailaoyingVSkaierteren20260714/51c9539c9099/index.m3u8",
      "vod_down_from": "",
      "vod_down_server": "",
      "vod_down_note": "",
      "vod_down_url": "",
      "vod_plot": 0,
      "vod_plot_name": "",
      "vod_plot_detail": "",
      "type_name": "篮球",
      "source_category_id": "8",
      "source_category_name": "篮球",
      "_sourceSlug": "bfzy",
      "_sourceShort": "暴风",
      "source_url": "https://bfzyapi.com/api.php/provide/vod/",
      "canonical_id": "meta:nba%E5%A4%8F%E5%AD%A3%E8%81%94%E8%B5%9B%E8%80%81%E9%B9%B0vs%E5%87%AF%E5%B0%94%E7%89%B9%E4%BA%BA20260714:0:0:unknown",
      "primary_category": "knowledge",
      "movie_release_channel": "unknown",
      "classification_evidence": [
        {
          "source": "source_category_id",
          "priority": 1,
          "category": "knowledge",
          "field": "source_category_id",
          "value": "8",
          "signal": "knowledge"
        }
      ],
      "classification_confidence": 0.99,
      "classification_confidence_level": "high",
      "classification_confidence_score": 0.99,
      "source_candidates": [
        {
          "source": "bfzy",
          "id": "152603",
          "url": "https://bfzyapi.com/api.php/provide/vod/",
          "updated_at": ""
        }
      ],
      "play_lines": [
        {
          "source": "bfzy",
          "name": "bfzym3u8",
          "url": "HD$https://s3.bfllvip.com/video/NBAxiajiliansailaoyingVSkaierteren20260714/51c9539c9099/index.m3u8"
        }
      ],
      "semantic_tags": "quality hd 清晰度 高清",
      "snapshot_filter_evidence": "catalog-derived"
    },
    {
      "vod_id": "agg_W3sicyI6ImJmenkiLCJpZCI6IjE1MjU5MCJ9XQ",
      "type_id": "55",
      "type_id_1": 53,
      "group_id": 0,
      "vod_name": "NBA夏季联赛：老鹰VS篮网20260712",
      "vod_sub": "",
      "vod_en": "NBAxiajiliansailaoyingVSlanwang20260712",
      "vod_status": 1,
      "vod_letter": "N",
      "vod_color": "",
      "vod_tag": "",
      "vod_class": "篮球",
      "vod_pic": "https://img.picbf.com/upload/vod/20260715-1/712665587a6c7b760b6a2e9b3803c4b4.jpg",
      "vod_pic_thumb": "",
      "vod_pic_slide": "",
      "vod_pic_screenshot": "",
      "vod_actor": "",
      "vod_director": "",
      "vod_writer": "",
      "vod_behind": "",
      "vod_blurb": "暂无剧情介绍",
      "vod_remarks": "更新至HD",
      "vod_pubdate": "",
      "vod_total": "0",
      "vod_serial": "0",
      "vod_tv": "",
      "vod_weekday": "",
      "vod_area": "",
      "vod_lang": "",
      "vod_year": "0",
      "vod_version": "",
      "vod_state": "",
      "vod_author": "",
      "vod_jumpurl": "",
      "vod_tpl": "",
      "vod_tpl_play": "",
      "vod_tpl_down": "",
      "vod_isend": 0,
      "vod_lock": 0,
      "vod_level": 0,
      "vod_copyright": 0,
      "vod_points": 0,
      "vod_points_play": 0,
      "vod_points_down": 0,
      "vod_hits": 993,
      "vod_hits_day": 585,
      "vod_hits_week": 301,
      "vod_hits_month": 342,
      "vod_duration": "",
      "vod_up": 367,
      "vod_down": 564,
      "vod_score": "2.0",
      "vod_score_all": 500,
      "vod_score_num": 250,
      "vod_time": "2026-07-15 16:02:37",
      "vod_time_add": "1784102547",
      "vod_time_hits": 0,
      "vod_time_make": 0,
      "vod_trysee": 0,
      "vod_douban_id": 0,
      "vod_douban_score": "0.0",
      "vod_reurl": "",
      "vod_rel_vod": "",
      "vod_rel_art": "",
      "vod_pwd": "",
      "vod_pwd_url": "",
      "vod_pwd_play": "",
      "vod_pwd_play_url": "",
      "vod_pwd_down": "",
      "vod_pwd_down_url": "",
      "vod_content": "暂无简介，敬请期待",
      "vod_play_from": "bfzym3u8",
      "vod_play_server": "",
      "vod_play_note": "",
      "vod_play_url": "HD$https://s3.bfllvip.com/video/NBAxiajiliansailaoyingVSlanwang20260712/bb145eabbf97/index.m3u8",
      "vod_down_from": "",
      "vod_down_server": "",
      "vod_down_note": "",
      "vod_down_url": "",
      "vod_plot": 0,
      "vod_plot_name": "",
      "vod_plot_detail": "",
      "type_name": "篮球",
      "source_category_id": "8",
      "source_category_name": "篮球",
      "_sourceSlug": "bfzy",
      "_sourceShort": "暴风",
      "source_url": "https://bfzyapi.com/api.php/provide/vod/",
      "canonical_id": "meta:nba%E5%A4%8F%E5%AD%A3%E8%81%94%E8%B5%9B%E8%80%81%E9%B9%B0vs%E7%AF%AE%E7%BD%9120260712:0:0:unknown",
      "primary_category": "knowledge",
      "movie_release_channel": "unknown",
      "classification_evidence": [
        {
          "source": "source_category_id",
          "priority": 1,
          "category": "knowledge",
          "field": "source_category_id",
          "value": "8",
          "signal": "knowledge"
        }
      ],
      "classification_confidence": 0.99,
      "classification_confidence_level": "high",
      "classification_confidence_score": 0.99,
      "source_candidates": [
        {
          "source": "bfzy",
          "id": "152590",
          "url": "https://bfzyapi.com/api.php/provide/vod/",
          "updated_at": ""
        }
      ],
      "play_lines": [
        {
          "source": "bfzy",
          "name": "bfzym3u8",
          "url": "HD$https://s3.bfllvip.com/video/NBAxiajiliansailaoyingVSlanwang20260712/bb145eabbf97/index.m3u8"
        }
      ],
      "semantic_tags": "quality hd 清晰度 高清",
      "snapshot_filter_evidence": "catalog-derived"
    },
    {
      "vod_id": "agg_W3sicyI6ImJmenkiLCJpZCI6IjE1MTYwOSJ9XQ",
      "type_id": "55",
      "type_id_1": 53,
      "group_id": 0,
      "vod_name": "NBA夏季联赛：老鹰VS雷霆20260707",
      "vod_sub": "",
      "vod_en": "NBAxiajiliansailaoyingVSleiting20260707",
      "vod_status": 1,
      "vod_letter": "N",
      "vod_color": "",
      "vod_tag": "",
      "vod_class": "篮球",
      "vod_pic": "https://img.picbf.com/upload/vod/20260708-1/ce3abeadfac3f8965e05c508037c086f.jpg",
      "vod_pic_thumb": "",
      "vod_pic_slide": "",
      "vod_pic_screenshot": "",
      "vod_actor": "",
      "vod_director": "",
      "vod_writer": "",
      "vod_behind": "",
      "vod_blurb": "暂无剧情介绍",
      "vod_remarks": "更新至HD",
      "vod_pubdate": "",
      "vod_total": "0",
      "vod_serial": "0",
      "vod_tv": "",
      "vod_weekday": "",
      "vod_area": "",
      "vod_lang": "",
      "vod_year": "0",
      "vod_version": "",
      "vod_state": "",
      "vod_author": "",
      "vod_jumpurl": "",
      "vod_tpl": "",
      "vod_tpl_play": "",
      "vod_tpl_down": "",
      "vod_isend": 0,
      "vod_lock": 0,
      "vod_level": 0,
      "vod_copyright": 0,
      "vod_points": 0,
      "vod_points_play": 0,
      "vod_points_down": 0,
      "vod_hits": 44,
      "vod_hits_day": 961,
      "vod_hits_week": 962,
      "vod_hits_month": 774,
      "vod_duration": "",
      "vod_up": 905,
      "vod_down": 132,
      "vod_score": "9.0",
      "vod_score_all": 1476,
      "vod_score_num": 164,
      "vod_time": "2026-07-08 08:48:58",
      "vod_time_add": "1783471728",
      "vod_time_hits": 0,
      "vod_time_make": 0,
      "vod_trysee": 0,
      "vod_douban_id": 0,
      "vod_douban_score": "0.0",
      "vod_reurl": "",
      "vod_rel_vod": "",
      "vod_rel_art": "",
      "vod_pwd": "",
      "vod_pwd_url": "",
      "vod_pwd_play": "",
      "vod_pwd_play_url": "",
      "vod_pwd_down": "",
      "vod_pwd_down_url": "",
      "vod_content": "暂无简介，敬请期待",
      "vod_play_from": "bfzym3u8",
      "vod_play_server": "",
      "vod_play_note": "",
      "vod_play_url": "HD$https://s3.bfllvip.com/video/NBAxiajiliansailaoyingVSleiting20260707/687ab39afe4c/index.m3u8",
      "vod_down_from": "",
      "vod_down_server": "",
      "vod_down_note": "",
      "vod_down_url": "",
      "vod_plot": 0,
      "vod_plot_name": "",
      "vod_plot_detail": "",
      "type_name": "篮球",
      "source_category_id": "8",
      "source_category_name": "篮球",
      "_sourceSlug": "bfzy",
      "_sourceShort": "暴风",
      "source_url": "https://bfzyapi.com/api.php/provide/vod/",
      "canonical_id": "meta:nba%E5%A4%8F%E5%AD%A3%E8%81%94%E8%B5%9B%E8%80%81%E9%B9%B0vs%E9%9B%B7%E9%9C%8620260707:0:0:unknown",
      "primary_category": "knowledge",
      "movie_release_channel": "unknown",
      "classification_evidence": [
        {
          "source": "source_category_id",
          "priority": 1,
          "category": "knowledge",
          "field": "source_category_id",
          "value": "8",
          "signal": "knowledge"
        }
      ],
      "classification_confidence": 0.99,
      "classification_confidence_level": "high",
      "classification_confidence_score": 0.99,
      "source_candidates": [
        {
          "source": "bfzy",
          "id": "151609",
          "url": "https://bfzyapi.com/api.php/provide/vod/",
          "updated_at": ""
        }
      ],
      "play_lines": [
        {
          "source": "bfzy",
          "name": "bfzym3u8",
          "url": "HD$https://s3.bfllvip.com/video/NBAxiajiliansailaoyingVSleiting20260707/687ab39afe4c/index.m3u8"
        }
      ],
      "semantic_tags": "quality hd 清晰度 高清",
      "snapshot_filter_evidence": "catalog-derived"
    },
    {
      "vod_id": "agg_W3sicyI6ImJmenkiLCJpZCI6IjE1MjEyOSJ9XQ",
      "type_id": "55",
      "type_id_1": 53,
      "group_id": 0,
      "vod_name": "NBA夏季联赛：雷霆VS湖人20260711",
      "vod_sub": "",
      "vod_en": "NBAxiajiliansaileitingVShuren20260711",
      "vod_status": 1,
      "vod_letter": "N",
      "vod_color": "",
      "vod_tag": "",
      "vod_class": "篮球",
      "vod_pic": "https://img.picbf.com/upload/vod/20260713-1/c484bbfab74d87d36eeae219ba1706d0.jpg",
      "vod_pic_thumb": "",
      "vod_pic_slide": "",
      "vod_pic_screenshot": "",
      "vod_actor": "",
      "vod_director": "",
      "vod_writer": "",
      "vod_behind": "",
      "vod_blurb": "暂无剧情介绍",
      "vod_remarks": "更新至HD",
      "vod_pubdate": "",
      "vod_total": "0",
      "vod_serial": "0",
      "vod_tv": "",
      "vod_weekday": "",
      "vod_area": "",
      "vod_lang": "",
      "vod_year": "0",
      "vod_version": "",
      "vod_state": "",
      "vod_author": "",
      "vod_jumpurl": "",
      "vod_tpl": "",
      "vod_tpl_play": "",
      "vod_tpl_down": "",
      "vod_isend": 0,
      "vod_lock": 0,
      "vod_level": 0,
      "vod_copyright": 0,
      "vod_points": 0,
      "vod_points_play": 0,
      "vod_points_down": 0,
      "vod_hits": 559,
      "vod_hits_day": 832,
      "vod_hits_week": 726,
      "vod_hits_month": 363,
      "vod_duration": "",
      "vod_up": 821,
      "vod_down": 262,
      "vod_score": "1.0",
      "vod_score_all": 816,
      "vod_score_num": 816,
      "vod_time": "2026-07-13 05:29:43",
      "vod_time_add": "1783891773",
      "vod_time_hits": 0,
      "vod_time_make": 0,
      "vod_trysee": 0,
      "vod_douban_id": 0,
      "vod_douban_score": "0.0",
      "vod_reurl": "",
      "vod_rel_vod": "",
      "vod_rel_art": "",
      "vod_pwd": "",
      "vod_pwd_url": "",
      "vod_pwd_play": "",
      "vod_pwd_play_url": "",
      "vod_pwd_down": "",
      "vod_pwd_down_url": "",
      "vod_content": "暂无简介，敬请期待",
      "vod_play_from": "bfzym3u8",
      "vod_play_server": "",
      "vod_play_note": "",
      "vod_play_url": "HD$https://s3.bfllvip.com/video/NBAxiajiliansaileitingVShuren20260711/c7fa410daca5/index.m3u8",
      "vod_down_from": "",
      "vod_down_server": "",
      "vod_down_note": "",
      "vod_down_url": "",
      "vod_plot": 0,
      "vod_plot_name": "",
      "vod_plot_detail": "",
      "type_name": "篮球",
      "source_category_id": "8",
      "source_category_name": "篮球",
      "_sourceSlug": "bfzy",
      "_sourceShort": "暴风",
      "source_url": "https://bfzyapi.com/api.php/provide/vod/",
      "canonical_id": "meta:nba%E5%A4%8F%E5%AD%A3%E8%81%94%E8%B5%9B%E9%9B%B7%E9%9C%86vs%E6%B9%96%E4%BA%BA20260711:0:0:unknown",
      "primary_category": "knowledge",
      "movie_release_channel": "unknown",
      "classification_evidence": [
        {
          "source": "source_category_id",
          "priority": 1,
          "category": "knowledge",
          "field": "source_category_id",
          "value": "8",
          "signal": "knowledge"
        }
      ],
      "classification_confidence": 0.99,
      "classification_confidence_level": "high",
      "classification_confidence_score": 0.99,
      "source_candidates": [
        {
          "source": "bfzy",
          "id": "152129",
          "url": "https://bfzyapi.com/api.php/provide/vod/",
          "updated_at": ""
        }
      ],
      "play_lines": [
        {
          "source": "bfzy",
          "name": "bfzym3u8",
          "url": "HD$https://s3.bfllvip.com/video/NBAxiajiliansaileitingVShuren20260711/c7fa410daca5/index.m3u8"
        }
      ],
      "semantic_tags": "quality hd 清晰度 高清",
      "snapshot_filter_evidence": "catalog-derived"
    },
    {
      "vod_id": "agg_W3sicyI6ImJmenkiLCJpZCI6IjE1MjExMiJ9XQ",
      "type_id": "55",
      "type_id_1": 53,
      "group_id": 0,
      "vod_name": "NBA夏季联赛：雷霆VS爵士20260708",
      "vod_sub": "",
      "vod_en": "NBAxiajiliansaileitingVSjueshi20260708",
      "vod_status": 1,
      "vod_letter": "N",
      "vod_color": "",
      "vod_tag": "",
      "vod_class": "篮球",
      "vod_pic": "https://img.picbf.com/upload/vod/20260713-1/18cac5b7ac7cca39fecfcee7918349ba.jpg",
      "vod_pic_thumb": "",
      "vod_pic_slide": "",
      "vod_pic_screenshot": "",
      "vod_actor": "",
      "vod_director": "",
      "vod_writer": "",
      "vod_behind": "",
      "vod_blurb": "暂无剧情介绍",
      "vod_remarks": "更新至HD",
      "vod_pubdate": "",
      "vod_total": "0",
      "vod_serial": "0",
      "vod_tv": "",
      "vod_weekday": "",
      "vod_area": "",
      "vod_lang": "",
      "vod_year": "0",
      "vod_version": "",
      "vod_state": "",
      "vod_author": "",
      "vod_jumpurl": "",
      "vod_tpl": "",
      "vod_tpl_play": "",
      "vod_tpl_down": "",
      "vod_isend": 0,
      "vod_lock": 0,
      "vod_level": 0,
      "vod_copyright": 0,
      "vod_points": 0,
      "vod_points_play": 0,
      "vod_points_down": 0,
      "vod_hits": 607,
      "vod_hits_day": 619,
      "vod_hits_week": 334,
      "vod_hits_month": 700,
      "vod_duration": "",
      "vod_up": 987,
      "vod_down": 264,
      "vod_score": "4.0",
      "vod_score_all": 468,
      "vod_score_num": 117,
      "vod_time": "2026-07-13 05:22:02",
      "vod_time_add": "1783891317",
      "vod_time_hits": 0,
      "vod_time_make": 0,
      "vod_trysee": 0,
      "vod_douban_id": 0,
      "vod_douban_score": "0.0",
      "vod_reurl": "",
      "vod_rel_vod": "",
      "vod_rel_art": "",
      "vod_pwd": "",
      "vod_pwd_url": "",
      "vod_pwd_play": "",
      "vod_pwd_play_url": "",
      "vod_pwd_down": "",
      "vod_pwd_down_url": "",
      "vod_content": "暂无简介，敬请期待",
      "vod_play_from": "bfzym3u8",
      "vod_play_server": "",
      "vod_play_note": "",
      "vod_play_url": "HD$https://s3.bfllvip.com/video/NBAxiajiliansaileitingVSjueshi20260708/b12d3b9a8e62/index.m3u8",
      "vod_down_from": "",
      "vod_down_server": "",
      "vod_down_note": "",
      "vod_down_url": "",
      "vod_plot": 0,
      "vod_plot_name": "",
      "vod_plot_detail": "",
      "type_name": "篮球",
      "source_category_id": "8",
      "source_category_name": "篮球",
      "_sourceSlug": "bfzy",
      "_sourceShort": "暴风",
      "source_url": "https://bfzyapi.com/api.php/provide/vod/",
      "canonical_id": "meta:nba%E5%A4%8F%E5%AD%A3%E8%81%94%E8%B5%9B%E9%9B%B7%E9%9C%86vs%E7%88%B5%E5%A3%AB20260708:0:0:unknown",
      "primary_category": "knowledge",
      "movie_release_channel": "unknown",
      "classification_evidence": [
        {
          "source": "source_category_id",
          "priority": 1,
          "category": "knowledge",
          "field": "source_category_id",
          "value": "8",
          "signal": "knowledge"
        }
      ],
      "classification_confidence": 0.99,
      "classification_confidence_level": "high",
      "classification_confidence_score": 0.99,
      "source_candidates": [
        {
          "source": "bfzy",
          "id": "152112",
          "url": "https://bfzyapi.com/api.php/provide/vod/",
          "updated_at": ""
        }
      ],
      "play_lines": [
        {
          "source": "bfzy",
          "name": "bfzym3u8",
          "url": "HD$https://s3.bfllvip.com/video/NBAxiajiliansaileitingVSjueshi20260708/b12d3b9a8e62/index.m3u8"
        }
      ],
      "semantic_tags": "quality hd 清晰度 高清",
      "snapshot_filter_evidence": "catalog-derived"
    },
    {
      "vod_id": "agg_W3sicyI6ImJmenkiLCJpZCI6IjE1MjU5NiJ9XQ",
      "type_id": "55",
      "type_id_1": 53,
      "group_id": 0,
      "vod_name": "NBA夏季联赛：雷霆VS勇士20260713",
      "vod_sub": "",
      "vod_en": "NBAxiajiliansaileitingVSyongshi20260713",
      "vod_status": 1,
      "vod_letter": "N",
      "vod_color": "",
      "vod_tag": "",
      "vod_class": "篮球",
      "vod_pic": "https://img.picbf.com/upload/vod/20260715-1/e2c06504cfebe179468db623c967b7be.jpg",
      "vod_pic_thumb": "",
      "vod_pic_slide": "",
      "vod_pic_screenshot": "",
      "vod_actor": "",
      "vod_director": "",
      "vod_writer": "",
      "vod_behind": "",
      "vod_blurb": "暂无剧情介绍",
      "vod_remarks": "更新至HD",
      "vod_pubdate": "",
      "vod_total": "0",
      "vod_serial": "0",
      "vod_tv": "",
      "vod_weekday": "",
      "vod_area": "",
      "vod_lang": "",
      "vod_year": "0",
      "vod_version": "",
      "vod_state": "",
      "vod_author": "",
      "vod_jumpurl": "",
      "vod_tpl": "",
      "vod_tpl_play": "",
      "vod_tpl_down": "",
      "vod_isend": 0,
      "vod_lock": 0,
      "vod_level": 0,
      "vod_copyright": 0,
      "vod_points": 0,
      "vod_points_play": 0,
      "vod_points_down": 0,
      "vod_hits": 11,
      "vod_hits_day": 773,
      "vod_hits_week": 41,
      "vod_hits_month": 28,
      "vod_duration": "",
      "vod_up": 391,
      "vod_down": 131,
      "vod_score": "8.0",
      "vod_score_all": 488,
      "vod_score_num": 61,
      "vod_time": "2026-07-15 16:06:17",
      "vod_time_add": "1784102775",
      "vod_time_hits": 0,
      "vod_time_make": 0,
      "vod_trysee": 0,
      "vod_douban_id": 0,
      "vod_douban_score": "0.0",
      "vod_reurl": "",
      "vod_rel_vod": "",
      "vod_rel_art": "",
      "vod_pwd": "",
      "vod_pwd_url": "",
      "vod_pwd_play": "",
      "vod_pwd_play_url": "",
      "vod_pwd_down": "",
      "vod_pwd_down_url": "",
      "vod_content": "暂无简介，敬请期待",
      "vod_play_from": "bfzym3u8",
      "vod_play_server": "",
      "vod_play_note": "",
      "vod_play_url": "HD$https://s3.bfllvip.com/video/NBAxiajiliansaileitingVSyongshi20260713/ab8cddfeb30a/index.m3u8",
      "vod_down_from": "",
      "vod_down_server": "",
      "vod_down_note": "",
      "vod_down_url": "",
      "vod_plot": 0,
      "vod_plot_name": "",
      "vod_plot_detail": "",
      "type_name": "篮球",
      "source_category_id": "8",
      "source_category_name": "篮球",
      "_sourceSlug": "bfzy",
      "_sourceShort": "暴风",
      "source_url": "https://bfzyapi.com/api.php/provide/vod/",
      "canonical_id": "meta:nba%E5%A4%8F%E5%AD%A3%E8%81%94%E8%B5%9B%E9%9B%B7%E9%9C%86vs%E5%8B%87%E5%A3%AB20260713:0:0:unknown",
      "primary_category": "knowledge",
      "movie_release_channel": "unknown",
      "classification_evidence": [
        {
          "source": "source_category_id",
          "priority": 1,
          "category": "knowledge",
          "field": "source_category_id",
          "value": "8",
          "signal": "knowledge"
        }
      ],
      "classification_confidence": 0.99,
      "classification_confidence_level": "high",
      "classification_confidence_score": 0.99,
      "source_candidates": [
        {
          "source": "bfzy",
          "id": "152596",
          "url": "https://bfzyapi.com/api.php/provide/vod/",
          "updated_at": ""
        }
      ],
      "play_lines": [
        {
          "source": "bfzy",
          "name": "bfzym3u8",
          "url": "HD$https://s3.bfllvip.com/video/NBAxiajiliansaileitingVSyongshi20260713/ab8cddfeb30a/index.m3u8"
        }
      ],
      "semantic_tags": "quality hd 清晰度 高清",
      "snapshot_filter_evidence": "catalog-derived"
    },
    {
      "vod_id": "agg_W3sicyI6ImJmenkiLCJpZCI6IjE1MjExNyJ9XQ",
      "type_id": "55",
      "type_id_1": 53,
      "group_id": 0,
      "vod_name": "NBA夏季联赛：马刺VS老鹰20260710",
      "vod_sub": "",
      "vod_en": "NBAxiajiliansaimaciVSlaoying20260710",
      "vod_status": 1,
      "vod_letter": "N",
      "vod_color": "",
      "vod_tag": "",
      "vod_class": "篮球",
      "vod_pic": "https://img.picbf.com/upload/vod/20260713-1/91f4ccb259b641993ad0c10c5a5053c0.jpg",
      "vod_pic_thumb": "",
      "vod_pic_slide": "",
      "vod_pic_screenshot": "",
      "vod_actor": "",
      "vod_director": "",
      "vod_writer": "",
      "vod_behind": "",
      "vod_blurb": "暂无剧情介绍",
      "vod_remarks": "更新至HD",
      "vod_pubdate": "",
      "vod_total": "0",
      "vod_serial": "0",
      "vod_tv": "",
      "vod_weekday": "",
      "vod_area": "",
      "vod_lang": "",
      "vod_year": "0",
      "vod_version": "",
      "vod_state": "",
      "vod_author": "",
      "vod_jumpurl": "",
      "vod_tpl": "",
      "vod_tpl_play": "",
      "vod_tpl_down": "",
      "vod_isend": 0,
      "vod_lock": 0,
      "vod_level": 0,
      "vod_copyright": 0,
      "vod_points": 0,
      "vod_points_play": 0,
      "vod_points_down": 0,
      "vod_hits": 31,
      "vod_hits_day": 727,
      "vod_hits_week": 344,
      "vod_hits_month": 52,
      "vod_duration": "",
      "vod_up": 557,
      "vod_down": 36,
      "vod_score": "4.0",
      "vod_score_all": 660,
      "vod_score_num": 165,
      "vod_time": "2026-07-13 05:24:22",
      "vod_time_add": "1783891459",
      "vod_time_hits": 0,
      "vod_time_make": 0,
      "vod_trysee": 0,
      "vod_douban_id": 0,
      "vod_douban_score": "0.0",
      "vod_reurl": "",
      "vod_rel_vod": "",
      "vod_rel_art": "",
      "vod_pwd": "",
      "vod_pwd_url": "",
      "vod_pwd_play": "",
      "vod_pwd_play_url": "",
      "vod_pwd_down": "",
      "vod_pwd_down_url": "",
      "vod_content": "暂无简介，敬请期待",
      "vod_play_from": "bfzym3u8",
      "vod_play_server": "",
      "vod_play_note": "",
      "vod_play_url": "HD$https://s3.bfllvip.com/video/NBAxiajiliansaimaciVSlaoying20260710/e8e09465e066/index.m3u8",
      "vod_down_from": "",
      "vod_down_server": "",
      "vod_down_note": "",
      "vod_down_url": "",
      "vod_plot": 0,
      "vod_plot_name": "",
      "vod_plot_detail": "",
      "type_name": "篮球",
      "source_category_id": "8",
      "source_category_name": "篮球",
      "_sourceSlug": "bfzy",
      "_sourceShort": "暴风",
      "source_url": "https://bfzyapi.com/api.php/provide/vod/",
      "canonical_id": "meta:nba%E5%A4%8F%E5%AD%A3%E8%81%94%E8%B5%9B%E9%A9%AC%E5%88%BAvs%E8%80%81%E9%B9%B020260710:0:0:unknown",
      "primary_category": "knowledge",
      "movie_release_channel": "unknown",
      "classification_evidence": [
        {
          "source": "source_category_id",
          "priority": 1,
          "category": "knowledge",
          "field": "source_category_id",
          "value": "8",
          "signal": "knowledge"
        }
      ],
      "classification_confidence": 0.99,
      "classification_confidence_level": "high",
      "classification_confidence_score": 0.99,
      "source_candidates": [
        {
          "source": "bfzy",
          "id": "152117",
          "url": "https://bfzyapi.com/api.php/provide/vod/",
          "updated_at": ""
        }
      ],
      "play_lines": [
        {
          "source": "bfzy",
          "name": "bfzym3u8",
          "url": "HD$https://s3.bfllvip.com/video/NBAxiajiliansaimaciVSlaoying20260710/e8e09465e066/index.m3u8"
        }
      ],
      "semantic_tags": "quality hd 清晰度 高清",
      "snapshot_filter_evidence": "catalog-derived"
    },
    {
      "vod_id": "agg_W3sicyI6ImJmenkiLCJpZCI6IjE1MjU5NyJ9XQ",
      "type_id": "55",
      "type_id_1": 53,
      "group_id": 0,
      "vod_name": "NBA夏季联赛：马刺VS雄鹿20260713",
      "vod_sub": "",
      "vod_en": "NBAxiajiliansaimaciVSxionglu20260713",
      "vod_status": 1,
      "vod_letter": "N",
      "vod_color": "",
      "vod_tag": "",
      "vod_class": "篮球",
      "vod_pic": "https://img.picbf.com/upload/vod/20260715-1/818b3b3cc730d78565d099d2ec29a3c5.jpg",
      "vod_pic_thumb": "",
      "vod_pic_slide": "",
      "vod_pic_screenshot": "",
      "vod_actor": "",
      "vod_director": "",
      "vod_writer": "",
      "vod_behind": "",
      "vod_blurb": "暂无剧情介绍",
      "vod_remarks": "更新至HD",
      "vod_pubdate": "",
      "vod_total": "0",
      "vod_serial": "0",
      "vod_tv": "",
      "vod_weekday": "",
      "vod_area": "",
      "vod_lang": "",
      "vod_year": "0",
      "vod_version": "",
      "vod_state": "",
      "vod_author": "",
      "vod_jumpurl": "",
      "vod_tpl": "",
      "vod_tpl_play": "",
      "vod_tpl_down": "",
      "vod_isend": 0,
      "vod_lock": 0,
      "vod_level": 0,
      "vod_copyright": 0,
      "vod_points": 0,
      "vod_points_play": 0,
      "vod_points_down": 0,
      "vod_hits": 369,
      "vod_hits_day": 839,
      "vod_hits_week": 245,
      "vod_hits_month": 49,
      "vod_duration": "",
      "vod_up": 681,
      "vod_down": 962,
      "vod_score": "3.0",
      "vod_score_all": 1833,
      "vod_score_num": 611,
      "vod_time": "2026-07-15 16:06:47",
      "vod_time_add": "1784102801",
      "vod_time_hits": 0,
      "vod_time_make": 0,
      "vod_trysee": 0,
      "vod_douban_id": 0,
      "vod_douban_score": "0.0",
      "vod_reurl": "",
      "vod_rel_vod": "",
      "vod_rel_art": "",
      "vod_pwd": "",
      "vod_pwd_url": "",
      "vod_pwd_play": "",
      "vod_pwd_play_url": "",
      "vod_pwd_down": "",
      "vod_pwd_down_url": "",
      "vod_content": "暂无简介，敬请期待",
      "vod_play_from": "bfzym3u8",
      "vod_play_server": "",
      "vod_play_note": "",
      "vod_play_url": "HD$https://s3.bfllvip.com/video/NBAxiajiliansaimaciVSxionglu20260713/c18ede6bceee/index.m3u8",
      "vod_down_from": "",
      "vod_down_server": "",
      "vod_down_note": "",
      "vod_down_url": "",
      "vod_plot": 0,
      "vod_plot_name": "",
      "vod_plot_detail": "",
      "type_name": "篮球",
      "source_category_id": "8",
      "source_category_name": "篮球",
      "_sourceSlug": "bfzy",
      "_sourceShort": "暴风",
      "source_url": "https://bfzyapi.com/api.php/provide/vod/",
      "canonical_id": "meta:nba%E5%A4%8F%E5%AD%A3%E8%81%94%E8%B5%9B%E9%A9%AC%E5%88%BAvs%E9%9B%84%E9%B9%BF20260713:0:0:unknown",
      "primary_category": "knowledge",
      "movie_release_channel": "unknown",
      "classification_evidence": [
        {
          "source": "source_category_id",
          "priority": 1,
          "category": "knowledge",
          "field": "source_category_id",
          "value": "8",
          "signal": "knowledge"
        }
      ],
      "classification_confidence": 0.99,
      "classification_confidence_level": "high",
      "classification_confidence_score": 0.99,
      "source_candidates": [
        {
          "source": "bfzy",
          "id": "152597",
          "url": "https://bfzyapi.com/api.php/provide/vod/",
          "updated_at": ""
        }
      ],
      "play_lines": [
        {
          "source": "bfzy",
          "name": "bfzym3u8",
          "url": "HD$https://s3.bfllvip.com/video/NBAxiajiliansaimaciVSxionglu20260713/c18ede6bceee/index.m3u8"
        }
      ],
      "semantic_tags": "quality hd 清晰度 高清",
      "snapshot_filter_evidence": "catalog-derived"
    },
    {
      "vod_id": "agg_W3sicyI6ImJmenkiLCJpZCI6IjE1MTU4MSJ9XQ",
      "type_id": "55",
      "type_id_1": 53,
      "group_id": 0,
      "vod_name": "NBA夏季联赛：马刺VS勇士金队20260706",
      "vod_sub": "",
      "vod_en": "NBAxiajiliansaimaciVSyongshijindui20260706",
      "vod_status": 1,
      "vod_letter": "N",
      "vod_color": "",
      "vod_tag": "",
      "vod_class": "篮球",
      "vod_pic": "https://img.picbf.com/upload/vod/20260707-1/41e691c74b5fb205cb6e5143312b4ae5.jpg",
      "vod_pic_thumb": "",
      "vod_pic_slide": "",
      "vod_pic_screenshot": "",
      "vod_actor": "",
      "vod_director": "",
      "vod_writer": "",
      "vod_behind": "",
      "vod_blurb": "暂无剧情介绍",
      "vod_remarks": "更新至HD",
      "vod_pubdate": "",
      "vod_total": "0",
      "vod_serial": "0",
      "vod_tv": "",
      "vod_weekday": "",
      "vod_area": "",
      "vod_lang": "",
      "vod_year": "0",
      "vod_version": "",
      "vod_state": "",
      "vod_author": "",
      "vod_jumpurl": "",
      "vod_tpl": "",
      "vod_tpl_play": "",
      "vod_tpl_down": "",
      "vod_isend": 0,
      "vod_lock": 0,
      "vod_level": 0,
      "vod_copyright": 0,
      "vod_points": 0,
      "vod_points_play": 0,
      "vod_points_down": 0,
      "vod_hits": 868,
      "vod_hits_day": 19,
      "vod_hits_week": 140,
      "vod_hits_month": 395,
      "vod_duration": "",
      "vod_up": 454,
      "vod_down": 786,
      "vod_score": "5.0",
      "vod_score_all": 3415,
      "vod_score_num": 683,
      "vod_time": "2026-07-07 14:41:00",
      "vod_time_add": "1783406458",
      "vod_time_hits": 0,
      "vod_time_make": 0,
      "vod_trysee": 0,
      "vod_douban_id": 0,
      "vod_douban_score": "0.0",
      "vod_reurl": "",
      "vod_rel_vod": "",
      "vod_rel_art": "",
      "vod_pwd": "",
      "vod_pwd_url": "",
      "vod_pwd_play": "",
      "vod_pwd_play_url": "",
      "vod_pwd_down": "",
      "vod_pwd_down_url": "",
      "vod_content": "暂无简介，敬请期待",
      "vod_play_from": "bfzym3u8",
      "vod_play_server": "",
      "vod_play_note": "",
      "vod_play_url": "HD$https://s3.bfllvip.com/video/NBAxiajiliansaimaciVSyongshijindui20260706/fb2f53a1266d/index.m3u8",
      "vod_down_from": "",
      "vod_down_server": "",
      "vod_down_note": "",
      "vod_down_url": "",
      "vod_plot": 0,
      "vod_plot_name": "",
      "vod_plot_detail": "",
      "type_name": "篮球",
      "source_category_id": "8",
      "source_category_name": "篮球",
      "_sourceSlug": "bfzy",
      "_sourceShort": "暴风",
      "source_url": "https://bfzyapi.com/api.php/provide/vod/",
      "canonical_id": "meta:nba%E5%A4%8F%E5%AD%A3%E8%81%94%E8%B5%9B%E9%A9%AC%E5%88%BAvs%E5%8B%87%E5%A3%AB%E9%87%91%E9%98%9F20260706:0:0:unknown",
      "primary_category": "knowledge",
      "movie_release_channel": "unknown",
      "classification_evidence": [
        {
          "source": "source_category_id",
          "priority": 1,
          "category": "knowledge",
          "field": "source_category_id",
          "value": "8",
          "signal": "knowledge"
        }
      ],
      "classification_confidence": 0.99,
      "classification_confidence_level": "high",
      "classification_confidence_score": 0.99,
      "source_candidates": [
        {
          "source": "bfzy",
          "id": "151581",
          "url": "https://bfzyapi.com/api.php/provide/vod/",
          "updated_at": ""
        }
      ],
      "play_lines": [
        {
          "source": "bfzy",
          "name": "bfzym3u8",
          "url": "HD$https://s3.bfllvip.com/video/NBAxiajiliansaimaciVSyongshijindui20260706/fb2f53a1266d/index.m3u8"
        }
      ],
      "semantic_tags": "quality hd 清晰度 高清",
      "snapshot_filter_evidence": "catalog-derived"
    },
    {
      "vod_id": "agg_W3sicyI6ImJmenkiLCJpZCI6IjE1MjYwNCJ9XQ",
      "type_id": "55",
      "type_id_1": 53,
      "group_id": 0,
      "vod_name": "NBA夏季联赛：猛龙VS步行者20260714",
      "vod_sub": "",
      "vod_en": "NBAxiajiliansaimenglongVSbuxingzhe20260714",
      "vod_status": 1,
      "vod_letter": "N",
      "vod_color": "",
      "vod_tag": "",
      "vod_class": "篮球",
      "vod_pic": "https://img.picbf.com/upload/vod/20260715-1/aea971b5d4c85054b7f3dbe289e7a7ae.jpg",
      "vod_pic_thumb": "",
      "vod_pic_slide": "",
      "vod_pic_screenshot": "",
      "vod_actor": "",
      "vod_director": "",
      "vod_writer": "",
      "vod_behind": "",
      "vod_blurb": "暂无剧情介绍",
      "vod_remarks": "更新至HD",
      "vod_pubdate": "",
      "vod_total": "0",
      "vod_serial": "0",
      "vod_tv": "",
      "vod_weekday": "",
      "vod_area": "",
      "vod_lang": "",
      "vod_year": "0",
      "vod_version": "",
      "vod_state": "",
      "vod_author": "",
      "vod_jumpurl": "",
      "vod_tpl": "",
      "vod_tpl_play": "",
      "vod_tpl_down": "",
      "vod_isend": 0,
      "vod_lock": 0,
      "vod_level": 0,
      "vod_copyright": 0,
      "vod_points": 0,
      "vod_points_play": 0,
      "vod_points_down": 0,
      "vod_hits": 448,
      "vod_hits_day": 127,
      "vod_hits_week": 474,
      "vod_hits_month": 670,
      "vod_duration": "",
      "vod_up": 30,
      "vod_down": 598,
      "vod_score": "5.0",
      "vod_score_all": 145,
      "vod_score_num": 29,
      "vod_time": "2026-07-15 16:10:08",
      "vod_time_add": "1784103002",
      "vod_time_hits": 0,
      "vod_time_make": 0,
      "vod_trysee": 0,
      "vod_douban_id": 0,
      "vod_douban_score": "0.0",
      "vod_reurl": "",
      "vod_rel_vod": "",
      "vod_rel_art": "",
      "vod_pwd": "",
      "vod_pwd_url": "",
      "vod_pwd_play": "",
      "vod_pwd_play_url": "",
      "vod_pwd_down": "",
      "vod_pwd_down_url": "",
      "vod_content": "暂无简介，敬请期待",
      "vod_play_from": "bfzym3u8",
      "vod_play_server": "",
      "vod_play_note": "",
      "vod_play_url": "HD$https://s3.bfllvip.com/video/NBAxiajiliansaimenglongVSbuxingzhe20260714/9ff56d84f417/index.m3u8",
      "vod_down_from": "",
      "vod_down_server": "",
      "vod_down_note": "",
      "vod_down_url": "",
      "vod_plot": 0,
      "vod_plot_name": "",
      "vod_plot_detail": "",
      "type_name": "篮球",
      "source_category_id": "8",
      "source_category_name": "篮球",
      "_sourceSlug": "bfzy",
      "_sourceShort": "暴风",
      "source_url": "https://bfzyapi.com/api.php/provide/vod/",
      "canonical_id": "meta:nba%E5%A4%8F%E5%AD%A3%E8%81%94%E8%B5%9B%E7%8C%9B%E9%BE%99vs%E6%AD%A5%E8%A1%8C%E8%80%8520260714:0:0:unknown",
      "primary_category": "knowledge",
      "movie_release_channel": "unknown",
      "classification_evidence": [
        {
          "source": "source_category_id",
          "priority": 1,
          "category": "knowledge",
          "field": "source_category_id",
          "value": "8",
          "signal": "knowledge"
        }
      ],
      "classification_confidence": 0.99,
      "classification_confidence_level": "high",
      "classification_confidence_score": 0.99,
      "source_candidates": [
        {
          "source": "bfzy",
          "id": "152604",
          "url": "https://bfzyapi.com/api.php/provide/vod/",
          "updated_at": ""
        }
      ],
      "play_lines": [
        {
          "source": "bfzy",
          "name": "bfzym3u8",
          "url": "HD$https://s3.bfllvip.com/video/NBAxiajiliansaimenglongVSbuxingzhe20260714/9ff56d84f417/index.m3u8"
        }
      ],
      "semantic_tags": "quality hd 清晰度 高清",
      "snapshot_filter_evidence": "catalog-derived"
    },
    {
      "vod_id": "agg_W3sicyI6ImJmenkiLCJpZCI6IjE1MjkwMCJ9XQ",
      "type_id": "55",
      "type_id_1": 53,
      "group_id": 0,
      "vod_name": "NBA夏季联赛：魔术VS76人20260716",
      "vod_sub": "",
      "vod_en": "NBAxiajiliansaimoshuVS76ren20260716",
      "vod_status": 1,
      "vod_letter": "N",
      "vod_color": "",
      "vod_tag": "",
      "vod_class": "篮球",
      "vod_pic": "https://img.picbf.com/upload/vod/20260717-1/380459f7fc25b8ec4a6ffa879da4d480.jpg",
      "vod_pic_thumb": "",
      "vod_pic_slide": "",
      "vod_pic_screenshot": "",
      "vod_actor": "",
      "vod_director": "",
      "vod_writer": "",
      "vod_behind": "",
      "vod_blurb": "暂无剧情介绍",
      "vod_remarks": "更新至HD",
      "vod_pubdate": "",
      "vod_total": "0",
      "vod_serial": "0",
      "vod_tv": "",
      "vod_weekday": "",
      "vod_area": "",
      "vod_lang": "",
      "vod_year": "0",
      "vod_version": "",
      "vod_state": "",
      "vod_author": "",
      "vod_jumpurl": "",
      "vod_tpl": "",
      "vod_tpl_play": "",
      "vod_tpl_down": "",
      "vod_isend": 0,
      "vod_lock": 0,
      "vod_level": 0,
      "vod_copyright": 0,
      "vod_points": 0,
      "vod_points_play": 0,
      "vod_points_down": 0,
      "vod_hits": 999,
      "vod_hits_day": 420,
      "vod_hits_week": 678,
      "vod_hits_month": 9,
      "vod_duration": "",
      "vod_up": 856,
      "vod_down": 27,
      "vod_score": "10.0",
      "vod_score_all": 2000,
      "vod_score_num": 200,
      "vod_time": "2026-07-17 22:07:05",
      "vod_time_add": "1784297221",
      "vod_time_hits": 0,
      "vod_time_make": 0,
      "vod_trysee": 0,
      "vod_douban_id": 0,
      "vod_douban_score": "0.0",
      "vod_reurl": "",
      "vod_rel_vod": "",
      "vod_rel_art": "",
      "vod_pwd": "",
      "vod_pwd_url": "",
      "vod_pwd_play": "",
      "vod_pwd_play_url": "",
      "vod_pwd_down": "",
      "vod_pwd_down_url": "",
      "vod_content": "暂无简介，敬请期待",
      "vod_play_from": "bfzym3u8",
      "vod_play_server": "",
      "vod_play_note": "",
      "vod_play_url": "HD$https://s3.bfllvip.com/video/NBAxiajiliansaimoshuVS76ren20260716/3dbbe445097e/index.m3u8",
      "vod_down_from": "",
      "vod_down_server": "",
      "vod_down_note": "",
      "vod_down_url": "",
      "vod_plot": 0,
      "vod_plot_name": "",
      "vod_plot_detail": "",
      "type_name": "篮球",
      "source_category_id": "8",
      "source_category_name": "篮球",
      "_sourceSlug": "bfzy",
      "_sourceShort": "暴风",
      "source_url": "https://bfzyapi.com/api.php/provide/vod/",
      "canonical_id": "meta:nba%E5%A4%8F%E5%AD%A3%E8%81%94%E8%B5%9B%E9%AD%94%E6%9C%AFvs76%E4%BA%BA20260716:0:0:unknown",
      "primary_category": "knowledge",
      "movie_release_channel": "unknown",
      "classification_evidence": [
        {
          "source": "source_category_id",
          "priority": 1,
          "category": "knowledge",
          "field": "source_category_id",
          "value": "8",
          "signal": "knowledge"
        }
      ],
      "classification_confidence": 0.99,
      "classification_confidence_level": "high",
      "classification_confidence_score": 0.99,
      "source_candidates": [
        {
          "source": "bfzy",
          "id": "152900",
          "url": "https://bfzyapi.com/api.php/provide/vod/",
          "updated_at": ""
        }
      ],
      "play_lines": [
        {
          "source": "bfzy",
          "name": "bfzym3u8",
          "url": "HD$https://s3.bfllvip.com/video/NBAxiajiliansaimoshuVS76ren20260716/3dbbe445097e/index.m3u8"
        }
      ],
      "semantic_tags": "quality hd 清晰度 高清",
      "snapshot_filter_evidence": "catalog-derived"
    },
    {
      "vod_id": "agg_W3sicyI6ImJmenkiLCJpZCI6IjE1MjU5OCJ9XQ",
      "type_id": "55",
      "type_id_1": 53,
      "group_id": 0,
      "vod_name": "NBA夏季联赛：魔术VS开拓者20260713",
      "vod_sub": "",
      "vod_en": "NBAxiajiliansaimoshuVSkaituozhe20260713",
      "vod_status": 1,
      "vod_letter": "N",
      "vod_color": "",
      "vod_tag": "",
      "vod_class": "篮球",
      "vod_pic": "https://img.picbf.com/upload/vod/20260715-1/fb764f363727f94025068f2459fef87c.jpg",
      "vod_pic_thumb": "",
      "vod_pic_slide": "",
      "vod_pic_screenshot": "",
      "vod_actor": "",
      "vod_director": "",
      "vod_writer": "",
      "vod_behind": "",
      "vod_blurb": "暂无剧情介绍",
      "vod_remarks": "更新至HD",
      "vod_pubdate": "",
      "vod_total": "0",
      "vod_serial": "0",
      "vod_tv": "",
      "vod_weekday": "",
      "vod_area": "",
      "vod_lang": "",
      "vod_year": "0",
      "vod_version": "",
      "vod_state": "",
      "vod_author": "",
      "vod_jumpurl": "",
      "vod_tpl": "",
      "vod_tpl_play": "",
      "vod_tpl_down": "",
      "vod_isend": 0,
      "vod_lock": 0,
      "vod_level": 0,
      "vod_copyright": 0,
      "vod_points": 0,
      "vod_points_play": 0,
      "vod_points_down": 0,
      "vod_hits": 999,
      "vod_hits_day": 485,
      "vod_hits_week": 309,
      "vod_hits_month": 846,
      "vod_duration": "",
      "vod_up": 812,
      "vod_down": 674,
      "vod_score": "6.0",
      "vod_score_all": 1254,
      "vod_score_num": 209,
      "vod_time": "2026-07-15 16:07:07",
      "vod_time_add": "1784102826",
      "vod_time_hits": 0,
      "vod_time_make": 0,
      "vod_trysee": 0,
      "vod_douban_id": 0,
      "vod_douban_score": "0.0",
      "vod_reurl": "",
      "vod_rel_vod": "",
      "vod_rel_art": "",
      "vod_pwd": "",
      "vod_pwd_url": "",
      "vod_pwd_play": "",
      "vod_pwd_play_url": "",
      "vod_pwd_down": "",
      "vod_pwd_down_url": "",
      "vod_content": "暂无简介，敬请期待",
      "vod_play_from": "bfzym3u8",
      "vod_play_server": "",
      "vod_play_note": "",
      "vod_play_url": "HD$https://s3.bfllvip.com/video/NBAxiajiliansaimoshuVSkaituozhe20260713/3a1118ed5a50/index.m3u8",
      "vod_down_from": "",
      "vod_down_server": "",
      "vod_down_note": "",
      "vod_down_url": "",
      "vod_plot": 0,
      "vod_plot_name": "",
      "vod_plot_detail": "",
      "type_name": "篮球",
      "source_category_id": "8",
      "source_category_name": "篮球",
      "_sourceSlug": "bfzy",
      "_sourceShort": "暴风",
      "source_url": "https://bfzyapi.com/api.php/provide/vod/",
      "canonical_id": "meta:nba%E5%A4%8F%E5%AD%A3%E8%81%94%E8%B5%9B%E9%AD%94%E6%9C%AFvs%E5%BC%80%E6%8B%93%E8%80%8520260713:0:0:unknown",
      "primary_category": "knowledge",
      "movie_release_channel": "unknown",
      "classification_evidence": [
        {
          "source": "source_category_id",
          "priority": 1,
          "category": "knowledge",
          "field": "source_category_id",
          "value": "8",
          "signal": "knowledge"
        }
      ],
      "classification_confidence": 0.99,
      "classification_confidence_level": "high",
      "classification_confidence_score": 0.99,
      "source_candidates": [
        {
          "source": "bfzy",
          "id": "152598",
          "url": "https://bfzyapi.com/api.php/provide/vod/",
          "updated_at": ""
        }
      ],
      "play_lines": [
        {
          "source": "bfzy",
          "name": "bfzym3u8",
          "url": "HD$https://s3.bfllvip.com/video/NBAxiajiliansaimoshuVSkaituozhe20260713/3a1118ed5a50/index.m3u8"
        }
      ],
      "semantic_tags": "quality hd 清晰度 高清",
      "snapshot_filter_evidence": "catalog-derived"
    },
    {
      "vod_id": "agg_W3sicyI6ImJmenkiLCJpZCI6IjE1MjU5MSJ9XQ",
      "type_id": "55",
      "type_id_1": 53,
      "group_id": 0,
      "vod_name": "NBA夏季联赛：尼克斯VS马刺20260712",
      "vod_sub": "",
      "vod_en": "NBAxiajiliansainikesiVSmaci20260712",
      "vod_status": 1,
      "vod_letter": "N",
      "vod_color": "",
      "vod_tag": "",
      "vod_class": "篮球",
      "vod_pic": "https://img.picbf.com/upload/vod/20260715-1/2713db0fd98c0edd15ce410a80935489.jpg",
      "vod_pic_thumb": "",
      "vod_pic_slide": "",
      "vod_pic_screenshot": "",
      "vod_actor": "",
      "vod_director": "",
      "vod_writer": "",
      "vod_behind": "",
      "vod_blurb": "暂无剧情介绍",
      "vod_remarks": "更新至HD",
      "vod_pubdate": "",
      "vod_total": "0",
      "vod_serial": "0",
      "vod_tv": "",
      "vod_weekday": "",
      "vod_area": "",
      "vod_lang": "",
      "vod_year": "0",
      "vod_version": "",
      "vod_state": "",
      "vod_author": "",
      "vod_jumpurl": "",
      "vod_tpl": "",
      "vod_tpl_play": "",
      "vod_tpl_down": "",
      "vod_isend": 0,
      "vod_lock": 0,
      "vod_level": 0,
      "vod_copyright": 0,
      "vod_points": 0,
      "vod_points_play": 0,
      "vod_points_down": 0,
      "vod_hits": 264,
      "vod_hits_day": 469,
      "vod_hits_week": 226,
      "vod_hits_month": 250,
      "vod_duration": "",
      "vod_up": 630,
      "vod_down": 106,
      "vod_score": "5.0",
      "vod_score_all": 2040,
      "vod_score_num": 408,
      "vod_time": "2026-07-15 16:02:57",
      "vod_time_add": "1784102569",
      "vod_time_hits": 0,
      "vod_time_make": 0,
      "vod_trysee": 0,
      "vod_douban_id": 0,
      "vod_douban_score": "0.0",
      "vod_reurl": "",
      "vod_rel_vod": "",
      "vod_rel_art": "",
      "vod_pwd": "",
      "vod_pwd_url": "",
      "vod_pwd_play": "",
      "vod_pwd_play_url": "",
      "vod_pwd_down": "",
      "vod_pwd_down_url": "",
      "vod_content": "暂无简介，敬请期待",
      "vod_play_from": "bfzym3u8",
      "vod_play_server": "",
      "vod_play_note": "",
      "vod_play_url": "HD$https://s3.bfllvip.com/video/NBAxiajiliansainikesiVSmaci20260712/5784c5029d98/index.m3u8",
      "vod_down_from": "",
      "vod_down_server": "",
      "vod_down_note": "",
      "vod_down_url": "",
      "vod_plot": 0,
      "vod_plot_name": "",
      "vod_plot_detail": "",
      "type_name": "篮球",
      "source_category_id": "8",
      "source_category_name": "篮球",
      "_sourceSlug": "bfzy",
      "_sourceShort": "暴风",
      "source_url": "https://bfzyapi.com/api.php/provide/vod/",
      "canonical_id": "meta:nba%E5%A4%8F%E5%AD%A3%E8%81%94%E8%B5%9B%E5%B0%BC%E5%85%8B%E6%96%AFvs%E9%A9%AC%E5%88%BA20260712:0:0:unknown",
      "primary_category": "knowledge",
      "movie_release_channel": "unknown",
      "classification_evidence": [
        {
          "source": "source_category_id",
          "priority": 1,
          "category": "knowledge",
          "field": "source_category_id",
          "value": "8",
          "signal": "knowledge"
        }
      ],
      "classification_confidence": 0.99,
      "classification_confidence_level": "high",
      "classification_confidence_score": 0.99,
      "source_candidates": [
        {
          "source": "bfzy",
          "id": "152591",
          "url": "https://bfzyapi.com/api.php/provide/vod/",
          "updated_at": ""
        }
      ],
      "play_lines": [
        {
          "source": "bfzy",
          "name": "bfzym3u8",
          "url": "HD$https://s3.bfllvip.com/video/NBAxiajiliansainikesiVSmaci20260712/5784c5029d98/index.m3u8"
        }
      ],
      "semantic_tags": "quality hd 清晰度 高清",
      "snapshot_filter_evidence": "catalog-derived"
    },
    {
      "vod_id": "agg_W3sicyI6ImJmenkiLCJpZCI6IjE1MjkwMSJ9XQ",
      "type_id": "55",
      "type_id_1": 53,
      "group_id": 0,
      "vod_name": "NBA夏季联赛：奇才VS快船20260716",
      "vod_sub": "",
      "vod_en": "NBAxiajiliansaiqicaiVSkuaichuan20260716",
      "vod_status": 1,
      "vod_letter": "N",
      "vod_color": "",
      "vod_tag": "",
      "vod_class": "篮球",
      "vod_pic": "https://img.picbf.com/upload/vod/20260717-1/3587e2337de1e4dd8b8510524f6e0682.jpg",
      "vod_pic_thumb": "",
      "vod_pic_slide": "",
      "vod_pic_screenshot": "",
      "vod_actor": "",
      "vod_director": "",
      "vod_writer": "",
      "vod_behind": "",
      "vod_blurb": "暂无剧情介绍",
      "vod_remarks": "更新至HD",
      "vod_pubdate": "",
      "vod_total": "0",
      "vod_serial": "0",
      "vod_tv": "",
      "vod_weekday": "",
      "vod_area": "",
      "vod_lang": "",
      "vod_year": "0",
      "vod_version": "",
      "vod_state": "",
      "vod_author": "",
      "vod_jumpurl": "",
      "vod_tpl": "",
      "vod_tpl_play": "",
      "vod_tpl_down": "",
      "vod_isend": 0,
      "vod_lock": 0,
      "vod_level": 0,
      "vod_copyright": 0,
      "vod_points": 0,
      "vod_points_play": 0,
      "vod_points_down": 0,
      "vod_hits": 690,
      "vod_hits_day": 763,
      "vod_hits_week": 181,
      "vod_hits_month": 665,
      "vod_duration": "",
      "vod_up": 608,
      "vod_down": 313,
      "vod_score": "8.0",
      "vod_score_all": 3664,
      "vod_score_num": 458,
      "vod_time": "2026-07-17 22:07:35",
      "vod_time_add": "1784297244",
      "vod_time_hits": 0,
      "vod_time_make": 0,
      "vod_trysee": 0,
      "vod_douban_id": 0,
      "vod_douban_score": "0.0",
      "vod_reurl": "",
      "vod_rel_vod": "",
      "vod_rel_art": "",
      "vod_pwd": "",
      "vod_pwd_url": "",
      "vod_pwd_play": "",
      "vod_pwd_play_url": "",
      "vod_pwd_down": "",
      "vod_pwd_down_url": "",
      "vod_content": "暂无简介，敬请期待",
      "vod_play_from": "bfzym3u8",
      "vod_play_server": "",
      "vod_play_note": "",
      "vod_play_url": "HD$https://s3.bfllvip.com/video/NBAxiajiliansaiqicaiVSkuaichuan20260716/fd54e0e16ef9/index.m3u8",
      "vod_down_from": "",
      "vod_down_server": "",
      "vod_down_note": "",
      "vod_down_url": "",
      "vod_plot": 0,
      "vod_plot_name": "",
      "vod_plot_detail": "",
      "type_name": "篮球",
      "source_category_id": "8",
      "source_category_name": "篮球",
      "_sourceSlug": "bfzy",
      "_sourceShort": "暴风",
      "source_url": "https://bfzyapi.com/api.php/provide/vod/",
      "canonical_id": "meta:nba%E5%A4%8F%E5%AD%A3%E8%81%94%E8%B5%9B%E5%A5%87%E6%89%8Dvs%E5%BF%AB%E8%88%B920260716:0:0:unknown",
      "primary_category": "knowledge",
      "movie_release_channel": "unknown",
      "classification_evidence": [
        {
          "source": "source_category_id",
          "priority": 1,
          "category": "knowledge",
          "field": "source_category_id",
          "value": "8",
          "signal": "knowledge"
        }
      ],
      "classification_confidence": 0.99,
      "classification_confidence_level": "high",
      "classification_confidence_score": 0.99,
      "source_candidates": [
        {
          "source": "bfzy",
          "id": "152901",
          "url": "https://bfzyapi.com/api.php/provide/vod/",
          "updated_at": ""
        }
      ],
      "play_lines": [
        {
          "source": "bfzy",
          "name": "bfzym3u8",
          "url": "HD$https://s3.bfllvip.com/video/NBAxiajiliansaiqicaiVSkuaichuan20260716/fd54e0e16ef9/index.m3u8"
        }
      ],
      "semantic_tags": "quality hd 清晰度 高清",
      "snapshot_filter_evidence": "catalog-derived"
    },
    {
      "vod_id": "agg_W3sicyI6ImJmenkiLCJpZCI6IjE1MjEzMCJ9XQ",
      "type_id": "55",
      "type_id_1": 53,
      "group_id": 0,
      "vod_name": "NBA夏季联赛：骑士VS步行者20260711",
      "vod_sub": "",
      "vod_en": "NBAxiajiliansaiqishiVSbuxingzhe20260711",
      "vod_status": 1,
      "vod_letter": "N",
      "vod_color": "",
      "vod_tag": "",
      "vod_class": "篮球",
      "vod_pic": "https://img.picbf.com/upload/vod/20260713-1/2d9891c5ad14de93f7d5525dd2e3fe3c.jpg",
      "vod_pic_thumb": "",
      "vod_pic_slide": "",
      "vod_pic_screenshot": "",
      "vod_actor": "",
      "vod_director": "",
      "vod_writer": "",
      "vod_behind": "",
      "vod_blurb": "暂无剧情介绍",
      "vod_remarks": "更新至HD",
      "vod_pubdate": "",
      "vod_total": "0",
      "vod_serial": "0",
      "vod_tv": "",
      "vod_weekday": "",
      "vod_area": "",
      "vod_lang": "",
      "vod_year": "0",
      "vod_version": "",
      "vod_state": "",
      "vod_author": "",
      "vod_jumpurl": "",
      "vod_tpl": "",
      "vod_tpl_play": "",
      "vod_tpl_down": "",
      "vod_isend": 0,
      "vod_lock": 0,
      "vod_level": 0,
      "vod_copyright": 0,
      "vod_points": 0,
      "vod_points_play": 0,
      "vod_points_down": 0,
      "vod_hits": 786,
      "vod_hits_day": 534,
      "vod_hits_week": 201,
      "vod_hits_month": 973,
      "vod_duration": "",
      "vod_up": 942,
      "vod_down": 900,
      "vod_score": "9.0",
      "vod_score_all": 8811,
      "vod_score_num": 979,
      "vod_time": "2026-07-13 05:30:13",
      "vod_time_add": "1783891803",
      "vod_time_hits": 0,
      "vod_time_make": 0,
      "vod_trysee": 0,
      "vod_douban_id": 0,
      "vod_douban_score": "0.0",
      "vod_reurl": "",
      "vod_rel_vod": "",
      "vod_rel_art": "",
      "vod_pwd": "",
      "vod_pwd_url": "",
      "vod_pwd_play": "",
      "vod_pwd_play_url": "",
      "vod_pwd_down": "",
      "vod_pwd_down_url": "",
      "vod_content": "暂无简介，敬请期待",
      "vod_play_from": "bfzym3u8",
      "vod_play_server": "",
      "vod_play_note": "",
      "vod_play_url": "HD$https://s3.bfllvip.com/video/NBAxiajiliansaiqishiVSbuxingzhe20260711/b5dc786a5fd5/index.m3u8",
      "vod_down_from": "",
      "vod_down_server": "",
      "vod_down_note": "",
      "vod_down_url": "",
      "vod_plot": 0,
      "vod_plot_name": "",
      "vod_plot_detail": "",
      "type_name": "篮球",
      "source_category_id": "8",
      "source_category_name": "篮球",
      "_sourceSlug": "bfzy",
      "_sourceShort": "暴风",
      "source_url": "https://bfzyapi.com/api.php/provide/vod/",
      "canonical_id": "meta:nba%E5%A4%8F%E5%AD%A3%E8%81%94%E8%B5%9B%E9%AA%91%E5%A3%ABvs%E6%AD%A5%E8%A1%8C%E8%80%8520260711:0:0:unknown",
      "primary_category": "knowledge",
      "movie_release_channel": "unknown",
      "classification_evidence": [
        {
          "source": "source_category_id",
          "priority": 1,
          "category": "knowledge",
          "field": "source_category_id",
          "value": "8",
          "signal": "knowledge"
        }
      ],
      "classification_confidence": 0.99,
      "classification_confidence_level": "high",
      "classification_confidence_score": 0.99,
      "source_candidates": [
        {
          "source": "bfzy",
          "id": "152130",
          "url": "https://bfzyapi.com/api.php/provide/vod/",
          "updated_at": ""
        }
      ],
      "play_lines": [
        {
          "source": "bfzy",
          "name": "bfzym3u8",
          "url": "HD$https://s3.bfllvip.com/video/NBAxiajiliansaiqishiVSbuxingzhe20260711/b5dc786a5fd5/index.m3u8"
        }
      ],
      "semantic_tags": "quality hd 清晰度 高清",
      "snapshot_filter_evidence": "catalog-derived"
    },
    {
      "vod_id": "agg_W3sicyI6ImJmenkiLCJpZCI6IjE1MjU5OSJ9XQ",
      "type_id": "55",
      "type_id_1": 53,
      "group_id": 0,
      "vod_name": "NBA夏季联赛：骑士VS活塞20260713",
      "vod_sub": "",
      "vod_en": "NBAxiajiliansaiqishiVShuosai20260713",
      "vod_status": 1,
      "vod_letter": "N",
      "vod_color": "",
      "vod_tag": "",
      "vod_class": "篮球",
      "vod_pic": "https://img.picbf.com/upload/vod/20260715-1/b03b70b48dfeac1636390234739cff65.jpg",
      "vod_pic_thumb": "",
      "vod_pic_slide": "",
      "vod_pic_screenshot": "",
      "vod_actor": "",
      "vod_director": "",
      "vod_writer": "",
      "vod_behind": "",
      "vod_blurb": "暂无剧情介绍",
      "vod_remarks": "更新至HD",
      "vod_pubdate": "",
      "vod_total": "0",
      "vod_serial": "0",
      "vod_tv": "",
      "vod_weekday": "",
      "vod_area": "",
      "vod_lang": "",
      "vod_year": "0",
      "vod_version": "",
      "vod_state": "",
      "vod_author": "",
      "vod_jumpurl": "",
      "vod_tpl": "",
      "vod_tpl_play": "",
      "vod_tpl_down": "",
      "vod_isend": 0,
      "vod_lock": 0,
      "vod_level": 0,
      "vod_copyright": 0,
      "vod_points": 0,
      "vod_points_play": 0,
      "vod_points_down": 0,
      "vod_hits": 508,
      "vod_hits_day": 412,
      "vod_hits_week": 832,
      "vod_hits_month": 486,
      "vod_duration": "",
      "vod_up": 733,
      "vod_down": 615,
      "vod_score": "8.0",
      "vod_score_all": 408,
      "vod_score_num": 51,
      "vod_time": "2026-07-15 16:07:37",
      "vod_time_add": "1784102848",
      "vod_time_hits": 0,
      "vod_time_make": 0,
      "vod_trysee": 0,
      "vod_douban_id": 0,
      "vod_douban_score": "0.0",
      "vod_reurl": "",
      "vod_rel_vod": "",
      "vod_rel_art": "",
      "vod_pwd": "",
      "vod_pwd_url": "",
      "vod_pwd_play": "",
      "vod_pwd_play_url": "",
      "vod_pwd_down": "",
      "vod_pwd_down_url": "",
      "vod_content": "暂无简介，敬请期待",
      "vod_play_from": "bfzym3u8",
      "vod_play_server": "",
      "vod_play_note": "",
      "vod_play_url": "HD$https://s3.bfllvip.com/video/NBAxiajiliansaiqishiVShuosai20260713/a034cadce9c2/index.m3u8",
      "vod_down_from": "",
      "vod_down_server": "",
      "vod_down_note": "",
      "vod_down_url": "",
      "vod_plot": 0,
      "vod_plot_name": "",
      "vod_plot_detail": "",
      "type_name": "篮球",
      "source_category_id": "8",
      "source_category_name": "篮球",
      "_sourceSlug": "bfzy",
      "_sourceShort": "暴风",
      "source_url": "https://bfzyapi.com/api.php/provide/vod/",
      "canonical_id": "meta:nba%E5%A4%8F%E5%AD%A3%E8%81%94%E8%B5%9B%E9%AA%91%E5%A3%ABvs%E6%B4%BB%E5%A1%9E20260713:0:0:unknown",
      "primary_category": "knowledge",
      "movie_release_channel": "unknown",
      "classification_evidence": [
        {
          "source": "source_category_id",
          "priority": 1,
          "category": "knowledge",
          "field": "source_category_id",
          "value": "8",
          "signal": "knowledge"
        }
      ],
      "classification_confidence": 0.99,
      "classification_confidence_level": "high",
      "classification_confidence_score": 0.99,
      "source_candidates": [
        {
          "source": "bfzy",
          "id": "152599",
          "url": "https://bfzyapi.com/api.php/provide/vod/",
          "updated_at": ""
        }
      ],
      "play_lines": [
        {
          "source": "bfzy",
          "name": "bfzym3u8",
          "url": "HD$https://s3.bfllvip.com/video/NBAxiajiliansaiqishiVShuosai20260713/a034cadce9c2/index.m3u8"
        }
      ],
      "semantic_tags": "quality hd 清晰度 高清",
      "snapshot_filter_evidence": "catalog-derived"
    },
    {
      "vod_id": "agg_W3sicyI6ImJmenkiLCJpZCI6IjE1MTU4MiJ9XQ",
      "type_id": "55",
      "type_id_1": 53,
      "group_id": 0,
      "vod_name": "NBA夏季联赛：热火VS湖人20260706",
      "vod_sub": "",
      "vod_en": "NBAxiajiliansairehuoVShuren20260706",
      "vod_status": 1,
      "vod_letter": "N",
      "vod_color": "",
      "vod_tag": "",
      "vod_class": "篮球",
      "vod_pic": "https://img.picbf.com/upload/vod/20260707-1/d5ad8b35efc522bc681dfabac3384014.jpg",
      "vod_pic_thumb": "",
      "vod_pic_slide": "",
      "vod_pic_screenshot": "",
      "vod_actor": "",
      "vod_director": "",
      "vod_writer": "",
      "vod_behind": "",
      "vod_blurb": "暂无剧情介绍",
      "vod_remarks": "更新至HD",
      "vod_pubdate": "",
      "vod_total": "0",
      "vod_serial": "0",
      "vod_tv": "",
      "vod_weekday": "",
      "vod_area": "",
      "vod_lang": "",
      "vod_year": "0",
      "vod_version": "",
      "vod_state": "",
      "vod_author": "",
      "vod_jumpurl": "",
      "vod_tpl": "",
      "vod_tpl_play": "",
      "vod_tpl_down": "",
      "vod_isend": 0,
      "vod_lock": 0,
      "vod_level": 0,
      "vod_copyright": 0,
      "vod_points": 0,
      "vod_points_play": 0,
      "vod_points_down": 0,
      "vod_hits": 791,
      "vod_hits_day": 763,
      "vod_hits_week": 35,
      "vod_hits_month": 307,
      "vod_duration": "",
      "vod_up": 205,
      "vod_down": 485,
      "vod_score": "4.0",
      "vod_score_all": 904,
      "vod_score_num": 226,
      "vod_time": "2026-07-07 14:41:40",
      "vod_time_add": "1783406496",
      "vod_time_hits": 0,
      "vod_time_make": 0,
      "vod_trysee": 0,
      "vod_douban_id": 0,
      "vod_douban_score": "0.0",
      "vod_reurl": "",
      "vod_rel_vod": "",
      "vod_rel_art": "",
      "vod_pwd": "",
      "vod_pwd_url": "",
      "vod_pwd_play": "",
      "vod_pwd_play_url": "",
      "vod_pwd_down": "",
      "vod_pwd_down_url": "",
      "vod_content": "暂无简介，敬请期待",
      "vod_play_from": "bfzym3u8",
      "vod_play_server": "",
      "vod_play_note": "",
      "vod_play_url": "HD$https://s3.bfllvip.com/video/NBAxiajiliansairehuoVShuren20260706/6231780e955a/index.m3u8",
      "vod_down_from": "",
      "vod_down_server": "",
      "vod_down_note": "",
      "vod_down_url": "",
      "vod_plot": 0,
      "vod_plot_name": "",
      "vod_plot_detail": "",
      "type_name": "篮球",
      "source_category_id": "8",
      "source_category_name": "篮球",
      "_sourceSlug": "bfzy",
      "_sourceShort": "暴风",
      "source_url": "https://bfzyapi.com/api.php/provide/vod/",
      "canonical_id": "meta:nba%E5%A4%8F%E5%AD%A3%E8%81%94%E8%B5%9B%E7%83%AD%E7%81%ABvs%E6%B9%96%E4%BA%BA20260706:0:0:unknown",
      "primary_category": "knowledge",
      "movie_release_channel": "unknown",
      "classification_evidence": [
        {
          "source": "source_category_id",
          "priority": 1,
          "category": "knowledge",
          "field": "source_category_id",
          "value": "8",
          "signal": "knowledge"
        }
      ],
      "classification_confidence": 0.99,
      "classification_confidence_level": "high",
      "classification_confidence_score": 0.99,
      "source_candidates": [
        {
          "source": "bfzy",
          "id": "151582",
          "url": "https://bfzyapi.com/api.php/provide/vod/",
          "updated_at": ""
        }
      ],
      "play_lines": [
        {
          "source": "bfzy",
          "name": "bfzym3u8",
          "url": "HD$https://s3.bfllvip.com/video/NBAxiajiliansairehuoVShuren20260706/6231780e955a/index.m3u8"
        }
      ],
      "semantic_tags": "quality hd 清晰度 高清",
      "snapshot_filter_evidence": "catalog-derived"
    },
    {
      "vod_id": "agg_W3sicyI6ImJmenkiLCJpZCI6IjE1MTU0NyJ9XQ",
      "type_id": "55",
      "type_id_1": 53,
      "group_id": 0,
      "vod_name": "NBA夏季联赛：热火VS马刺20260704",
      "vod_sub": "",
      "vod_en": "NBAxiajiliansairehuoVSmaci20260704",
      "vod_status": 1,
      "vod_letter": "N",
      "vod_color": "",
      "vod_tag": "",
      "vod_class": "篮球",
      "vod_pic": "https://img.picbf.com/upload/vod/20260706-1/351fa0a307b190a1697540c5816fc66a.jpg",
      "vod_pic_thumb": "",
      "vod_pic_slide": "",
      "vod_pic_screenshot": "",
      "vod_actor": "",
      "vod_director": "",
      "vod_writer": "",
      "vod_behind": "",
      "vod_blurb": "暂无剧情介绍",
      "vod_remarks": "更新至HD",
      "vod_pubdate": "",
      "vod_total": "0",
      "vod_serial": "0",
      "vod_tv": "",
      "vod_weekday": "",
      "vod_area": "",
      "vod_lang": "",
      "vod_year": "0",
      "vod_version": "",
      "vod_state": "",
      "vod_author": "",
      "vod_jumpurl": "",
      "vod_tpl": "",
      "vod_tpl_play": "",
      "vod_tpl_down": "",
      "vod_isend": 0,
      "vod_lock": 0,
      "vod_level": 0,
      "vod_copyright": 0,
      "vod_points": 0,
      "vod_points_play": 0,
      "vod_points_down": 0,
      "vod_hits": 557,
      "vod_hits_day": 239,
      "vod_hits_week": 439,
      "vod_hits_month": 320,
      "vod_duration": "",
      "vod_up": 58,
      "vod_down": 703,
      "vod_score": "4.0",
      "vod_score_all": 2280,
      "vod_score_num": 570,
      "vod_time": "2026-07-07 04:02:01",
      "vod_time_add": "1783346526",
      "vod_time_hits": 0,
      "vod_time_make": 0,
      "vod_trysee": 0,
      "vod_douban_id": 0,
      "vod_douban_score": "0.0",
      "vod_reurl": "",
      "vod_rel_vod": "",
      "vod_rel_art": "",
      "vod_pwd": "",
      "vod_pwd_url": "",
      "vod_pwd_play": "",
      "vod_pwd_play_url": "",
      "vod_pwd_down": "",
      "vod_pwd_down_url": "",
      "vod_content": "暂无简介，敬请期待",
      "vod_play_from": "bfzym3u8",
      "vod_play_server": "",
      "vod_play_note": "",
      "vod_play_url": "HD$https://s3.bfllvip.com/video/NBAxiajiliansairehuoVSmaci20260704/0ff4dc3cdaed/index.m3u8",
      "vod_down_from": "",
      "vod_down_server": "",
      "vod_down_note": "",
      "vod_down_url": "",
      "vod_plot": 0,
      "vod_plot_name": "",
      "vod_plot_detail": "",
      "type_name": "篮球",
      "source_category_id": "8",
      "source_category_name": "篮球",
      "_sourceSlug": "bfzy",
      "_sourceShort": "暴风",
      "source_url": "https://bfzyapi.com/api.php/provide/vod/",
      "canonical_id": "meta:nba%E5%A4%8F%E5%AD%A3%E8%81%94%E8%B5%9B%E7%83%AD%E7%81%ABvs%E9%A9%AC%E5%88%BA20260704:0:0:unknown",
      "primary_category": "knowledge",
      "movie_release_channel": "unknown",
      "classification_evidence": [
        {
          "source": "source_category_id",
          "priority": 1,
          "category": "knowledge",
          "field": "source_category_id",
          "value": "8",
          "signal": "knowledge"
        }
      ],
      "classification_confidence": 0.99,
      "classification_confidence_level": "high",
      "classification_confidence_score": 0.99,
      "source_candidates": [
        {
          "source": "bfzy",
          "id": "151547",
          "url": "https://bfzyapi.com/api.php/provide/vod/",
          "updated_at": ""
        }
      ],
      "play_lines": [
        {
          "source": "bfzy",
          "name": "bfzym3u8",
          "url": "HD$https://s3.bfllvip.com/video/NBAxiajiliansairehuoVSmaci20260704/0ff4dc3cdaed/index.m3u8"
        }
      ],
      "semantic_tags": "quality hd 清晰度 高清",
      "snapshot_filter_evidence": "catalog-derived"
    },
    {
      "vod_id": "agg_W3sicyI6ImJmenkiLCJpZCI6IjE1MjU5MiJ9XQ",
      "type_id": "55",
      "type_id_1": 53,
      "group_id": 0,
      "vod_name": "NBA夏季联赛：热火VS魔术20260712",
      "vod_sub": "",
      "vod_en": "NBAxiajiliansairehuoVSmoshu20260712",
      "vod_status": 1,
      "vod_letter": "N",
      "vod_color": "",
      "vod_tag": "",
      "vod_class": "篮球",
      "vod_pic": "https://img.picbf.com/upload/vod/20260715-1/dadc92d8bc9980c9ebbe180f9a183b77.jpg",
      "vod_pic_thumb": "",
      "vod_pic_slide": "",
      "vod_pic_screenshot": "",
      "vod_actor": "",
      "vod_director": "",
      "vod_writer": "",
      "vod_behind": "",
      "vod_blurb": "暂无剧情介绍",
      "vod_remarks": "更新至HD",
      "vod_pubdate": "",
      "vod_total": "0",
      "vod_serial": "0",
      "vod_tv": "",
      "vod_weekday": "",
      "vod_area": "",
      "vod_lang": "",
      "vod_year": "0",
      "vod_version": "",
      "vod_state": "",
      "vod_author": "",
      "vod_jumpurl": "",
      "vod_tpl": "",
      "vod_tpl_play": "",
      "vod_tpl_down": "",
      "vod_isend": 0,
      "vod_lock": 0,
      "vod_level": 0,
      "vod_copyright": 0,
      "vod_points": 0,
      "vod_points_play": 0,
      "vod_points_down": 0,
      "vod_hits": 166,
      "vod_hits_day": 851,
      "vod_hits_week": 871,
      "vod_hits_month": 459,
      "vod_duration": "",
      "vod_up": 512,
      "vod_down": 828,
      "vod_score": "4.0",
      "vod_score_all": 1612,
      "vod_score_num": 403,
      "vod_time": "2026-07-15 16:03:17",
      "vod_time_add": "1784102595",
      "vod_time_hits": 0,
      "vod_time_make": 0,
      "vod_trysee": 0,
      "vod_douban_id": 0,
      "vod_douban_score": "0.0",
      "vod_reurl": "",
      "vod_rel_vod": "",
      "vod_rel_art": "",
      "vod_pwd": "",
      "vod_pwd_url": "",
      "vod_pwd_play": "",
      "vod_pwd_play_url": "",
      "vod_pwd_down": "",
      "vod_pwd_down_url": "",
      "vod_content": "暂无简介，敬请期待",
      "vod_play_from": "bfzym3u8",
      "vod_play_server": "",
      "vod_play_note": "",
      "vod_play_url": "HD$https://s3.bfllvip.com/video/NBAxiajiliansairehuoVSmoshu20260712/3233c5598cd5/index.m3u8",
      "vod_down_from": "",
      "vod_down_server": "",
      "vod_down_note": "",
      "vod_down_url": "",
      "vod_plot": 0,
      "vod_plot_name": "",
      "vod_plot_detail": "",
      "type_name": "篮球",
      "source_category_id": "8",
      "source_category_name": "篮球",
      "_sourceSlug": "bfzy",
      "_sourceShort": "暴风",
      "source_url": "https://bfzyapi.com/api.php/provide/vod/",
      "canonical_id": "meta:nba%E5%A4%8F%E5%AD%A3%E8%81%94%E8%B5%9B%E7%83%AD%E7%81%ABvs%E9%AD%94%E6%9C%AF20260712:0:0:unknown",
      "primary_category": "knowledge",
      "movie_release_channel": "unknown",
      "classification_evidence": [
        {
          "source": "source_category_id",
          "priority": 1,
          "category": "knowledge",
          "field": "source_category_id",
          "value": "8",
          "signal": "knowledge"
        }
      ],
      "classification_confidence": 0.99,
      "classification_confidence_level": "high",
      "classification_confidence_score": 0.99,
      "source_candidates": [
        {
          "source": "bfzy",
          "id": "152592",
          "url": "https://bfzyapi.com/api.php/provide/vod/",
          "updated_at": ""
        }
      ],
      "play_lines": [
        {
          "source": "bfzy",
          "name": "bfzym3u8",
          "url": "HD$https://s3.bfllvip.com/video/NBAxiajiliansairehuoVSmoshu20260712/3233c5598cd5/index.m3u8"
        }
      ],
      "semantic_tags": "quality hd 清晰度 高清",
      "snapshot_filter_evidence": "catalog-derived"
    }
  ],
  "content_revision": "snapshot-b693cb2ce1ea39323d02",
  "snapshot_mode": "generated-filter-pack",
  "snapshot_filter": {
    "key": "quality",
    "value": "hd"
  }
}